Workbook

Sheet MOVIMIENTOS
A1: AGRO PACAYALES · PLANTA CAMOTE 2026 | MOVIMIENTOS — registra aquí un evento por fila
A2: Única hoja que llenas: escribe la fecha como 24-7 (saldrá "vie 24-07" solita) + Tipo (lista) + Calidad + Unidad (jabas/sacos/kg) + Cantidad → los Kg salen solos. Si registras en kg (muestras, malogrado, reproceso, otras salidas) los Kg = Cantidad. Guía/ticket y nota al final. KARDEX, SALDO DIARIO y RESUMEN se arman solos.
A4: Fecha | B4: Tipo | C4: Calidad | D4: Unidad | E4: Cantidad | F4: Kg | G4: N° Guía / Ticket | H4: Observación
A5: 46214 | B5: AJUSTE | C5: A | D5: jabas | E5: 2 | F5: =IF($B5="","",IF($D5="kg",N($E5),IF($D5="sacos",N($E5)*97,IF($D5="jabas",N($E5)*IFERROR(VLOOKUP($C5,LISTAS!$A$2:$B$12,2,0),0),"")))) -> 30 | I5: =N($F5) -> 30
A6: 46214 | B6: AJUSTE | C6: M | D6: jabas | E6: 1 | F6: =IF($B6="","",IF($D6="kg",N($E6),IF($D6="sacos",N($E6)*97,IF($D6="jabas",N($E6)*IFERROR(VLOOKUP($C6,LISTAS!$A$2:$B$12,2,0),0),"")))) -> 17 | I6: =N($F6) -> 17
A7: 46214 | B7: SALDO INICIAL | C7: M | D7: jabas | E7: 7 | F7: =IF($B7="","",IF($D7="kg",N($E7),IF($D7="sacos",N($E7)*97,IF($D7="jabas",N($E7)*IFERROR(VLOOKUP($C7,LISTAS!$A$2:$B$12,2,0),0),"")))) -> 119 | I7: =N($F7) -> 119
A8: 46214 | B8: SALDO INICIAL | C8: Chancho | D8: sacos | E8: 20 | F8: =IF($B8="","",IF($D8="kg",N($E8),IF($D8="sacos",N($E8)*97,IF($D8="jabas",N($E8)*IFERROR(VLOOKUP($C8,LISTAS!$A$2:$B$12,2,0),0),"")))) -> 1940 | I8: =N($F8) -> 1940
A9: 46215 | B9: COMPRA | C9: — | D9: sacos | E9: 30 | F9: =IF($B9="","",IF($D9="kg",N($E9),IF($D9="sacos",N($E9)*97,IF($D9="jabas",N($E9)*IFERROR(VLOOKUP($C9,LISTAS!$A$2:$B$12,2,0),0),"")))) -> 2910 | H9: peso aprox 95 kg/saco | I9: =N($F9) -> 2910
A10: 46215 | B10: PROCESO | C10: A | D10: jabas | E10: 59 | F10: =IF($B10="","",IF($D10="kg",N($E10),IF($D10="sacos",N($E10)*97,IF($D10="jabas",N($E10)*IFERROR(VLOOKUP($C10,LISTAS!$A$2:$B$12,2,0),0),"")))) -> 885 | I10: =N($F10) -> 885
A11: 46215 | B11: PROCESO | C11: P | D11: jabas | E11: 11 | F11: =IF($B11="","",IF($D11="kg",N($E11),IF($D11="sacos",N($E11)*97,IF($D11="jabas",N($E11)*IFERROR(VLOOKUP($C11,LISTAS!$A$2:$B$12,2,0),0),"")))) -> 198 | I11: =N($F11) -> 198
A12: 46215 | B12: PROCESO | C12: C | D12: jabas | E12: 12 | F12: =IF($B12="","",IF($D12="kg",N($E12),IF($D12="sacos",N($E12)*97,IF($D12="jabas",N($E12)*IFERROR(VLOOKUP($C12,LISTAS!$A$2:$B$12,2,0),0),"")))) -> 204 | I12: =N($F12) -> 204
A13: 46215 | B13: PROCESO | C13: M | D13: jabas | E13: 64 | F13: =IF($B13="","",IF($D13="kg",N($E13),IF($D13="sacos",N($E13)*97,IF($D13="jabas",N($E13)*IFERROR(VLOOKUP($C13,LISTAS!$A$2:$B$12,2,0),0),"")))) -> 1088 | I13: =N($F13) -> 1088
A14: 46215 | B14: PROCESO | C14: Chancho | D14: sacos | E14: 6 | F14: =IF($B14="","",IF($D14="kg",N($E14),IF($D14="sacos",N($E14)*97,IF($D14="jabas",N($E14)*IFERROR(VLOOKUP($C14,LISTAS!$A$2:$B$12,2,0),0),"")))) -> 582 | I14: =N($F14) -> 582
A15: 46215 | B15: ENVÍO A SUPESA | C15: A | D15: jabas | E15: 67 | F15: =IF($B15="","",IF($D15="kg",N($E15),IF($D15="sacos",N($E15)*97,IF($D15="jabas",N($E15)*IFERROR(VLOOKUP($C15,LISTAS!$A$2:$B$12,2,0),0),"")))) -> 1005 | G15: 2977 | I15: =N($F15) -> 1005
A16: 46215 | B16: ENVÍO A SUPESA | C16: P | D16: jabas | E16: 11 | F16: =IF($B16="","",IF($D16="kg",N($E16),IF($D16="sacos",N($E16)*97,IF($D16="jabas",N($E16)*IFERROR(VLOOKUP($C16,LISTAS!$A$2:$B$12,2,0),0),"")))) -> 198 | G16: 2977 | I16: =N($F16) -> 198
A17: 46215 | B17: ENVÍO A SUPESA | C17: C | D17: jabas | E17: 12 | F17: =IF($B17="","",IF($D17="kg",N($E17),IF($D17="sacos",N($E17)*97,IF($D17="jabas",N($E17)*IFERROR(VLOOKUP($C17,LISTAS!$A$2:$B$12,2,0),0),"")))) -> 204 | G17: 2977 | I17: =N($F17) -> 204
A18: 46215 | B18: ENVÍO A SUPESA | C18: M | D18: jabas | E18: 42 | F18: =IF($B18="","",IF($D18="kg",N($E18),IF($D18="sacos",N($E18)*97,IF($D18="jabas",N($E18)*IFERROR(VLOOKUP($C18,LISTAS!$A$2:$B$12,2,0),0),"")))) -> 714 | G18: 2977 | I18: =N($F18) -> 714
A19: 46216 | B19: COMPRA | C19: — | D19: sacos | E19: 40 | F19: =IF($B19="","",IF($D19="kg",N($E19),IF($D19="sacos",N($E19)*97,IF($D19="jabas",N($E19)*IFERROR(VLOOKUP($C19,LISTAS!$A$2:$B$12,2,0),0),"")))) -> 3880 | H19: peso aprox 95 kg/saco | I19: =N($F19) -> 3880
A20: 46216 | B20: PROCESO | C20: A | D20: jabas | E20: 107 | F20: =IF($B20="","",IF($D20="kg",N($E20),IF($D20="sacos",N($E20)*97,IF($D20="jabas",N($E20)*IFERROR(VLOOKUP($C20,LISTAS!$A$2:$B$12,2,0),0),"")))) -> 1605 | I20: =N($F20) -> 1605
A21: 46216 | B21: PROCESO | C21: P | D21: jabas | E21: 11 | F21: =IF($B21="","",IF($D21="kg",N($E21),IF($D21="sacos",N($E21)*97,IF($D21="jabas",N($E21)*IFERROR(VLOOKUP($C21,LISTAS!$A$2:$B$12,2,0),0),"")))) -> 198 | I21: =N($F21) -> 198
A22: 46216 | B22: PROCESO | C22: C | D22: jabas | E22: 12 | F22: =IF($B22="","",IF($D22="kg",N($E22),IF($D22="sacos",N($E22)*97,IF($D22="jabas",N($E22)*IFERROR(VLOOKUP($C22,LISTAS!$A$2:$B$12,2,0),0),"")))) -> 204 | I22: =N($F22) -> 204
A23: 46216 | B23: PROCESO | C23: M | D23: jabas | E23: 110 | F23: =IF($B23="","",IF($D23="kg",N($E23),IF($D23="sacos",N($E23)*97,IF($D23="jabas",N($E23)*IFERROR(VLOOKUP($C23,LISTAS!$A$2:$B$12,2,0),0),"")))) -> 1870 | I23: =N($F23) -> 1870
A24: 46216 | B24: PROCESO | C24: Chancho | D24: sacos | E24: 2 | F24: =IF($B24="","",IF($D24="kg",N($E24),IF($D24="sacos",N($E24)*97,IF($D24="jabas",N($E24)*IFERROR(VLOOKUP($C24,LISTAS!$A$2:$B$12,2,0),0),"")))) -> 194 | I24: =N($F24) -> 194
A25: 46216 | B25: ENVÍO A SUPESA | C25: A | D25: jabas | E25: 67 | F25: =IF($B25="","",IF($D25="kg",N($E25),IF($D25="sacos",N($E25)*97,IF($D25="jabas",N($E25)*IFERROR(VLOOKUP($C25,LISTAS!$A$2:$B$12,2,0),0),"")))) -> 1005 | G25: 2980 | I25: =N($F25) -> 1005
A26: 46216 | B26: ENVÍO A SUPESA | C26: P | D26: jabas | E26: 11 | F26: =IF($B26="","",IF($D26="kg",N($E26),IF($D26="sacos",N($E26)*97,IF($D26="jabas",N($E26)*IFERROR(VLOOKUP($C26,LISTAS!$A$2:$B$12,2,0),0),"")))) -> 198 | G26: 2980 | I26: =N($F26) -> 198
A27: 46216 | B27: ENVÍO A SUPESA | C27: C | D27: jabas | E27: 12 | F27: =IF($B27="","",IF($D27="kg",N($E27),IF($D27="sacos",N($E27)*97,IF($D27="jabas",N($E27)*IFERROR(VLOOKUP($C27,LISTAS!$A$2:$B$12,2,0),0),"")))) -> 204 | G27: 2980 | I27: =N($F27) -> 204
A28: 46216 | B28: ENVÍO A SUPESA | C28: M | D28: jabas | E28: 97 | F28: =IF($B28="","",IF($D28="kg",N($E28),IF($D28="sacos",N($E28)*97,IF($D28="jabas",N($E28)*IFERROR(VLOOKUP($C28,LISTAS!$A$2:$B$12,2,0),0),"")))) -> 1649 | G28: 2980 | I28: =N($F28) -> 1649
A29: 46217 | B29: COMPRA | C29: — | D29: sacos | E29: 40 | F29: =IF($B29="","",IF($D29="kg",N($E29),IF($D29="sacos",N($E29)*97,IF($D29="jabas",N($E29)*IFERROR(VLOOKUP($C29,LISTAS!$A$2:$B$12,2,0),0),"")))) -> 3880 | H29: peso aprox 95 kg/saco | I29: =N($F29) -> 3880
A30: 46217 | B30: PROCESO | C30: A | D30: jabas | E30: 45 | F30: =IF($B30="","",IF($D30="kg",N($E30),IF($D30="sacos",N($E30)*97,IF($D30="jabas",N($E30)*IFERROR(VLOOKUP($C30,LISTAS!$A$2:$B$12,2,0),0),"")))) -> 675 | I30: =N($F30) -> 675
A31: 46217 | B31: PROCESO | C31: P | D31: jabas | E31: 11 | F31: =IF($B31="","",IF($D31="kg",N($E31),IF($D31="sacos",N($E31)*97,IF($D31="jabas",N($E31)*IFERROR(VLOOKUP($C31,LISTAS!$A$2:$B$12,2,0),0),"")))) -> 198 | I31: =N($F31) -> 198
A32: 46217 | B32: PROCESO | C32: C | D32: jabas | E32: 12 | F32: =IF($B32="","",IF($D32="kg",N($E32),IF($D32="sacos",N($E32)*97,IF($D32="jabas",N($E32)*IFERROR(VLOOKUP($C32,LISTAS!$A$2:$B$12,2,0),0),"")))) -> 204 | I32: =N($F32) -> 204
A33: 46217 | B33: PROCESO | C33: M | D33: jabas | E33: 121 | F33: =IF($B33="","",IF($D33="kg",N($E33),IF($D33="sacos",N($E33)*97,IF($D33="jabas",N($E33)*IFERROR(VLOOKUP($C33,LISTAS!$A$2:$B$12,2,0),0),"")))) -> 2057 | I33: =N($F33) -> 2057
A34: 46217 | B34: PROCESO | C34: Chancho | D34: sacos | E34: 7 | F34: =IF($B34="","",IF($D34="kg",N($E34),IF($D34="sacos",N($E34)*97,IF($D34="jabas",N($E34)*IFERROR(VLOOKUP($C34,LISTAS!$A$2:$B$12,2,0),0),"")))) -> 679 | I34: =N($F34) -> 679
A35: 46217 | B35: ENVÍO A SUPESA | C35: A | D35: jabas | E35: 67 | F35: =IF($B35="","",IF($D35="kg",N($E35),IF($D35="sacos",N($E35)*97,IF($D35="jabas",N($E35)*IFERROR(VLOOKUP($C35,LISTAS!$A$2:$B$12,2,0),0),"")))) -> 1005 | G35: 2984 | I35: =N($F35) -> 1005
A36: 46217 | B36: ENVÍO A SUPESA | C36: P | D36: jabas | E36: 11 | F36: =IF($B36="","",IF($D36="kg",N($E36),IF($D36="sacos",N($E36)*97,IF($D36="jabas",N($E36)*IFERROR(VLOOKUP($C36,LISTAS!$A$2:$B$12,2,0),0),"")))) -> 198 | G36: 2984 | I36: =N($F36) -> 198
A37: 46217 | B37: ENVÍO A SUPESA | C37: C | D37: jabas | E37: 12 | F37: =IF($B37="","",IF($D37="kg",N($E37),IF($D37="sacos",N($E37)*97,IF($D37="jabas",N($E37)*IFERROR(VLOOKUP($C37,LISTAS!$A$2:$B$12,2,0),0),"")))) -> 204 | G37: 2984 | I37: =N($F37) -> 204
A38: 46217 | B38: ENVÍO A SUPESA | C38: M | D38: jabas | E38: 116 | F38: =IF($B38="","",IF($D38="kg",N($E38),IF($D38="sacos",N($E38)*97,IF($D38="jabas",N($E38)*IFERROR(VLOOKUP($C38,LISTAS!$A$2:$B$12,2,0),0),"")))) -> 1972 | G38: 2984 | I38: =N($F38) -> 1972
A39: 46218 | B39: COMPRA | C39: — | D39: sacos | E39: 40 | F39: =IF($B39="","",IF($D39="kg",N($E39),IF($D39="sacos",N($E39)*97,IF($D39="jabas",N($E39)*IFERROR(VLOOKUP($C39,LISTAS!$A$2:$B$12,2,0),0),"")))) -> 3880 | H39: peso aprox 95 kg/saco | I39: =N($F39) -> 3880
A40: 46218 | B40: PROCESO | C40: A | D40: jabas | E40: 79 | F40: =IF($B40="","",IF($D40="kg",N($E40),IF($D40="sacos",N($E40)*97,IF($D40="jabas",N($E40)*IFERROR(VLOOKUP($C40,LISTAS!$A$2:$B$12,2,0),0),"")))) -> 1185 | I40: =N($F40) -> 1185
A41: 46218 | B41: PROCESO | C41: P | D41: jabas | E41: 22 | F41: =IF($B41="","",IF($D41="kg",N($E41),IF($D41="sacos",N($E41)*97,IF($D41="jabas",N($E41)*IFERROR(VLOOKUP($C41,LISTAS!$A$2:$B$12,2,0),0),"")))) -> 396 | I41: =N($F41) -> 396
A42: 46218 | B42: PROCESO | C42: C | D42: jabas | E42: 21 | F42: =IF($B42="","",IF($D42="kg",N($E42),IF($D42="sacos",N($E42)*97,IF($D42="jabas",N($E42)*IFERROR(VLOOKUP($C42,LISTAS!$A$2:$B$12,2,0),0),"")))) -> 357 | I42: =N($F42) -> 357
A43: 46218 | B43: PROCESO | C43: M | D43: jabas | E43: 83 | F43: =IF($B43="","",IF($D43="kg",N($E43),IF($D43="sacos",N($E43)*97,IF($D43="jabas",N($E43)*IFERROR(VLOOKUP($C43,LISTAS!$A$2:$B$12,2,0),0),"")))) -> 1411 | I43: =N($F43) -> 1411
A44: 46218 | B44: PROCESO | C44: Chancho | D44: sacos | E44: 5 | F44: =IF($B44="","",IF($D44="kg",N($E44),IF($D44="sacos",N($E44)*97,IF($D44="jabas",N($E44)*IFERROR(VLOOKUP($C44,LISTAS!$A$2:$B$12,2,0),0),"")))) -> 485 | I44: =N($F44) -> 485
A45: 46218 | B45: ENVÍO A SUPESA | C45: A | D45: jabas | E45: 67 | F45: =IF($B45="","",IF($D45="kg",N($E45),IF($D45="sacos",N($E45)*97,IF($D45="jabas",N($E45)*IFERROR(VLOOKUP($C45,LISTAS!$A$2:$B$12,2,0),0),"")))) -> 1005 | G45: 2986 | I45: =N($F45) -> 1005
A46: 46218 | B46: ENVÍO A SUPESA | C46: P | D46: jabas | E46: 11 | F46: =IF($B46="","",IF($D46="kg",N($E46),IF($D46="sacos",N($E46)*97,IF($D46="jabas",N($E46)*IFERROR(VLOOKUP($C46,LISTAS!$A$2:$B$12,2,0),0),"")))) -> 198 | G46: 2986 | I46: =N($F46) -> 198
A47: 46218 | B47: ENVÍO A SUPESA | C47: C | D47: jabas | E47: 9 | F47: =IF($B47="","",IF($D47="kg",N($E47),IF($D47="sacos",N($E47)*97,IF($D47="jabas",N($E47)*IFERROR(VLOOKUP($C47,LISTAS!$A$2:$B$12,2,0),0),"")))) -> 153 | G47: 2986 | I47: =N($F47) -> 153
A48: 46218 | B48: ENVÍO A SUPESA | C48: M | D48: jabas | E48: 95 | F48: =IF($B48="","",IF($D48="kg",N($E48),IF($D48="sacos",N($E48)*97,IF($D48="jabas",N($E48)*IFERROR(VLOOKUP($C48,LISTAS!$A$2:$B$12,2,0),0),"")))) -> 1615 | G48: 2986 | I48: =N($F48) -> 1615
A49: 46218 | B49: VENTA CHANCHO | C49: Chancho | D49: sacos | E49: 35 | F49: =IF($B49="","",IF($D49="kg",N($E49),IF($D49="sacos",N($E49)*97,IF($D49="jabas",N($E49)*IFERROR(VLOOKUP($C49,LISTAS!$A$2:$B$12,2,0),0),"")))) -> 3395 | G49: TCK002-724 | I49: =N($F49) -> 3395
A50: 46219 | B50: COMPRA | C50: — | D50: sacos | E50: 40 | F50: =IF($B50="","",IF($D50="kg",N($E50),IF($D50="sacos",N($E50)*97,IF($D50="jabas",N($E50)*IFERROR(VLOOKUP($C50,LISTAS!$A$2:$B$12,2,0),0),"")))) -> 3880 | H50: peso aprox 95 kg/saco | I50: =N($F50) -> 3880
A51: 46219 | B51: PROCESO | C51: A | D51: jabas | E51: 68 | F51: =IF($B51="","",IF($D51="kg",N($E51),IF($D51="sacos",N($E51)*97,IF($D51="jabas",N($E51)*IFERROR(VLOOKUP($C51,LISTAS!$A$2:$B$12,2,0),0),"")))) -> 1020 | I51: =N($F51) -> 1020
A52: 46219 | B52: PROCESO | C52: P | D52: jabas | E52: 11 | F52: =IF($B52="","",IF($D52="kg",N($E52),IF($D52="sacos",N($E52)*97,IF($D52="jabas",N($E52)*IFERROR(VLOOKUP($C52,LISTAS!$A$2:$B$12,2,0),0),"")))) -> 198 | I52: =N($F52) -> 198
A53: 46219 | B53: PROCESO | C53: C | D53: jabas | E53: 12 | F53: =IF($B53="","",IF($D53="kg",N($E53),IF($D53="sacos",N($E53)*97,IF($D53="jabas",N($E53)*IFERROR(VLOOKUP($C53,LISTAS!$A$2:$B$12,2,0),0),"")))) -> 204 | I53: =N($F53) -> 204
A54: 46219 | B54: PROCESO | C54: M | D54: jabas | E54: 116 | F54: =IF($B54="","",IF($D54="kg",N($E54),IF($D54="sacos",N($E54)*97,IF($D54="jabas",N($E54)*IFERROR(VLOOKUP($C54,LISTAS!$A$2:$B$12,2,0),0),"")))) -> 1972 | I54: =N($F54) -> 1972
A55: 46219 | B55: PROCESO | C55: Chancho | D55: sacos | E55: 4 | F55: =IF($B55="","",IF($D55="kg",N($E55),IF($D55="sacos",N($E55)*97,IF($D55="jabas",N($E55)*IFERROR(VLOOKUP($C55,LISTAS!$A$2:$B$12,2,0),0),"")))) -> 388 | I55: =N($F55) -> 388
A56: 46219 | B56: ENVÍO A SUPESA | C56: A | D56: jabas | E56: 63 | F56: =IF($B56="","",IF($D56="kg",N($E56),IF($D56="sacos",N($E56)*97,IF($D56="jabas",N($E56)*IFERROR(VLOOKUP($C56,LISTAS!$A$2:$B$12,2,0),0),"")))) -> 945 | G56: 2992 | I56: =N($F56) -> 945
A57: 46219 | B57: ENVÍO A SUPESA | C57: P | D57: jabas | E57: 11 | F57: =IF($B57="","",IF($D57="kg",N($E57),IF($D57="sacos",N($E57)*97,IF($D57="jabas",N($E57)*IFERROR(VLOOKUP($C57,LISTAS!$A$2:$B$12,2,0),0),"")))) -> 198 | G57: 2992 | I57: =N($F57) -> 198
A58: 46219 | B58: ENVÍO A SUPESA | C58: C | D58: jabas | E58: 12 | F58: =IF($B58="","",IF($D58="kg",N($E58),IF($D58="sacos",N($E58)*97,IF($D58="jabas",N($E58)*IFERROR(VLOOKUP($C58,LISTAS!$A$2:$B$12,2,0),0),"")))) -> 204 | G58: 2992 | I58: =N($F58) -> 204
A59: 46219 | B59: ENVÍO A SUPESA | C59: M | D59: jabas | E59: 115 | F59: =IF($B59="","",IF($D59="kg",N($E59),IF($D59="sacos",N($E59)*97,IF($D59="jabas",N($E59)*IFERROR(VLOOKUP($C59,LISTAS!$A$2:$B$12,2,0),0),"")))) -> 1955 | G59: 2992 | I59: =N($F59) -> 1955
A60: 46220 | B60: COMPRA | C60: — | D60: sacos | E60: 60 | F60: =IF($B60="","",IF($D60="kg",N($E60),IF($D60="sacos",N($E60)*97,IF($D60="jabas",N($E60)*IFERROR(VLOOKUP($C60,LISTAS!$A$2:$B$12,2,0),0),"")))) -> 5820 | H60: peso aprox 95 kg/saco | I60: =N($F60) -> 5820
A61: 46220 | B61: PROCESO | C61: A | D61: jabas | E61: 99 | F61: =IF($B61="","",IF($D61="kg",N($E61),IF($D61="sacos",N($E61)*97,IF($D61="jabas",N($E61)*IFERROR(VLOOKUP($C61,LISTAS!$A$2:$B$12,2,0),0),"")))) -> 1485 | I61: =N($F61) -> 1485
A62: 46220 | B62: PROCESO | C62: P | D62: jabas | E62: 4 | F62: =IF($B62="","",IF($D62="kg",N($E62),IF($D62="sacos",N($E62)*97,IF($D62="jabas",N($E62)*IFERROR(VLOOKUP($C62,LISTAS!$A$2:$B$12,2,0),0),"")))) -> 72 | I62: =N($F62) -> 72
A63: 46220 | B63: PROCESO | C63: C | D63: jabas | E63: 9 | F63: =IF($B63="","",IF($D63="kg",N($E63),IF($D63="sacos",N($E63)*97,IF($D63="jabas",N($E63)*IFERROR(VLOOKUP($C63,LISTAS!$A$2:$B$12,2,0),0),"")))) -> 153 | I63: =N($F63) -> 153
A64: 46220 | B64: PROCESO | C64: M | D64: jabas | E64: 178 | F64: =IF($B64="","",IF($D64="kg",N($E64),IF($D64="sacos",N($E64)*97,IF($D64="jabas",N($E64)*IFERROR(VLOOKUP($C64,LISTAS!$A$2:$B$12,2,0),0),"")))) -> 3026 | I64: =N($F64) -> 3026
A65: 46220 | B65: PROCESO | C65: Chancho | D65: sacos | E65: 10 | F65: =IF($B65="","",IF($D65="kg",N($E65),IF($D65="sacos",N($E65)*97,IF($D65="jabas",N($E65)*IFERROR(VLOOKUP($C65,LISTAS!$A$2:$B$12,2,0),0),"")))) -> 970 | I65: =N($F65) -> 970
A66: 46220 | B66: ENVÍO A SUPESA | C66: A | D66: jabas | E66: 67 | F66: =IF($B66="","",IF($D66="kg",N($E66),IF($D66="sacos",N($E66)*97,IF($D66="jabas",N($E66)*IFERROR(VLOOKUP($C66,LISTAS!$A$2:$B$12,2,0),0),"")))) -> 1005 | G66: 2994 | I66: =N($F66) -> 1005
A67: 46220 | B67: ENVÍO A SUPESA | C67: P | D67: jabas | E67: 11 | F67: =IF($B67="","",IF($D67="kg",N($E67),IF($D67="sacos",N($E67)*97,IF($D67="jabas",N($E67)*IFERROR(VLOOKUP($C67,LISTAS!$A$2:$B$12,2,0),0),"")))) -> 198 | G67: 2994 | I67: =N($F67) -> 198
A68: 46220 | B68: ENVÍO A SUPESA | C68: C | D68: jabas | E68: 12 | F68: =IF($B68="","",IF($D68="kg",N($E68),IF($D68="sacos",N($E68)*97,IF($D68="jabas",N($E68)*IFERROR(VLOOKUP($C68,LISTAS!$A$2:$B$12,2,0),0),"")))) -> 204 | G68: 2994 | I68: =N($F68) -> 204
A69: 46220 | B69: ENVÍO A SUPESA | C69: M | D69: jabas | E69: 118 | F69: =IF($B69="","",IF($D69="kg",N($E69),IF($D69="sacos",N($E69)*97,IF($D69="jabas",N($E69)*IFERROR(VLOOKUP($C69,LISTAS!$A$2:$B$12,2,0),0),"")))) -> 2006 | G69: 2994 | I69: =N($F69) -> 2006
A70: 46220 | B70: VENTA CHANCHO | C70: Chancho | D70: sacos | E70: 15 | F70: =IF($B70="","",IF($D70="kg",N($E70),IF($D70="sacos",N($E70)*97,IF($D70="jabas",N($E70)*IFERROR(VLOOKUP($C70,LISTAS!$A$2:$B$12,2,0),0),"")))) -> 1455 | G70: TCK002-725 | I70: =N($F70) -> 1455
A71: 46220 | B71: COMPRA | C71: — | D71: sacos | E71: 5 | F71: =IF($B71="","",IF($D71="kg",N($E71),IF($D71="sacos",N($E71)*97,IF($D71="jabas",N($E71)*IFERROR(VLOOKUP($C71,LISTAS!$A$2:$B$12,2,0),0),"")))) -> 485 | H71: peso aprox 95 kg/saco | I71: =N($F71) -> 485
A72: 46220 | B72: PROCESO | C72: A | D72: jabas | E72: 4 | F72: =IF($B72="","",IF($D72="kg",N($E72),IF($D72="sacos",N($E72)*97,IF($D72="jabas",N($E72)*IFERROR(VLOOKUP($C72,LISTAS!$A$2:$B$12,2,0),0),"")))) -> 60 | I72: =N($F72) -> 60
A73: 46220 | B73: PROCESO | C73: M | D73: jabas | E73: 18 | F73: =IF($B73="","",IF($D73="kg",N($E73),IF($D73="sacos",N($E73)*97,IF($D73="jabas",N($E73)*IFERROR(VLOOKUP($C73,LISTAS!$A$2:$B$12,2,0),0),"")))) -> 306 | I73: =N($F73) -> 306
A74: 46220 | B74: PROCESO | C74: Chancho | D74: sacos | E74: 1 | F74: =IF($B74="","",IF($D74="kg",N($E74),IF($D74="sacos",N($E74)*97,IF($D74="jabas",N($E74)*IFERROR(VLOOKUP($C74,LISTAS!$A$2:$B$12,2,0),0),"")))) -> 97 | I74: =N($F74) -> 97
A75: 46221 | B75: ENVÍO A SUPESA | C75: A | D75: jabas | E75: 67 | F75: =IF($B75="","",IF($D75="kg",N($E75),IF($D75="sacos",N($E75)*97,IF($D75="jabas",N($E75)*IFERROR(VLOOKUP($C75,LISTAS!$A$2:$B$12,2,0),0),"")))) -> 1005 | G75: 2996 | I75: =N($F75) -> 1005
A76: 46221 | B76: ENVÍO A SUPESA | C76: P | D76: jabas | E76: 4 | F76: =IF($B76="","",IF($D76="kg",N($E76),IF($D76="sacos",N($E76)*97,IF($D76="jabas",N($E76)*IFERROR(VLOOKUP($C76,LISTAS!$A$2:$B$12,2,0),0),"")))) -> 72 | G76: 2996 | I76: =N($F76) -> 72
A77: 46221 | B77: ENVÍO A SUPESA | C77: C | D77: jabas | E77: 9 | F77: =IF($B77="","",IF($D77="kg",N($E77),IF($D77="sacos",N($E77)*97,IF($D77="jabas",N($E77)*IFERROR(VLOOKUP($C77,LISTAS!$A$2:$B$12,2,0),0),"")))) -> 153 | G77: 2996 | I77: =N($F77) -> 153
A78: 46221 | B78: ENVÍO A SUPESA | C78: M | D78: jabas | E78: 114 | F78: =IF($B78="","",IF($D78="kg",N($E78),IF($D78="sacos",N($E78)*97,IF($D78="jabas",N($E78)*IFERROR(VLOOKUP($C78,LISTAS!$A$2:$B$12,2,0),0),"")))) -> 1938 | G78: 2996 | I78: =N($F78) -> 1938
A79: 46221 | B79: PROCESO | C79: A | D79: jabas | E79: 67 | F79: =IF($B79="","",IF($D79="kg",N($E79),IF($D79="sacos",N($E79)*97,IF($D79="jabas",N($E79)*IFERROR(VLOOKUP($C79,LISTAS!$A$2:$B$12,2,0),0),"")))) -> 1005 | I79: =N($F79) -> 1005
A80: 46221 | B80: PROCESO | C80: P | D80: jabas | E80: 11 | F80: =IF($B80="","",IF($D80="kg",N($E80),IF($D80="sacos",N($E80)*97,IF($D80="jabas",N($E80)*IFERROR(VLOOKUP($C80,LISTAS!$A$2:$B$12,2,0),0),"")))) -> 198 | I80: =N($F80) -> 198
A81: 46221 | B81: PROCESO | C81: C | D81: jabas | E81: 12 | F81: =IF($B81="","",IF($D81="kg",N($E81),IF($D81="sacos",N($E81)*97,IF($D81="jabas",N($E81)*IFERROR(VLOOKUP($C81,LISTAS!$A$2:$B$12,2,0),0),"")))) -> 204 | I81: =N($F81) -> 204
A82: 46221 | B82: PROCESO | C82: M | D82: jabas | E82: 54 | F82: =IF($B82="","",IF($D82="kg",N($E82),IF($D82="sacos",N($E82)*97,IF($D82="jabas",N($E82)*IFERROR(VLOOKUP($C82,LISTAS!$A$2:$B$12,2,0),0),"")))) -> 918 | I82: =N($F82) -> 918
A83: 46221 | B83: PROCESO | C83: Chancho | D83: sacos | E83: 10 | F83: =IF($B83="","",IF($D83="kg",N($E83),IF($D83="sacos",N($E83)*97,IF($D83="jabas",N($E83)*IFERROR(VLOOKUP($C83,LISTAS!$A$2:$B$12,2,0),0),"")))) -> 970 | I83: =N($F83) -> 970
A84: 46221 | B84: TRASIEGO | C84: A | D84: jabas | E84: 1 | F84: =IF($B84="","",IF($D84="kg",N($E84),IF($D84="sacos",N($E84)*97,IF($D84="jabas",N($E84)*IFERROR(VLOOKUP($C84,LISTAS!$A$2:$B$12,2,0),0),"")))) -> 15 | I84: =N($F84) -> 15
A85: 46221 | B85: COMPRA | C85: — | D85: sacos | E85: 33 | F85: =IF($B85="","",IF($D85="kg",N($E85),IF($D85="sacos",N($E85)*97,IF($D85="jabas",N($E85)*IFERROR(VLOOKUP($C85,LISTAS!$A$2:$B$12,2,0),0),"")))) -> 3201 | H85: Compra del sabado 18/07 (33 sacos) | I85: =N($F85) -> 3201
A86: 46222 | B86: PROCESO | C86: A | D86: jabas | E86: 40 | F86: =IF($B86="","",IF($D86="kg",N($E86),IF($D86="sacos",N($E86)*97,IF($D86="jabas",N($E86)*IFERROR(VLOOKUP($C86,LISTAS!$A$2:$B$12,2,0),0),"")))) -> 600 | I86: =N($F86) -> 600
A87: 46222 | B87: PROCESO | C87: P | D87: jabas | E87: 0 | F87: =IF($B87="","",IF($D87="kg",N($E87),IF($D87="sacos",N($E87)*97,IF($D87="jabas",N($E87)*IFERROR(VLOOKUP($C87,LISTAS!$A$2:$B$12,2,0),0),"")))) -> 0 | I87: =N($F87) -> 0
A88: 46222 | B88: PROCESO | C88: C | D88: jabas | E88: 0 | F88: =IF($B88="","",IF($D88="kg",N($E88),IF($D88="sacos",N($E88)*97,IF($D88="jabas",N($E88)*IFERROR(VLOOKUP($C88,LISTAS!$A$2:$B$12,2,0),0),"")))) -> 0 | I88: =N($F88) -> 0
A89: 46222 | B89: PROCESO | C89: M | D89: jabas | E89: 34 | F89: =IF($B89="","",IF($D89="kg",N($E89),IF($D89="sacos",N($E89)*97,IF($D89="jabas",N($E89)*IFERROR(VLOOKUP($C89,LISTAS!$A$2:$B$12,2,0),0),"")))) -> 578 | I89: =N($F89) -> 578
A90: 46222 | B90: PROCESO | C90: Chancho | D90: sacos | E90: 3 | F90: =IF($B90="","",IF($D90="kg",N($E90),IF($D90="sacos",N($E90)*97,IF($D90="jabas",N($E90)*IFERROR(VLOOKUP($C90,LISTAS!$A$2:$B$12,2,0),0),"")))) -> 291 | I90: =N($F90) -> 291
A91: 46222 | B91: ENVÍO A SUPESA | C91: A | D91: jabas | E91: 67 | F91: =IF($B91="","",IF($D91="kg",N($E91),IF($D91="sacos",N($E91)*97,IF($D91="jabas",N($E91)*IFERROR(VLOOKUP($C91,LISTAS!$A$2:$B$12,2,0),0),"")))) -> 1005 | G91: 2998 | I91: =N($F91) -> 1005
A92: 46222 | B92: ENVÍO A SUPESA | C92: P | D92: jabas | E92: 11 | F92: =IF($B92="","",IF($D92="kg",N($E92),IF($D92="sacos",N($E92)*97,IF($D92="jabas",N($E92)*IFERROR(VLOOKUP($C92,LISTAS!$A$2:$B$12,2,0),0),"")))) -> 198 | G92: 2998 | I92: =N($F92) -> 198
A93: 46222 | B93: ENVÍO A SUPESA | C93: C | D93: jabas | E93: 12 | F93: =IF($B93="","",IF($D93="kg",N($E93),IF($D93="sacos",N($E93)*97,IF($D93="jabas",N($E93)*IFERROR(VLOOKUP($C93,LISTAS!$A$2:$B$12,2,0),0),"")))) -> 204 | G93: 2998 | I93: =N($F93) -> 204
A94: 46222 | B94: ENVÍO A SUPESA | C94: M | D94: jabas | E94: 28 | F94: =IF($B94="","",IF($D94="kg",N($E94),IF($D94="sacos",N($E94)*97,IF($D94="jabas",N($E94)*IFERROR(VLOOKUP($C94,LISTAS!$A$2:$B$12,2,0),0),"")))) -> 476 | G94: 2998 | I94: =N($F94) -> 476
A95: 46222 | B95: COMPRA | C95: — | D95: sacos | E95: 17 | F95: =IF($B95="","",IF($D95="kg",N($E95),IF($D95="sacos",N($E95)*97,IF($D95="jabas",N($E95)*IFERROR(VLOOKUP($C95,LISTAS!$A$2:$B$12,2,0),0),"")))) -> 1649 | H95: Compra del domingo 19/07 (17 sacos) | I95: =N($F95) -> 1649
A96: 46223 | B96: COMPRA | C96: — | D96: sacos | E96: 48 | F96: =IF($B96="","",IF($D96="kg",N($E96),IF($D96="sacos",N($E96)*97,IF($D96="jabas",N($E96)*IFERROR(VLOOKUP($C96,LISTAS!$A$2:$B$12,2,0),0),"")))) -> 4656 | H96: TOTAL 70 SACOS, LUNES PROCESO 48 | I96: =N($F96) -> 4656
A97: 46223 | B97: PROCESO | C97: A | D97: jabas | E97: 68 | F97: =IF($B97="","",IF($D97="kg",N($E97),IF($D97="sacos",N($E97)*97,IF($D97="jabas",N($E97)*IFERROR(VLOOKUP($C97,LISTAS!$A$2:$B$12,2,0),0),"")))) -> 1020 | I97: =N($F97) -> 1020
A98: 46223 | B98: PROCESO | C98: P | D98: jabas | E98: 23 | F98: =IF($B98="","",IF($D98="kg",N($E98),IF($D98="sacos",N($E98)*97,IF($D98="jabas",N($E98)*IFERROR(VLOOKUP($C98,LISTAS!$A$2:$B$12,2,0),0),"")))) -> 414 | I98: =N($F98) -> 414
A99: 46223 | B99: PROCESO | C99: C | D99: jabas | E99: 23 | F99: =IF($B99="","",IF($D99="kg",N($E99),IF($D99="sacos",N($E99)*97,IF($D99="jabas",N($E99)*IFERROR(VLOOKUP($C99,LISTAS!$A$2:$B$12,2,0),0),"")))) -> 391 | I99: =N($F99) -> 391
A100: 46223 | B100: PROCESO | C100: M | D100: jabas | E100: 129 | F100: =IF($B100="","",IF($D100="kg",N($E100),IF($D100="sacos",N($E100)*97,IF($D100="jabas",N($E100)*IFERROR(VLOOKUP($C100,LISTAS!$A$2:$B$12,2,0),0),"")))) -> 2193 | I100: =N($F100) -> 2193
A101: 46223 | B101: PROCESO | C101: Chancho | D101: sacos | E101: 6.5 | F101: =IF($B101="","",IF($D101="kg",N($E101),IF($D101="sacos",N($E101)*97,IF($D101="jabas",N($E101)*IFERROR(VLOOKUP($C101,LISTAS!$A$2:$B$12,2,0),0),"")))) -> 630.5 | I101: =N($F101) -> 630.5
...

Sheet SALDO DIARIO
A1: AGRO PACAYALES · PLANTA CAMOTE 2026 | SALDO DIARIO — lo que queda en almacén al cierre de cada día
A2: Automático. Cada fila = cierre del día: jabas por calidad para contar el almacén, sacos de chancho y kg del kardex. RECHAZO no suma (va a reproceso); DEVOLUCIÓN sí suma completo. La última fila con datos es tu stock de HOY.
A4: Fecha | B4: A (jabas) | C4: P (jabas) | D4: C (jabas) | E4: M (jabas) | F4: Chancho (sacos) | G4: TOTAL jabas | H4: Stock Kg
A5: =IFERROR(INDEX(K$5:K$400,MATCH(ROW()-4,J$5:J$400,0)),"") -> 46214 | B5: =IF($A5="","",SUMPRODUCT((MOVIMIENTOS!$B$5:$B$400="SALDO INICIAL")*(MOVIMIENTOS!$C$5:$C$400="A")*(MOVIMIENTOS!$D$5:$D$400="jabas")*(MOVIMIENTOS!$A$5:$A$400<>"")*(MOVIMIENTOS!$A$5:$A$400<=$A5)*MOVIMIENTOS!$E$5:$E$400)+SUMPRODUCT((MOVIMIENTOS!$B$5:$B$400="PROCESO")*(MOVIMIENTOS!$C$5:$C$400="A")*(MOVIMIENTOS!$D$5:$D$400="jabas")*(MOVIMIENTOS!$A$5:$A$400<>"")*(MOVIMIENTOS!$A$5:$A$400<=$A5)*MOVIMIENTOS!$E$5:$E$400)-SUMPRODUCT((MOVIMIENTOS!$B$5:$B$400="ENVÍO A SUPESA")*(MOVIMIENTOS!$C$5:$C$400="A")*(MOVIMIENTOS!$D$5:$D$400="jabas")*(MOVIMIENTOS!$A$5:$A$400<>"")*(MOVIMIENTOS!$A$5:$A$400<=$A5)*MOVIMIENTOS!$E$5:$E$400)+SUMPRODUCT((MOVIMIENTOS!$B$5:$B$400="DEVOLUCIÓN")*(MOVIMIENTOS!$C$5:$C$400="A")*(MOVIMIENTOS!$D$5:$D$400="jabas")*(MOVIMIENTOS!$A$5:$A$400<>"")*(MOVIMIENTOS!$A$5:$A$400<=$A5)*MOVIMIENTOS!$E$5:$E$400)-SUMPRODUCT((MOVIMIENTOS!$B$5:$B$400="TRASIEGO")*(MOVIMIENTOS!$C$5:$C$400="A")*(MOVIMIENTOS!$D$5:$D$400="jabas")*(MOVIMIENTOS!$A$5:$A$400<>"")*(MOVIMIENTOS!$A$5:$A$400<=$A5)*MOVIMIENTOS!$E$5:$E$400)-SUMPRODUCT((MOVIMIENTOS!$B$5:$B$400="REGALO")*(MOVIMIENTOS!$C$5:$C$400="A")*(MOVIMIENTOS!$D$5:$D$400="jabas")*(MOVIMIENTOS!$A$5:$A$400<>"")*(MOVIMIENTOS!$A$5:$A$400<=$A5)*MOVIMIENTOS!$E$5:$E$400)-SUMPRODUCT((MOVIMIENTOS!$B$5:$B$400="VENTA")*(MOVIMIENTOS!$C$5:$C$400="A")*(MOVIMIENTOS!$D$5:$D$400="jabas")*(MOVIMIENTOS!$A$5:$A$400<>"")*(MOVIMIENTOS!$A$5:$A$400<=$A5)*MOVIMIENTOS!$E$5:$E$400)+SUMPRODUCT((MOVIMIENTOS!$B$5:$B$400="AJUSTE")*(MOVIMIENTOS!$C$5:$C$400="A")*(MOVIMIENTOS!$D$5:$D$400="jabas")*(MOVIMIENTOS!$A$5:$A$400<>"")*(MOVIMIENTOS!$A$5:$A$400<=$A5)*MOVIMIENTOS!$E$5:$E$400)) -> 2 | C5: =IF($A5="","",SUMPRODUCT((MOVIMIENTOS!$B$5:$B$400="SALDO INICIAL")*(MOVIMIENTOS!$C$5:$C$400="P")*(MOVIMIENTOS!$D$5:$D$400="jabas")*(MOVIMIENTOS!$A$5:$A$400<>"")*(MOVIMIENTOS!$A$5:$A$400<=$A5)*MOVIMIENTOS!$E$5:$E$400)+SUMPRODUCT((MOVIMIENTOS!$B$5:$B$400="PROCESO")*(MOVIMIENTOS!$C$5:$C$400="P")*(MOVIMIENTOS!$D$5:$D$400="jabas")*(MOVIMIENTOS!$A$5:$A$400<>"")*(MOVIMIENTOS!$A$5:$A$400<=$A5)*MOVIMIENTOS!$E$5:$E$400)-SUMPRODUCT((MOVIMIENTOS!$B$5:$B$400="ENVÍO A SUPESA")*(MOVIMIENTOS!$C$5:$C$400="P")*(MOVIMIENTOS!$D$5:$D$400="jabas")*(MOVIMIENTOS!$A$5:$A$400<>"")*(MOVIMIENTOS!$A$5:$A$400<=$A5)*MOVIMIENTOS!$E$5:$E$400)+SUMPRODUCT((MOVIMIENTOS!$B$5:$B$400="DEVOLUCIÓN")*(MOVIMIENTOS!$C$5:$C$400="P")*(MOVIMIENTOS!$D$5:$D$400="jabas")*(MOVIMIENTOS!$A$5:$A$400<>"")*(MOVIMIENTOS!$A$5:$A$400<=$A5)*MOVIMIENTOS!$E$5:$E$400)-SUMPRODUCT((MOVIMIENTOS!$B$5:$B$400="TRASIEGO")*(MOVIMIENTOS!$C$5:$C$400="P")*(MOVIMIENTOS!$D$5:$D$400="jabas")*(MOVIMIENTOS!$A$5:$A$400<>"")*(MOVIMIENTOS!$A$5:$A$400<=$A5)*MOVIMIENTOS!$E$5:$E$400)-SUMPRODUCT((MOVIMIENTOS!$B$5:$B$400="REGALO")*(MOVIMIENTOS!$C$5:$C$400="P")*(MOVIMIENTOS!$D$5:$D$400="jabas")*(MOVIMIENTOS!$A$5:$A$400<>"")*(MOVIMIENTOS!$A$5:$A$400<=$A5)*MOVIMIENTOS!$E$5:$E$400)-SUMPRODUCT((MOVIMIENTOS!$B$5:$B$400="VENTA")*(MOVIMIENTOS!$C$5:$C$400="P")*(MOVIMIENTOS!$D$5:$D$400="jabas")*(MOVIMIENTOS!$A$5:$A$400<>"")*(MOVIMIENTOS!$A$5:$A$400<=$A5)*MOVIMIENTOS!$E$5:$E$400)+SUMPRODUCT((MOVIMIENTOS!$B$5:$B$400="AJUSTE")*(MOVIMIENTOS!$C$5:$C$400="P")*(MOVIMIENTOS!$D$5:$D$400="jabas")*(MOVIMIENTOS!$A$5:$A$400<>"")*(MOVIMIENTOS!$A$5:$A$400<=$A5)*MOVIMIENTOS!$E$5:$E$400)) -> 0 | D5: =IF($A5="","",SUMPRODUCT((MOVIMIENTOS!$B$5:$B$400="SALDO INICIAL")*(MOVIMIENTOS!$C$5:$C$400="C")*(MOVIMIENTOS!$D$5:$D$400="jabas")*(MOVIMIENTOS!$A$5:$A$400<>"")*(MOVIMIENTOS!$A$5:$A$400<=$A5)*MOVIMIENTOS!$E$5:$E$400)+SUMPRODUCT((MOVIMIENTOS!$B$5:$B$400="PROCESO")*(MOVIMIENTOS!$C$5:$C$400="C")*(MOVIMIENTOS!$D$5:$D$400="jabas")*(MOVIMIENTOS!$A$5:$A$400<>"")*(MOVIMIENTOS!$A$5:$A$400<=$A5)*MOVIMIENTOS!$E$5:$E$400)-SUMPRODUCT((MOVIMIENTOS!$B$5:$B$400="ENVÍO A SUPESA")*(MOVIMIENTOS!$C$5:$C$400="C")*(MOVIMIENTOS!$D$5:$D$400="jabas")*(MOVIMIENTOS!$A$5:$A$400<>"")*(MOVIMIENTOS!$A$5:$A$400<=$A5)*MOVIMIENTOS!$E$5:$E$400)+SUMPRODUCT((MOVIMIENTOS!$B$5:$B$400="DEVOLUCIÓN")*(MOVIMIENTOS!$C$5:$C$400="C")*(MOVIMIENTOS!$D$5:$D$400="jabas")*(MOVIMIENTOS!$A$5:$A$400<>"")*(MOVIMIENTOS!$A$5:$A$400<=$A5)*MOVIMIENTOS!$E$5:$E$400)-SUMPRODUCT((MOVIMIENTOS!$B$5:$B$400="TRASIEGO")*(MOVIMIENTOS!$C$5:$C$400="C")*(MOVIMIENTOS!$D$5:$D$400="jabas")*(MOVIMIENTOS!$A$5:$A$400<>"")*(MOVIMIENTOS!$A$5:$A$400<=$A5)*MOVIMIENTOS!$E$5:$E$400)-SUMPRODUCT((MOVIMIENTOS!$B$5:$B$400="REGALO")*(MOVIMIENTOS!$C$5:$C$400="C")*(MOVIMIENTOS!$D$5:$D$400="jabas")*(MOVIMIENTOS!$A$5:$A$400<>"")*(MOVIMIENTOS!$A$5:$A$400<=$A5)*MOVIMIENTOS!$E$5:$E$400)-SUMPRODUCT((MOVIMIENTOS!$B$5:$B$400="VENTA")*(MOVIMIENTOS!$C$5:$C$400="C")*(MOVIMIENTOS!$D$5:$D$400="jabas")*(MOVIMIENTOS!$A$5:$A$400<>"")*(MOVIMIENTOS!$A$5:$A$400<=$A5)*MOVIMIENTOS!$E$5:$E$400)+SUMPRODUCT((MOVIMIENTOS!$B$5:$B$400="AJUSTE")*(MOVIMIENTOS!$C$5:$C$400="C")*(MOVIMIENTOS!$D$5:$D$400="jabas")*(MOVIMIENTOS!$A$5:$A$400<>"")*(MOVIMIENTOS!$A$5:$A$400<=$A5)*MOVIMIENTOS!$E$5:$E$400)) -> 0 | E5: =IF($A5="","",SUMPRODUCT((MOVIMIENTOS!$B$5:$B$400="SALDO INICIAL")*(MOVIMIENTOS!$C$5:$C$400="M")*(MOVIMIENTOS!$D$5:$D$400="jabas")*(MOVIMIENTOS!$A$5:$A$400<>"")*(MOVIMIENTOS!$A$5:$A$400<=$A5)*MOVIMIENTOS!$E$5:$E$400)+SUMPRODUCT((MOVIMIENTOS!$B$5:$B$400="PROCESO")*(MOVIMIENTOS!$C$5:$C$400="M")*(MOVIMIENTOS!$D$5:$D$400="jabas")*(MOVIMIENTOS!$A$5:$A$400<>"")*(MOVIMIENTOS!$A$5:$A$400<=$A5)*MOVIMIENTOS!$E$5:$E$400)-SUMPRODUCT((MOVIMIENTOS!$B$5:$B$400="ENVÍO A SUPESA")*(MOVIMIENTOS!$C$5:$C$400="M")*(MOVIMIENTOS!$D$5:$D$400="jabas")*(MOVIMIENTOS!$A$5:$A$400<>"")*(MOVIMIENTOS!$A$5:$A$400<=$A5)*MOVIMIENTOS!$E$5:$E$400)+SUMPRODUCT((MOVIMIENTOS!$B$5:$B$400="DEVOLUCIÓN")*(MOVIMIENTOS!$C$5:$C$400="M")*(MOVIMIENTOS!$D$5:$D$400="jabas")*(MOVIMIENTOS!$A$5:$A$400<>"")*(MOVIMIENTOS!$A$5:$A$400<=$A5)*MOVIMIENTOS!$E$5:$E$400)-SUMPRODUCT((MOVIMIENTOS!$B$5:$B$400="TRASIEGO")*(MOVIMIENTOS!$C$5:$C$400="M")*(MOVIMIENTOS!$D$5:$D$400="jabas")*(MOVIMIENTOS!$A$5:$A$400<>"")*(MOVIMIENTOS!$A$5:$A$400<=$A5)*MOVIMIENTOS!$E$5:$E$400)-SUMPRODUCT((MOVIMIENTOS!$B$5:$B$400="REGALO")*(MOVIMIENTOS!$C$5:$C$400="M")*(MOVIMIENTOS!$D$5:$D$400="jabas")*(MOVIMIENTOS!$A$5:$A$400<>"")*(MOVIMIENTOS!$A$5:$A$400<=$A5)*MOVIMIENTOS!$E$5:$E$400)-SUMPRODUCT((MOVIMIENTOS!$B$5:$B$400="VENTA")*(MOVIMIENTOS!$C$5:$C$400="M")*(MOVIMIENTOS!$D$5:$D$400="jabas")*(MOVIMIENTOS!$A$5:$A$400<>"")*(MOVIMIENTOS!$A$5:$A$400<=$A5)*MOVIMIENTOS!$E$5:$E$400)+SUMPRODUCT((MOVIMIENTOS!$B$5:$B$400="AJUSTE")*(MOVIMIENTOS!$C$5:$C$400="M")*(MOVIMIENTOS!$D$5:$D$400="jabas")*(MOVIMIENTOS!$A$5:$A$400<>"")*(MOVIMIENTOS!$A$5:$A$400<=$A5)*MOVIMIENTOS!$E$5:$E$400)) -> 8 | F5: =IF($A5="","",SUMPRODUCT((MOVIMIENTOS!$B$5:$B$400="SALDO INICIAL")*(MOVIMIENTOS!$C$5:$C$400="Chancho")*(MOVIMIENTOS!$D$5:$D$400="sacos")*(MOVIMIENTOS!$A$5:$A$400<>"")*(MOVIMIENTOS!$A$5:$A$400<=$A5)*MOVIMIENTOS!$E$5:$E$400)+SUMPRODUCT((MOVIMIENTOS!$B$5:$B$400="PROCESO")*(MOVIMIENTOS!$C$5:$C$400="Chancho")*(MOVIMIENTOS!$D$5:$D$400="sacos")*(MOVIMIENTOS!$A$5:$A$400<>"")*(MOVIMIENTOS!$A$5:$A$400<=$A5)*MOVIMIENTOS!$E$5:$E$400)-SUMPRODUCT((MOVIMIENTOS!$B$5:$B$400="VENTA CHANCHO")*(MOVIMIENTOS!$C$5:$C$400="Chancho")*(MOVIMIENTOS!$D$5:$D$400="sacos")*(MOVIMIENTOS!$A$5:$A$400<>"")*(MOVIMIENTOS!$A$5:$A$400<=$A5)*MOVIMIENTOS!$E$5:$E$400)-SUMPRODUCT((MOVIMIENTOS!$B$5:$B$400="REGALO")*(MOVIMIENTOS!$C$5:$C$400="Chancho")*(MOVIMIENTOS!$D$5:$D$400="sacos")*(MOVIMIENTOS!$A$5:$A$400<>"")*(MOVIMIENTOS!$A$5:$A$400<=$A5)*MOVIMIENTOS!$E$5:$E$400)-SUMPRODUCT((MOVIMIENTOS!$B$5:$B$400="VENTA")*(MOVIMIENTOS!$C$5:$C$400="Chancho")*(MOVIMIENTOS!$D$5:$D$400="sacos")*(MOVIMIENTOS!$A$5:$A$400<>"")*(MOVIMIENTOS!$A$5:$A$400<=$A5)*MOVIMIENTOS!$E$5:$E$400)+SUMPRODUCT((MOVIMIENTOS!$B$5:$B$400="AJUSTE")*(MOVIMIENTOS!$C$5:$C$400="Chancho")*(MOVIMIENTOS!$D$5:$D$400="sacos")*(MOVIMIENTOS!$A$5:$A$400<>"")*(MOVIMIENTOS!$A$5:$A$400<=$A5)*MOVIMIENTOS!$E$5:$E$400)) -> 20 | G5: =IF($A5="","",SUM(B5:E5)) -> 10 | H5: =IF($A5="","",SUMPRODUCT((((MOVIMIENTOS!$B$5:$B$400="SALDO INICIAL")*(MOVIMIENTOS!$C$5:$C$400<>"Chancho"))+(MOVIMIENTOS!$B$5:$B$400="COMPRA")+(MOVIMIENTOS!$B$5:$B$400="REPROCESO")+(MOVIMIENTOS!$B$5:$B$400="DEVOLUCIÓN")+((MOVIMIENTOS!$B$5:$B$400="AJUSTE")*(MOVIMIENTOS!$C$5:$C$400<>"Chancho")))*(MOVIMIENTOS!$A$5:$A$400<>"")*(MOVIMIENTOS!$A$5:$A$400<=$A5)*MOVIMIENTOS!$I$5:$I$400)-SUMPRODUCT(((MOVIMIENTOS!$B$5:$B$400="ENVÍO A SUPESA")+(MOVIMIENTOS!$B$5:$B$400="ENVÍO A TOTTUS")+(MOVIMIENTOS!$B$5:$B$400="ENVIO A TOTTUS")+(MOVIMIENTOS!$B$5:$B$400="MALOGRADO")+(MOVIMIENTOS!$B$5:$B$400="OTRA SALIDA")+((MOVIMIENTOS!$B$5:$B$400="PROCESO")*(MOVIMIENTOS!$C$5:$C$400="Chancho"))+((MOVIMIENTOS!$B$5:$B$400="REGALO")*(MOVIMIENTOS!$C$5:$C$400<>"Chancho"))+((MOVIMIENTOS!$B$5:$B$400="VENTA")*(MOVIMIENTOS!$C$5:$C$400<>"Chancho")))*(MOVIMIENTOS!$A$5:$A$400<>"")*(MOVIMIENTOS!$A$5:$A$400<=$A5)*MOVIMIENTOS!$I$5:$I$400)) -> 166 | J5: =IF(MOVIMIENTOS!$A$5<>"",1,"") -> 1 | K5: =MOVIMIENTOS!$A5 -> 46214
A6: =IFERROR(INDEX(K$5:K$400,MATCH(ROW()-4,J$5:J$400,0)),"") -> 46215 | B6: =IF($A6="","",SUMPRODUCT((MOVIMIENTOS!$B$5:$B$400="SALDO INICIAL")*(MOVIMIENTOS!$C$5:$C$400="A")*(MOVIMIENTOS!$D$5:$D$400="jabas")*(MOVIMIENTOS!$A$5:$A$400<>"")*(MOVIMIENTOS!$A$5:$A$400<=$A6)*MOVIMIENTOS!$E$5:$E$400)+SUMPRODUCT((MOVIMIENTOS!$B$5:$B$400="PROCESO")*(MOVIMIENTOS!$C$5:$C$400="A")*(MOVIMIENTOS!$D$5:$D$400="jabas")*(MOVIMIENTOS!$A$5:$A$400<>"")*(MOVIMIENTOS!$A$5:$A$400<=$A6)*MOVIMIENTOS!$E$5:$E$400)-SUMPRODUCT((MOVIMIENTOS!$B$5:$B$400="ENVÍO A SUPESA")*(MOVIMIENTOS!$C$5:$C$400="A")*(MOVIMIENTOS!$D$5:$D$400="jabas")*(MOVIMIENTOS!$A$5:$A$400<>"")*(MOVIMIENTOS!$A$5:$A$400<=$A6)*MOVIMIENTOS!$E$5:$E$400)+SUMPRODUCT((MOVIMIENTOS!$B$5:$B$400="DEVOLUCIÓN")*(MOVIMIENTOS!$C$5:$C$400="A")*(MOVIMIENTOS!$D$5:$D$400="jabas")*(MOVIMIENTOS!$A$5:$A$400<>"")*(MOVIMIENTOS!$A$5:$A$400<=$A6)*MOVIMIENTOS!$E$5:$E$400)-SUMPRODUCT((MOVIMIENTOS!$B$5:$B$400="TRASIEGO")*(MOVIMIENTOS!$C$5:$C$400="A")*(MOVIMIENTOS!$D$5:$D$400="jabas")*(MOVIMIENTOS!$A$5:$A$400<>"")*(MOVIMIENTOS!$A$5:$A$400<=$A6)*MOVIMIENTOS!$E$5:$E$400)-SUMPRODUCT((MOVIMIENTOS!$B$5:$B$400="REGALO")*(MOVIMIENTOS!$C$5:$C$400="A")*(MOVIMIENTOS!$D$5:$D$400="jabas")*(MOVIMIENTOS!$A$5:$A$400<>"")*(MOVIMIENTOS!$A$5:$A$400<=$A6)*MOVIMIENTOS!$E$5:$E$400)-SUMPRODUCT((MOVIMIENTOS!$B$5:$B$400="VENTA")*(MOVIMIENTOS!$C$5:$C$400="A")*(MOVIMIENTOS!$D$5:$D$400="jabas")*(MOVIMIENTOS!$A$5:$A$400<>"")*(MOVIMIENTOS!$A$5:$A$400<=$A6)*MOVIMIENTOS!$E$5:$E$400)+SUMPRODUCT((MOVIMIENTOS!$B$5:$B$400="AJUSTE")*(MOVIMIENTOS!$C$5:$C$400="A")*(MOVIMIENTOS!$D$5:$D$400="jabas")*(MOVIMIENTOS!$A$5:$A$400<>"")*(MOVIMIENTOS!$A$5:$A$400<=$A6)*MOVIMIENTOS!$E$5:$E$400)) -> -6 | C6: =IF($A6="","",SUMPRODUCT((MOVIMIENTOS!$B$5:$B$400="SALDO INICIAL")*(MOVIMIENTOS!$C$5:$C$400="P")*(MOVIMIENTOS!$D$5:$D$400="jabas")*(MOVIMIENTOS!$A$5:$A$400<>"")*(MOVIMIENTOS!$A$5:$A$400<=$A6)*MOVIMIENTOS!$E$5:$E$400)+SUMPRODUCT((MOVIMIENTOS!$B$5:$B$400="PROCESO")*(MOVIMIENTOS!$C$5:$C$400="P")*(MOVIMIENTOS!$D$5:$D$400="jabas")*(MOVIMIENTOS!$A$5:$A$400<>"")*(MOVIMIENTOS!$A$5:$A$400<=$A6)*MOVIMIENTOS!$E$5:$E$400)-SUMPRODUCT((MOVIMIENTOS!$B$5:$B$400="ENVÍO A SUPESA")*(MOVIMIENTOS!$C$5:$C$400="P")*(MOVIMIENTOS!$D$5:$D$400="jabas")*(MOVIMIENTOS!$A$5:$A$400<>"")*(MOVIMIENTOS!$A$5:$A$400<=$A6)*MOVIMIENTOS!$E$5:$E$400)+SUMPRODUCT((MOVIMIENTOS!$B$5:$B$400="DEVOLUCIÓN")*(MOVIMIENTOS!$C$5:$C$400="P")*(MOVIMIENTOS!$D$5:$D$400="jabas")*(MOVIMIENTOS!$A$5:$A$400<>"")*(MOVIMIENTOS!$A$5:$A$400<=$A6)*MOVIMIENTOS!$E$5:$E$400)-SUMPRODUCT((MOVIMIENTOS!$B$5:$B$400="TRASIEGO")*(MOVIMIENTOS!$C$5:$C$400="P")*(MOVIMIENTOS!$D$5:$D$400="jabas")*(MOVIMIENTOS!$A$5:$A$400<>"")*(MOVIMIENTOS!$A$5:$A$400<=$A6)*MOVIMIENTOS!$E$5:$E$400)-SUMPRODUCT((MOVIMIENTOS!$B$5:$B$400="REGALO")*(MOVIMIENTOS!$C$5:$C$400="P")*(MOVIMIENTOS!$D$5:$D$400="jabas")*(MOVIMIENTOS!$A$5:$A$400<>"")*(MOVIMIENTOS!$A$5:$A$400<=$A6)*MOVIMIENTOS!$E$5:$E$400)-SUMPRODUCT((MOVIMIENTOS!$B$5:$B$400="VENTA")*(MOVIMIENTOS!$C$5:$C$400="P")*(MOVIMIENTOS!$D$5:$D$400="jabas")*(MOVIMIENTOS!$A$5:$A$400<>"")*(MOVIMIENTOS!$A$5:$A$400<=$A6)*MOVIMIENTOS!$E$5:$E$400)+SUMPRODUCT((MOVIMIENTOS!$B$5:$B$400="AJUSTE")*(MOVIMIENTOS!$C$5:$C$400="P")*(MOVIMIENTOS!$D$5:$D$400="jabas")*(MOVIMIENTOS!$A$5:$A$400<>"")*(MOVIMIENTOS!$A$5:$A$400<=$A6)*MOVIMIENTOS!$E$5:$E$400)) -> 0 | D6: =IF($A6="","",SUMPRODUCT((MOVIMIENTOS!$B$5:$B$400="SALDO INICIAL")*(MOVIMIENTOS!$C$5:$C$400="C")*(MOVIMIENTOS!$D$5:$D$400="jabas")*(MOVIMIENTOS!$A$5:$A$400<>"")*(MOVIMIENTOS!$A$5:$A$400<=$A6)*MOVIMIENTOS!$E$5:$E$400)+SUMPRODUCT((MOVIMIENTOS!$B$5:$B$400="PROCESO")*(MOVIMIENTOS!$C$5:$C$400="C")*(MOVIMIENTOS!$D$5:$D$400="jabas")*(MOVIMIENTOS!$A$5:$A$400<>"")*(MOVIMIENTOS!$A$5:$A$400<=$A6)*MOVIMIENTOS!$E$5:$E$400)-SUMPRODUCT((MOVIMIENTOS!$B$5:$B$400="ENVÍO A SUPESA")*(MOVIMIENTOS!$C$5:$C$400="C")*(MOVIMIENTOS!$D$5:$D$400="jabas")*(MOVIMIENTOS!$A$5:$A$400<>"")*(MOVIMIENTOS!$A$5:$A$400<=$A6)*MOVIMIENTOS!$E$5:$E$400)+SUMPRODUCT((MOVIMIENTOS!$B$5:$B$400="DEVOLUCIÓN")*(MOVIMIENTOS!$C$5:$C$400="C")*(MOVIMIENTOS!$D$5:$D$400="jabas")*(MOVIMIENTOS!$A$5:$A$400<>"")*(MOVIMIENTOS!$A$5:$A$400<=$A6)*MOVIMIENTOS!$E$5:$E$400)-SUMPRODUCT((MOVIMIENTOS!$B$5:$B$400="TRASIEGO")*(MOVIMIENTOS!$C$5:$C$400="C")*(MOVIMIENTOS!$D$5:$D$400="jabas")*(MOVIMIENTOS!$A$5:$A$400<>"")*(MOVIMIENTOS!$A$5:$A$400<=$A6)*MOVIMIENTOS!$E$5:$E$400)-SUMPRODUCT((MOVIMIENTOS!$B$5:$B$400="REGALO")*(MOVIMIENTOS!$C$5:$C$400="C")*(MOVIMIENTOS!$D$5:$D$400="jabas")*(MOVIMIENTOS!$A$5:$A$400<>"")*(MOVIMIENTOS!$A$5:$A$400<=$A6)*MOVIMIENTOS!$E$5:$E$400)-SUMPRODUCT((MOVIMIENTOS!$B$5:$B$400="VENTA")*(MOVIMIENTOS!$C$5:$C$400="C")*(MOVIMIENTOS!$D$5:$D$400="jabas")*(MOVIMIENTOS!$A$5:$A$400<>"")*(MOVIMIENTOS!$A$5:$A$400<=$A6)*MOVIMIENTOS!$E$5:$E$400)+SUMPRODUCT((MOVIMIENTOS!$B$5:$B$400="AJUSTE")*(MOVIMIENTOS!$C$5:$C$400="C")*(MOVIMIENTOS!$D$5:$D$400="jabas")*(MOVIMIENTOS!$A$5:$A$400<>"")*(MOVIMIENTOS!$A$5:$A$400<=$A6)*MOVIMIENTOS!$E$5:$E$400)) -> 0 | E6: =IF($A6="","",SUMPRODUCT((MOVIMIENTOS!$B$5:$B$400="SALDO INICIAL")*(MOVIMIENTOS!$C$5:$C$400="M")*(MOVIMIENTOS!$D$5:$D$400="jabas")*(MOVIMIENTOS!$A$5:$A$400<>"")*(MOVIMIENTOS!$A$5:$A$400<=$A6)*MOVIMIENTOS!$E$5:$E$400)+SUMPRODUCT((MOVIMIENTOS!$B$5:$B$400="PROCESO")*(MOVIMIENTOS!$C$5:$C$400="M")*(MOVIMIENTOS!$D$5:$D$400="jabas")*(MOVIMIENTOS!$A$5:$A$400<>"")*(MOVIMIENTOS!$A$5:$A$400<=$A6)*MOVIMIENTOS!$E$5:$E$400)-SUMPRODUCT((MOVIMIENTOS!$B$5:$B$400="ENVÍO A SUPESA")*(MOVIMIENTOS!$C$5:$C$400="M")*(MOVIMIENTOS!$D$5:$D$400="jabas")*(MOVIMIENTOS!$A$5:$A$400<>"")*(MOVIMIENTOS!$A$5:$A$400<=$A6)*MOVIMIENTOS!$E$5:$E$400)+SUMPRODUCT((MOVIMIENTOS!$B$5:$B$400="DEVOLUCIÓN")*(MOVIMIENTOS!$C$5:$C$400="M")*(MOVIMIENTOS!$D$5:$D$400="jabas")*(MOVIMIENTOS!$A$5:$A$400<>"")*(MOVIMIENTOS!$A$5:$A$400<=$A6)*MOVIMIENTOS!$E$5:$E$400)-SUMPRODUCT((MOVIMIENTOS!$B$5:$B$400="TRASIEGO")*(MOVIMIENTOS!$C$5:$C$400="M")*(MOVIMIENTOS!$D$5:$D$400="jabas")*(MOVIMIENTOS!$A$5:$A$400<>"")*(MOVIMIENTOS!$A$5:$A$400<=$A6)*MOVIMIENTOS!$E$5:$E$400)-SUMPRODUCT((MOVIMIENTOS!$B$5:$B$400="REGALO")*(MOVIMIENTOS!$C$5:$C$400="M")*(MOVIMIENTOS!$D$5:$D$400="jabas")*(MOVIMIENTOS!$A$5:$A$400<>"")*(MOVIMIENTOS!$A$5:$A$400<=$A6)*MOVIMIENTOS!$E$5:$E$400)-SUMPRODUCT((MOVIMIENTOS!$B$5:$B$400="VENTA")*(MOVIMIENTOS!$C$5:$C$400="M")*(MOVIMIENTOS!$D$5:$D$400="jabas")*(MOVIMIENTOS!$A$5:$A$400<>"")*(MOVIMIENTOS!$A$5:$A$400<=$A6)*MOVIMIENTOS!$E$5:$E$400)+SUMPRODUCT((MOVIMIENTOS!$B$5:$B$400="AJUSTE")*(MOVIMIENTOS!$C$5:$C$400="M")*(MOVIMIENTOS!$D$5:$D$400="jabas")*(MOVIMIENTOS!$A$5:$A$400<>"")*(MOVIMIENTOS!$A$5:$A$400<=$A6)*MOVIMIENTOS!$E$5:$E$400)) -> 30 | F6: =IF($A6="","",SUMPRODUCT((MOVIMIENTOS!$B$5:$B$400="SALDO INICIAL")*(MOVIMIENTOS!$C$5:$C$400="Chancho")*(MOVIMIENTOS!$D$5:$D$400="sacos")*(MOVIMIENTOS!$A$5:$A$400<>"")*(MOVIMIENTOS!$A$5:$A$400<=$A6)*MOVIMIENTOS!$E$5:$E$400)+SUMPRODUCT((MOVIMIENTOS!$B$5:$B$400="PROCESO")*(MOVIMIENTOS!$C$5:$C$400="Chancho")*(MOVIMIENTOS!$D$5:$D$400="sacos")*(MOVIMIENTOS!$A$5:$A$400<>"")*(MOVIMIENTOS!$A$5:$A$400<=$A6)*MOVIMIENTOS!$E$5:$E$400)-SUMPRODUCT((MOVIMIENTOS!$B$5:$B$400="VENTA CHANCHO")*(MOVIMIENTOS!$C$5:$C$400="Chancho")*(MOVIMIENTOS!$D$5:$D$400="sacos")*(MOVIMIENTOS!$A$5:$A$400<>"")*(MOVIMIENTOS!$A$5:$A$400<=$A6)*MOVIMIENTOS!$E$5:$E$400)-SUMPRODUCT((MOVIMIENTOS!$B$5:$B$400="REGALO")*(MOVIMIENTOS!$C$5:$C$400="Chancho")*(MOVIMIENTOS!$D$5:$D$400="sacos")*(MOVIMIENTOS!$A$5:$A$400<>"")*(MOVIMIENTOS!$A$5:$A$400<=$A6)*MOVIMIENTOS!$E$5:$E$400)-SUMPRODUCT((MOVIMIENTOS!$B$5:$B$400="VENTA")*(MOVIMIENTOS!$C$5:$C$400="Chancho")*(MOVIMIENTOS!$D$5:$D$400="sacos")*(MOVIMIENTOS!$A$5:$A$400<>"")*(MOVIMIENTOS!$A$5:$A$400<=$A6)*MOVIMIENTOS!$E$5:$E$400)+SUMPRODUCT((MOVIMIENTOS!$B$5:$B$400="AJUSTE")*(MOVIMIENTOS!$C$5:$C$400="Chancho")*(MOVIMIENTOS!$D$5:$D$400="sacos")*(MOVIMIENTOS!$A$5:$A$400<>"")*(MOVIMIENTOS!$A$5:$A$400<=$A6)*MOVIMIENTOS!$E$5:$E$400)) -> 26 | G6: =IF($A6="","",SUM(B6:E6)) -> 24 | H6: =IF($A6="","",SUMPRODUCT((((MOVIMIENTOS!$B$5:$B$400="SALDO INICIAL")*(MOVIMIENTOS!$C$5:$C$400<>"Chancho"))+(MOVIMIENTOS!$B$5:$B$400="COMPRA")+(MOVIMIENTOS!$B$5:$B$400="REPROCESO")+(MOVIMIENTOS!$B$5:$B$400="DEVOLUCIÓN")+((MOVIMIENTOS!$B$5:$B$400="AJUSTE")*(MOVIMIENTOS!$C$5:$C$400<>"Chancho")))*(MOVIMIENTOS!$A$5:$A$400<>"")*(MOVIMIENTOS!$A$5:$A$400<=$A6)*MOVIMIENTOS!$I$5:$I$400)-SUMPRODUCT(((MOVIMIENTOS!$B$5:$B$400="ENVÍO A SUPESA")+(MOVIMIENTOS!$B$5:$B$400="ENVÍO A TOTTUS")+(MOVIMIENTOS!$B$5:$B$400="ENVIO A TOTTUS")+(MOVIMIENTOS!$B$5:$B$400="MALOGRADO")+(MOVIMIENTOS!$B$5:$B$400="OTRA SALIDA")+((MOVIMIENTOS!$B$5:$B$400="PROCESO")*(MOVIMIENTOS!$C$5:$C$400="Chancho"))+((MOVIMIENTOS!$B$5:$B$400="REGALO")*(MOVIMIENTOS!$C$5:$C$400<>"Chancho"))+((MOVIMIENTOS!$B$5:$B$400="VENTA")*(MOVIMIENTOS!$C$5:$C$400<>"Chancho")))*(MOVIMIENTOS!$A$5:$A$400<>"")*(MOVIMIENTOS!$A$5:$A$400<=$A6)*MOVIMIENTOS!$I$5:$I$400)) -> 373 | J6: =IF(AND(MOVIMIENTOS!$A6<>"",COUNTIF(MOVIMIENTOS!$A$5:$A5,MOVIMIENTOS!$A6)=0),COUNT(J$4:J5)+1,"") | K6: =MOVIMIENTOS!$A6 -> 46214
A7: =IFERROR(INDEX(K$5:K$400,MATCH(ROW()-4,J$5:J$400,0)),"") -> 46216 | B7: =IF($A7="","",SUMPRODUCT((MOVIMIENTOS!$B$5:$B$400="SALDO INICIAL")*(MOVIMIENTOS!$C$5:$C$400="A")*(MOVIMIENTOS!$D$5:$D$400="jabas")*(MOVIMIENTOS!$A$5:$A$400<>"")*(MOVIMIENTOS!$A$5:$A$400<=$A7)*MOVIMIENTOS!$E$5:$E$400)+SUMPRODUCT((MOVIMIENTOS!$B$5:$B$400="PROCESO")*(MOVIMIENTOS!$C$5:$C$400="A")*(MOVIMIENTOS!$D$5:$D$400="jabas")*(MOVIMIENTOS!$A$5:$A$400<>"")*(MOVIMIENTOS!$A$5:$A$400<=$A7)*MOVIMIENTOS!$E$5:$E$400)-SUMPRODUCT((MOVIMIENTOS!$B$5:$B$400="ENVÍO A SUPESA")*(MOVIMIENTOS!$C$5:$C$400="A")*(MOVIMIENTOS!$D$5:$D$400="jabas")*(MOVIMIENTOS!$A$5:$A$400<>"")*(MOVIMIENTOS!$A$5:$A$400<=$A7)*MOVIMIENTOS!$E$5:$E$400)+SUMPRODUCT((MOVIMIENTOS!$B$5:$B$400="DEVOLUCIÓN")*(MOVIMIENTOS!$C$5:$C$400="A")*(MOVIMIENTOS!$D$5:$D$400="jabas")*(MOVIMIENTOS!$A$5:$A$400<>"")*(MOVIMIENTOS!$A$5:$A$400<=$A7)*MOVIMIENTOS!$E$5:$E$400)-SUMPRODUCT((MOVIMIENTOS!$B$5:$B$400="TRASIEGO")*(MOVIMIENTOS!$C$5:$C$400="A")*(MOVIMIENTOS!$D$5:$D$400="jabas")*(MOVIMIENTOS!$A$5:$A$400<>"")*(MOVIMIENTOS!$A$5:$A$400<=$A7)*MOVIMIENTOS!$E$5:$E$400)-SUMPRODUCT((MOVIMIENTOS!$B$5:$B$400="REGALO")*(MOVIMIENTOS!$C$5:$C$400="A")*(MOVIMIENTOS!$D$5:$D$400="jabas")*(MOVIMIENTOS!$A$5:$A$400<>"")*(MOVIMIENTOS!$A$5:$A$400<=$A7)*MOVIMIENTOS!$E$5:$E$400)-SUMPRODUCT((MOVIMIENTOS!$B$5:$B$400="VENTA")*(MOVIMIENTOS!$C$5:$C$400="A")*(MOVIMIENTOS!$D$5:$D$400="jabas")*(MOVIMIENTOS!$A$5:$A$400<>"")*(MOVIMIENTOS!$A$5:$A$400<=$A7)*MOVIMIENTOS!$E$5:$E$400)+SUMPRODUCT((MOVIMIENTOS!$B$5:$B$400="AJUSTE")*(MOVIMIENTOS!$C$5:$C$400="A")*(MOVIMIENTOS!$D$5:$D$400="jabas")*(MOVIMIENTOS!$A$5:$A$400<>"")*(MOVIMIENTOS!$A$5:$A$400<=$A7)*MOVIMIENTOS!$E$5:$E$400)) -> 34 | C7: =IF($A7="","",SUMPRODUCT((MOVIMIENTOS!$B$5:$B$400="SALDO INICIAL")*(MOVIMIENTOS!$C$5:$C$400="P")*(MOVIMIENTOS!$D$5:$D$400="jabas")*(MOVIMIENTOS!$A$5:$A$400<>"")*(MOVIMIENTOS!$A$5:$A$400<=$A7)*MOVIMIENTOS!$E$5:$E$400)+SUMPRODUCT((MOVIMIENTOS!$B$5:$B$400="PROCESO")*(MOVIMIENTOS!$C$5:$C$400="P")*(MOVIMIENTOS!$D$5:$D$400="jabas")*(MOVIMIENTOS!$A$5:$A$400<>"")*(MOVIMIENTOS!$A$5:$A$400<=$A7)*MOVIMIENTOS!$E$5:$E$400)-SUMPRODUCT((MOVIMIENTOS!$B$5:$B$400="ENVÍO A SUPESA")*(MOVIMIENTOS!$C$5:$C$400="P")*(MOVIMIENTOS!$D$5:$D$400="jabas")*(MOVIMIENTOS!$A$5:$A$400<>"")*(MOVIMIENTOS!$A$5:$A$400<=$A7)*MOVIMIENTOS!$E$5:$E$400)+SUMPRODUCT((MOVIMIENTOS!$B$5:$B$400="DEVOLUCIÓN")*(MOVIMIENTOS!$C$5:$C$400="P")*(MOVIMIENTOS!$D$5:$D$400="jabas")*(MOVIMIENTOS!$A$5:$A$400<>"")*(MOVIMIENTOS!$A$5:$A$400<=$A7)*MOVIMIENTOS!$E$5:$E$400)-SUMPRODUCT((MOVIMIENTOS!$B$5:$B$400="TRASIEGO")*(MOVIMIENTOS!$C$5:$C$400="P")*(MOVIMIENTOS!$D$5:$D$400="jabas")*(MOVIMIENTOS!$A$5:$A$400<>"")*(MOVIMIENTOS!$A$5:$A$400<=$A7)*MOVIMIENTOS!$E$5:$E$400)-SUMPRODUCT((MOVIMIENTOS!$B$5:$B$400="REGALO")*(MOVIMIENTOS!$C$5:$C$400="P")*(MOVIMIENTOS!$D$5:$D$400="jabas")*(MOVIMIENTOS!$A$5:$A$400<>"")*(MOVIMIENTOS!$A$5:$A$400<=$A7)*MOVIMIENTOS!$E$5:$E$400)-SUMPRODUCT((MOVIMIENTOS!$B$5:$B$400="VENTA")*(MOVIMIENTOS!$C$5:$C$400="P")*(MOVIMIENTOS!$D$5:$D$400="jabas")*(MOVIMIENTOS!$A$5:$A$400<>"")*(MOVIMIENTOS!$A$5:$A$400<=$A7)*MOVIMIENTOS!$E$5:$E$400)+SUMPRODUCT((MOVIMIENTOS!$B$5:$B$400="AJUSTE")*(MOVIMIENTOS!$C$5:$C$400="P")*(MOVIMIENTOS!$D$5:$D$400="jabas")*(MOVIMIENTOS!$A$5:$A$400<>"")*(MOVIMIENTOS!$A$5:$A$400<=$A7)*MOVIMIENTOS!$E$5:$E$400)) -> 0 | D7: =IF($A7="","",SUMPRODUCT((MOVIMIENTOS!$B$5:$B$400="SALDO INICIAL")*(MOVIMIENTOS!$C$5:$C$400="C")*(MOVIMIENTOS!$D$5:$D$400="jabas")*(MOVIMIENTOS!$A$5:$A$400<>"")*(MOVIMIENTOS!$A$5:$A$400<=$A7)*MOVIMIENTOS!$E$5:$E$400)+SUMPRODUCT((MOVIMIENTOS!$B$5:$B$400="PROCESO")*(MOVIMIENTOS!$C$5:$C$400="C")*(MOVIMIENTOS!$D$5:$D$400="jabas")*(MOVIMIENTOS!$A$5:$A$400<>"")*(MOVIMIENTOS!$A$5:$A$400<=$A7)*MOVIMIENTOS!$E$5:$E$400)-SUMPRODUCT((MOVIMIENTOS!$B$5:$B$400="ENVÍO A SUPESA")*(MOVIMIENTOS!$C$5:$C$400="C")*(MOVIMIENTOS!$D$5:$D$400="jabas")*(MOVIMIENTOS!$A$5:$A$400<>"")*(MOVIMIENTOS!$A$5:$A$400<=$A7)*MOVIMIENTOS!$E$5:$E$400)+SUMPRODUCT((MOVIMIENTOS!$B$5:$B$400="DEVOLUCIÓN")*(MOVIMIENTOS!$C$5:$C$400="C")*(MOVIMIENTOS!$D$5:$D$400="jabas")*(MOVIMIENTOS!$A$5:$A$400<>"")*(MOVIMIENTOS!$A$5:$A$400<=$A7)*MOVIMIENTOS!$E$5:$E$400)-SUMPRODUCT((MOVIMIENTOS!$B$5:$B$400="TRASIEGO")*(MOVIMIENTOS!$C$5:$C$400="C")*(MOVIMIENTOS!$D$5:$D$400="jabas")*(MOVIMIENTOS!$A$5:$A$400<>"")*(MOVIMIENTOS!$A$5:$A$400<=$A7)*MOVIMIENTOS!$E$5:$E$400)-SUMPRODUCT((MOVIMIENTOS!$B$5:$B$400="REGALO")*(MOVIMIENTOS!$C$5:$C$400="C")*(MOVIMIENTOS!$D$5:$D$400="jabas")*(MOVIMIENTOS!$A$5:$A$400<>"")*(MOVIMIENTOS!$A$5:$A$400<=$A7)*MOVIMIENTOS!$E$5:$E$400)-SUMPRODUCT((MOVIMIENTOS!$B$5:$B$400="VENTA")*(MOVIMIENTOS!$C$5:$C$400="C")*(MOVIMIENTOS!$D$5:$D$400="jabas")*(MOVIMIENTOS!$A$5:$A$400<>"")*(MOVIMIENTOS!$A$5:$A$400<=$A7)*MOVIMIENTOS!$E$5:$E$400)+SUMPRODUCT((MOVIMIENTOS!$B$5:$B$400="AJUSTE")*(MOVIMIENTOS!$C$5:$C$400="C")*(MOVIMIENTOS!$D$5:$D$400="jabas")*(MOVIMIENTOS!$A$5:$A$400<>"")*(MOVIMIENTOS!$A$5:$A$400<=$A7)*MOVIMIENTOS!$E$5:$E$400)) -> 0 | E7: =IF($A7="","",SUMPRODUCT((MOVIMIENTOS!$B$5:$B$400="SALDO INICIAL")*(MOVIMIENTOS!$C$5:$C$400="M")*(MOVIMIENTOS!$D$5:$D$400="jabas")*(MOVIMIENTOS!$A$5:$A$400<>"")*(MOVIMIENTOS!$A$5:$A$400<=$A7)*MOVIMIENTOS!$E$5:$E$400)+SUMPRODUCT((MOVIMIENTOS!$B$5:$B$400="PROCESO")*(MOVIMIENTOS!$C$5:$C$400="M")*(MOVIMIENTOS!$D$5:$D$400="jabas")*(MOVIMIENTOS!$A$5:$A$400<>"")*(MOVIMIENTOS!$A$5:$A$400<=$A7)*MOVIMIENTOS!$E$5:$E$400)-SUMPRODUCT((MOVIMIENTOS!$B$5:$B$400="ENVÍO A SUPESA")*(MOVIMIENTOS!$C$5:$C$400="M")*(MOVIMIENTOS!$D$5:$D$400="jabas")*(MOVIMIENTOS!$A$5:$A$400<>"")*(MOVIMIENTOS!$A$5:$A$400<=$A7)*MOVIMIENTOS!$E$5:$E$400)+SUMPRODUCT((MOVIMIENTOS!$B$5:$B$400="DEVOLUCIÓN")*(MOVIMIENTOS!$C$5:$C$400="M")*(MOVIMIENTOS!$D$5:$D$400="jabas")*(MOVIMIENTOS!$A$5:$A$400<>"")*(MOVIMIENTOS!$A$5:$A$400<=$A7)*MOVIMIENTOS!$E$5:$E$400)-SUMPRODUCT((MOVIMIENTOS!$B$5:$B$400="TRASIEGO")*(MOVIMIENTOS!$C$5:$C$400="M")*(MOVIMIENTOS!$D$5:$D$400="jabas")*(MOVIMIENTOS!$A$5:$A$400<>"")*(MOVIMIENTOS!$A$5:$A$400<=$A7)*MOVIMIENTOS!$E$5:$E$400)-SUMPRODUCT((MOVIMIENTOS!$B$5:$B$400="REGALO")*(MOVIMIENTOS!$C$5:$C$400="M")*(MOVIMIENTOS!$D$5:$D$400="jabas")*(MOVIMIENTOS!$A$5:$A$400<>"")*(MOVIMIENTOS!$A$5:$A$400<=$A7)*MOVIMIENTOS!$E$5:$E$400)-SUMPRODUCT((MOVIMIENTOS!$B$5:$B$400="VENTA")*(MOVIMIENTOS!$C$5:$C$400="M")*(MOVIMIENTOS!$D$5:$D$400="jabas")*(MOVIMIENTOS!$A$5:$A$400<>"")*(MOVIMIENTOS!$A$5:$A$400<=$A7)*MOVIMIENTOS!$E$5:$E$400)+SUMPRODUCT((MOVIMIENTOS!$B$5:$B$400="AJUSTE")*(MOVIMIENTOS!$C$5:$C$400="M")*(MOVIMIENTOS!$D$5:$D$400="jabas")*(MOVIMIENTOS!$A$5:$A$400<>"")*(MOVIMIENTOS!$A$5:$A$400<=$A7)*MOVIMIENTOS!$E$5:$E$400)) -> 43 | F7: =IF($A7="","",SUMPRODUCT((MOVIMIENTOS!$B$5:$B$400="SALDO INICIAL")*(MOVIMIENTOS!$C$5:$C$400="Chancho")*(MOVIMIENTOS!$D$5:$D$400="sacos")*(MOVIMIENTOS!$A$5:$A$400<>"")*(MOVIMIENTOS!$A$5:$A$400<=$A7)*MOVIMIENTOS!$E$5:$E$400)+SUMPRODUCT((MOVIMIENTOS!$B$5:$B$400="PROCESO")*(MOVIMIENTOS!$C$5:$C$400="Chancho")*(MOVIMIENTOS!$D$5:$D$400="sacos")*(MOVIMIENTOS!$A$5:$A$400<>"")*(MOVIMIENTOS!$A$5:$A$400<=$A7)*MOVIMIENTOS!$E$5:$E$400)-SUMPRODUCT((MOVIMIENTOS!$B$5:$B$400="VENTA CHANCHO")*(MOVIMIENTOS!$C$5:$C$400="Chancho")*(MOVIMIENTOS!$D$5:$D$400="sacos")*(MOVIMIENTOS!$A$5:$A$400<>"")*(MOVIMIENTOS!$A$5:$A$400<=$A7)*MOVIMIENTOS!$E$5:$E$400)-SUMPRODUCT((MOVIMIENTOS!$B$5:$B$400="REGALO")*(MOVIMIENTOS!$C$5:$C$400="Chancho")*(MOVIMIENTOS!$D$5:$D$400="sacos")*(MOVIMIENTOS!$A$5:$A$400<>"")*(MOVIMIENTOS!$A$5:$A$400<=$A7)*MOVIMIENTOS!$E$5:$E$400)-SUMPRODUCT((MOVIMIENTOS!$B$5:$B$400="VENTA")*(MOVIMIENTOS!$C$5:$C$400="Chancho")*(MOVIMIENTOS!$D$5:$D$400="sacos")*(MOVIMIENTOS!$A$5:$A$400<>"")*(MOVIMIENTOS!$A$5:$A$400<=$A7)*MOVIMIENTOS!$E$5:$E$400)+SUMPRODUCT((MOVIMIENTOS!$B$5:$B$400="AJUSTE")*(MOVIMIENTOS!$C$5:$C$400="Chancho")*(MOVIMIENTOS!$D$5:$D$400="sacos")*(MOVIMIENTOS!$A$5:$A$400<>"")*(MOVIMIENTOS!$A$5:$A$400<=$A7)*MOVIMIENTOS!$E$5:$E$400)) -> 28 | G7: =IF($A7="","",SUM(B7:E7)) -> 77 | H7: =IF($A7="","",SUMPRODUCT((((MOVIMIENTOS!$B$5:$B$400="SALDO INICIAL")*(MOVIMIENTOS!$C$5:$C$400<>"Chancho"))+(MOVIMIENTOS!$B$5:$B$400="COMPRA")+(MOVIMIENTOS!$B$5:$B$400="REPROCESO")+(MOVIMIENTOS!$B$5:$B$400="DEVOLUCIÓN")+((MOVIMIENTOS!$B$5:$B$400="AJUSTE")*(MOVIMIENTOS!$C$5:$C$400<>"Chancho")))*(MOVIMIENTOS!$A$5:$A$400<>"")*(MOVIMIENTOS!$A$5:$A$400<=$A7)*MOVIMIENTOS!$I$5:$I$400)-SUMPRODUCT(((MOVIMIENTOS!$B$5:$B$400="ENVÍO A SUPESA")+(MOVIMIENTOS!$B$5:$B$400="ENVÍO A TOTTUS")+(MOVIMIENTOS!$B$5:$B$400="ENVIO A TOTTUS")+(MOVIMIENTOS!$B$5:$B$400="MALOGRADO")+(MOVIMIENTOS!$B$5:$B$400="OTRA SALIDA")+((MOVIMIENTOS!$B$5:$B$400="PROCESO")*(MOVIMIENTOS!$C$5:$C$400="Chancho"))+((MOVIMIENTOS!$B$5:$B$400="REGALO")*(MOVIMIENTOS!$C$5:$C$400<>"Chancho"))+((MOVIMIENTOS!$B$5:$B$400="VENTA")*(MOVIMIENTOS!$C$5:$C$400<>"Chancho")))*(MOVIMIENTOS!$A$5:$A$400<>"")*(MOVIMIENTOS!$A$5:$A$400<=$A7)*MOVIMIENTOS!$I$5:$I$400)) -> 1003 | J7: =IF(AND(MOVIMIENTOS!$A7<>"",COUNTIF(MOVIMIENTOS!$A$5:$A6,MOVIMIENTOS!$A7)=0),COUNT(J$4:J6)+1,"") | K7: =MOVIMIENTOS!$A7 -> 46214
A8: =IFERROR(INDEX(K$5:K$400,MATCH(ROW()-4,J$5:J$400,0)),"") -> 46217 | B8: =IF($A8="","",SUMPRODUCT((MOVIMIENTOS!$B$5:$B$400="SALDO INICIAL")*(MOVIMIENTOS!$C$5:$C$400="A")*(MOVIMIENTOS!$D$5:$D$400="jabas")*(MOVIMIENTOS!$A$5:$A$400<>"")*(MOVIMIENTOS!$A$5:$A$400<=$A8)*MOVIMIENTOS!$E$5:$E$400)+SUMPRODUCT((MOVIMIENTOS!$B$5:$B$400="PROCESO")*(MOVIMIENTOS!$C$5:$C$400="A")*(MOVIMIENTOS!$D$5:$D$400="jabas")*(MOVIMIENTOS!$A$5:$A$400<>"")*(MOVIMIENTOS!$A$5:$A$400<=$A8)*MOVIMIENTOS!$E$5:$E$400)-SUMPRODUCT((MOVIMIENTOS!$B$5:$B$400="ENVÍO A SUPESA")*(MOVIMIENTOS!$C$5:$C$400="A")*(MOVIMIENTOS!$D$5:$D$400="jabas")*(MOVIMIENTOS!$A$5:$A$400<>"")*(MOVIMIENTOS!$A$5:$A$400<=$A8)*MOVIMIENTOS!$E$5:$E$400)+SUMPRODUCT((MOVIMIENTOS!$B$5:$B$400="DEVOLUCIÓN")*(MOVIMIENTOS!$C$5:$C$400="A")*(MOVIMIENTOS!$D$5:$D$400="jabas")*(MOVIMIENTOS!$A$5:$A$400<>"")*(MOVIMIENTOS!$A$5:$A$400<=$A8)*MOVIMIENTOS!$E$5:$E$400)-SUMPRODUCT((MOVIMIENTOS!$B$5:$B$400="TRASIEGO")*(MOVIMIENTOS!$C$5:$C$400="A")*(MOVIMIENTOS!$D$5:$D$400="jabas")*(MOVIMIENTOS!$A$5:$A$400<>"")*(MOVIMIENTOS!$A$5:$A$400<=$A8)*MOVIMIENTOS!$E$5:$E$400)-SUMPRODUCT((MOVIMIENTOS!$B$5:$B$400="REGALO")*(MOVIMIENTOS!$C$5:$C$400="A")*(MOVIMIENTOS!$D$5:$D$400="jabas")*(MOVIMIENTOS!$A$5:$A$400<>"")*(MOVIMIENTOS!$A$5:$A$400<=$A8)*MOVIMIENTOS!$E$5:$E$400)-SUMPRODUCT((MOVIMIENTOS!$B$5:$B$400="VENTA")*(MOVIMIENTOS!$C$5:$C$400="A")*(MOVIMIENTOS!$D$5:$D$400="jabas")*(MOVIMIENTOS!$A$5:$A$400<>"")*(MOVIMIENTOS!$A$5:$A$400<=$A8)*MOVIMIENTOS!$E$5:$E$400)+SUMPRODUCT((MOVIMIENTOS!$B$5:$B$400="AJUSTE")*(MOVIMIENTOS!$C$5:$C$400="A")*(MOVIMIENTOS!$D$5:$D$400="jabas")*(MOVIMIENTOS!$A$5:$A$400<>"")*(MOVIMIENTOS!$A$5:$A$400<=$A8)*MOVIMIENTOS!$E$5:$E$400)) -> 12 | C8: =IF($A8="","",SUMPRODUCT((MOVIMIENTOS!$B$5:$B$400="SALDO INICIAL")*(MOVIMIENTOS!$C$5:$C$400="P")*(MOVIMIENTOS!$D$5:$D$400="jabas")*(MOVIMIENTOS!$A$5:$A$400<>"")*(MOVIMIENTOS!$A$5:$A$400<=$A8)*MOVIMIENTOS!$E$5:$E$400)+SUMPRODUCT((MOVIMIENTOS!$B$5:$B$400="PROCESO")*(MOVIMIENTOS!$C$5:$C$400="P")*(MOVIMIENTOS!$D$5:$D$400="jabas")*(MOVIMIENTOS!$A$5:$A$400<>"")*(MOVIMIENTOS!$A$5:$A$400<=$A8)*MOVIMIENTOS!$E$5:$E$400)-SUMPRODUCT((MOVIMIENTOS!$B$5:$B$400="ENVÍO A SUPESA")*(MOVIMIENTOS!$C$5:$C$400="P")*(MOVIMIENTOS!$D$5:$D$400="jabas")*(MOVIMIENTOS!$A$5:$A$400<>"")*(MOVIMIENTOS!$A$5:$A$400<=$A8)*MOVIMIENTOS!$E$5:$E$400)+SUMPRODUCT((MOVIMIENTOS!$B$5:$B$400="DEVOLUCIÓN")*(MOVIMIENTOS!$C$5:$C$400="P")*(MOVIMIENTOS!$D$5:$D$400="jabas")*(MOVIMIENTOS!$A$5:$A$400<>"")*(MOVIMIENTOS!$A$5:$A$400<=$A8)*MOVIMIENTOS!$E$5:$E$400)-SUMPRODUCT((MOVIMIENTOS!$B$5:$B$400="TRASIEGO")*(MOVIMIENTOS!$C$5:$C$400="P")*(MOVIMIENTOS!$D$5:$D$400="jabas")*(MOVIMIENTOS!$A$5:$A$400<>"")*(MOVIMIENTOS!$A$5:$A$400<=$A8)*MOVIMIENTOS!$E$5:$E$400)-SUMPRODUCT((MOVIMIENTOS!$B$5:$B$400="REGALO")*(MOVIMIENTOS!$C$5:$C$400="P")*(MOVIMIENTOS!$D$5:$D$400="jabas")*(MOVIMIENTOS!$A$5:$A$400<>"")*(MOVIMIENTOS!$A$5:$A$400<=$A8)*MOVIMIENTOS!$E$5:$E$400)-SUMPRODUCT((MOVIMIENTOS!$B$5:$B$400="VENTA")*(MOVIMIENTOS!$C$5:$C$400="P")*(MOVIMIENTOS!$D$5:$D$400="jabas")*(MOVIMIENTOS!$A$5:$A$400<>"")*(MOVIMIENTOS!$A$5:$A$400<=$A8)*MOVIMIENTOS!$E$5:$E$400)+SUMPRODUCT((MOVIMIENTOS!$B$5:$B$400="AJUSTE")*(MOVIMIENTOS!$C$5:$C$400="P")*(MOVIMIENTOS!$D$5:$D$400="jabas")*(MOVIMIENTOS!$A$5:$A$400<>"")*(MOVIMIENTOS!$A$5:$A$400<=$A8)*MOVIMIENTOS!$E$5:$E$400)) -> 0 | D8: =IF($A8="","",SUMPRODUCT((MOVIMIENTOS!$B$5:$B$400="SALDO INICIAL")*(MOVIMIENTOS!$C$5:$C$400="C")*(MOVIMIENTOS!$D$5:$D$400="jabas")*(MOVIMIENTOS!$A$5:$A$400<>"")*(MOVIMIENTOS!$A$5:$A$400<=$A8)*MOVIMIENTOS!$E$5:$E$400)+SUMPRODUCT((MOVIMIENTOS!$B$5:$B$400="PROCESO")*(MOVIMIENTOS!$C$5:$C$400="C")*(MOVIMIENTOS!$D$5:$D$400="jabas")*(MOVIMIENTOS!$A$5:$A$400<>"")*(MOVIMIENTOS!$A$5:$A$400<=$A8)*MOVIMIENTOS!$E$5:$E$400)-SUMPRODUCT((MOVIMIENTOS!$B$5:$B$400="ENVÍO A SUPESA")*(MOVIMIENTOS!$C$5:$C$400="C")*(MOVIMIENTOS!$D$5:$D$400="jabas")*(MOVIMIENTOS!$A$5:$A$400<>"")*(MOVIMIENTOS!$A$5:$A$400<=$A8)*MOVIMIENTOS!$E$5:$E$400)+SUMPRODUCT((MOVIMIENTOS!$B$5:$B$400="DEVOLUCIÓN")*(MOVIMIENTOS!$C$5:$C$400="C")*(MOVIMIENTOS!$D$5:$D$400="jabas")*(MOVIMIENTOS!$A$5:$A$400<>"")*(MOVIMIENTOS!$A$5:$A$400<=$A8)*MOVIMIENTOS!$E$5:$E$400)-SUMPRODUCT((MOVIMIENTOS!$B$5:$B$400="TRASIEGO")*(MOVIMIENTOS!$C$5:$C$400="C")*(MOVIMIENTOS!$D$5:$D$400="jabas")*(MOVIMIENTOS!$A$5:$A$400<>"")*(MOVIMIENTOS!$A$5:$A$400<=$A8)*MOVIMIENTOS!$E$5:$E$400)-SUMPRODUCT((MOVIMIENTOS!$B$5:$B$400="REGALO")*(MOVIMIENTOS!$C$5:$C$400="C")*(MOVIMIENTOS!$D$5:$D$400="jabas")*(MOVIMIENTOS!$A$5:$A$400<>"")*(MOVIMIENTOS!$A$5:$A$400<=$A8)*MOVIMIENTOS!$E$5:$E$400)-SUMPRODUCT((MOVIMIENTOS!$B$5:$B$400="VENTA")*(MOVIMIENTOS!$C$5:$C$400="C")*(MOVIMIENTOS!$D$5:$D$400="jabas")*(MOVIMIENTOS!$A$5:$A$400<>"")*(MOVIMIENTOS!$A$5:$A$400<=$A8)*MOVIMIENTOS!$E$5:$E$400)+SUMPRODUCT((MOVIMIENTOS!$B$5:$B$400="AJUSTE")*(MOVIMIENTOS!$C$5:$C$400="C")*(MOVIMIENTOS!$D$5:$D$400="jabas")*(MOVIMIENTOS!$A$5:$A$400<>"")*(MOVIMIENTOS!$A$5:$A$400<=$A8)*MOVIMIENTOS!$E$5:$E$400)) -> 0 | E8: =IF($A8="","",SUMPRODUCT((MOVIMIENTOS!$B$5:$B$400="SALDO INICIAL")*(MOVIMIENTOS!$C$5:$C$400="M")*(MOVIMIENTOS!$D$5:$D$400="jabas")*(MOVIMIENTOS!$A$5:$A$400<>"")*(MOVIMIENTOS!$A$5:$A$400<=$A8)*MOVIMIENTOS!$E$5:$E$400)+SUMPRODUCT((MOVIMIENTOS!$B$5:$B$400="PROCESO")*(MOVIMIENTOS!$C$5:$C$400="M")*(MOVIMIENTOS!$D$5:$D$400="jabas")*(MOVIMIENTOS!$A$5:$A$400<>"")*(MOVIMIENTOS!$A$5:$A$400<=$A8)*MOVIMIENTOS!$E$5:$E$400)-SUMPRODUCT((MOVIMIENTOS!$B$5:$B$400="ENVÍO A SUPESA")*(MOVIMIENTOS!$C$5:$C$400="M")*(MOVIMIENTOS!$D$5:$D$400="jabas")*(MOVIMIENTOS!$A$5:$A$400<>"")*(MOVIMIENTOS!$A$5:$A$400<=$A8)*MOVIMIENTOS!$E$5:$E$400)+SUMPRODUCT((MOVIMIENTOS!$B$5:$B$400="DEVOLUCIÓN")*(MOVIMIENTOS!$C$5:$C$400="M")*(MOVIMIENTOS!$D$5:$D$400="jabas")*(MOVIMIENTOS!$A$5:$A$400<>"")*(MOVIMIENTOS!$A$5:$A$400<=$A8)*MOVIMIENTOS!$E$5:$E$400)-SUMPRODUCT((MOVIMIENTOS!$B$5:$B$400="TRASIEGO")*(MOVIMIENTOS!$C$5:$C$400="M")*(MOVIMIENTOS!$D$5:$D$400="jabas")*(MOVIMIENTOS!$A$5:$A$400<>"")*(MOVIMIENTOS!$A$5:$A$400<=$A8)*MOVIMIENTOS!$E$5:$E$400)-SUMPRODUCT((MOVIMIENTOS!$B$5:$B$400="REGALO")*(MOVIMIENTOS!$C$5:$C$400="M")*(MOVIMIENTOS!$D$5:$D$400="jabas")*(MOVIMIENTOS!$A$5:$A$400<>"")*(MOVIMIENTOS!$A$5:$A$400<=$A8)*MOVIMIENTOS!$E$5:$E$400)-SUMPRODUCT((MOVIMIENTOS!$B$5:$B$400="VENTA")*(MOVIMIENTOS!$C$5:$C$400="M")*(MOVIMIENTOS!$D$5:$D$400="jabas")*(MOVIMIENTOS!$A$5:$A$400<>"")*(MOVIMIENTOS!$A$5:$A$400<=$A8)*MOVIMIENTOS!$E$5:$E$400)+SUMPRODUCT((MOVIMIENTOS!$B$5:$B$400="AJUSTE")*(MOVIMIENTOS!$C$5:$C$400="M")*(MOVIMIENTOS!$D$5:$D$400="jabas")*(MOVIMIENTOS!$A$5:$A$400<>"")*(MOVIMIENTOS!$A$5:$A$400<=$A8)*MOVIMIENTOS!$E$5:$E$400)) -> 48 | F8: =IF($A8="","",SUMPRODUCT((MOVIMIENTOS!$B$5:$B$400="SALDO INICIAL")*(MOVIMIENTOS!$C$5:$C$400="Chancho")*(MOVIMIENTOS!$D$5:$D$400="sacos")*(MOVIMIENTOS!$A$5:$A$400<>"")*(MOVIMIENTOS!$A$5:$A$400<=$A8)*MOVIMIENTOS!$E$5:$E$400)+SUMPRODUCT((MOVIMIENTOS!$B$5:$B$400="PROCESO")*(MOVIMIENTOS!$C$5:$C$400="Chancho")*(MOVIMIENTOS!$D$5:$D$400="sacos")*(MOVIMIENTOS!$A$5:$A$400<>"")*(MOVIMIENTOS!$A$5:$A$400<=$A8)*MOVIMIENTOS!$E$5:$E$400)-SUMPRODUCT((MOVIMIENTOS!$B$5:$B$400="VENTA CHANCHO")*(MOVIMIENTOS!$C$5:$C$400="Chancho")*(MOVIMIENTOS!$D$5:$D$400="sacos")*(MOVIMIENTOS!$A$5:$A$400<>"")*(MOVIMIENTOS!$A$5:$A$400<=$A8)*MOVIMIENTOS!$E$5:$E$400)-SUMPRODUCT((MOVIMIENTOS!$B$5:$B$400="REGALO")*(MOVIMIENTOS!$C$5:$C$400="Chancho")*(MOVIMIENTOS!$D$5:$D$400="sacos")*(MOVIMIENTOS!$A$5:$A$400<>"")*(MOVIMIENTOS!$A$5:$A$400<=$A8)*MOVIMIENTOS!$E$5:$E$400)-SUMPRODUCT((MOVIMIENTOS!$B$5:$B$400="VENTA")*(MOVIMIENTOS!$C$5:$C$400="Chancho")*(MOVIMIENTOS!$D$5:$D$400="sacos")*(MOVIMIENTOS!$A$5:$A$400<>"")*(MOVIMIENTOS!$A$5:$A$400<=$A8)*MOVIMIENTOS!$E$5:$E$400)+SUMPRODUCT((MOVIMIENTOS!$B$5:$B$400="AJUSTE")*(MOVIMIENTOS!$C$5:$C$400="Chancho")*(MOVIMIENTOS!$D$5:$D$400="sacos")*(MOVIMIENTOS!$A$5:$A$400<>"")*(MOVIMIENTOS!$A$5:$A$400<=$A8)*MOVIMIENTOS!$E$5:$E$400)) -> 35 | G8: =IF($A8="","",SUM(B8:E8)) -> 60 | H8: =IF($A8="","",SUMPRODUCT((((MOVIMIENTOS!$B$5:$B$400="SALDO INICIAL")*(MOVIMIENTOS!$C$5:$C$400<>"Chancho"))+(MOVIMIENTOS!$B$5:$B$400="COMPRA")+(MOVIMIENTOS!$B$5:$B$400="REPROCESO")+(MOVIMIENTOS!$B$5:$B$400="DEVOLUCIÓN")+((MOVIMIENTOS!$B$5:$B$400="AJUSTE")*(MOVIMIENTOS!$C$5:$C$400<>"Chancho")))*(MOVIMIENTOS!$A$5:$A$400<>"")*(MOVIMIENTOS!$A$5:$A$400<=$A8)*MOVIMIENTOS!$I$5:$I$400)-SUMPRODUCT(((MOVIMIENTOS!$B$5:$B$400="ENVÍO A SUPESA")+(MOVIMIENTOS!$B$5:$B$400="ENVÍO A TOTTUS")+(MOVIMIENTOS!$B$5:$B$400="ENVIO A TOTTUS")+(MOVIMIENTOS!$B$5:$B$400="MALOGRADO")+(MOVIMIENTOS!$B$5:$B$400="OTRA SALIDA")+((MOVIMIENTOS!$B$5:$B$400="PROCESO")*(MOVIMIENTOS!$C$5:$C$400="Chancho"))+((MOVIMIENTOS!$B$5:$B$400="REGALO")*(MOVIMIENTOS!$C$5:$C$400<>"Chancho"))+((MOVIMIENTOS!$B$5:$B$400="VENTA")*(MOVIMIENTOS!$C$5:$C$400<>"Chancho")))*(MOVIMIENTOS!$A$5:$A$400<>"")*(MOVIMIENTOS!$A$5:$A$400<=$A8)*MOVIMIENTOS!$I$5:$I$400)) -> 825 | J8: =IF(AND(MOVIMIENTOS!$A8<>"",COUNTIF(MOVIMIENTOS!$A$5:$A7,MOVIMIENTOS!$A8)=0),COUNT(J$4:J7)+1,"") | K8: =MOVIMIENTOS!$A8 -> 46214
A9: =IFERROR(INDEX(K$5:K$400,MATCH(ROW()-4,J$5:J$400,0)),"") -> 46218 | B9: =IF($A9="","",SUMPRODUCT((MOVIMIENTOS!$B$5:$B$400="SALDO INICIAL")*(MOVIMIENTOS!$C$5:$C$400="A")*(MOVIMIENTOS!$D$5:$D$400="jabas")*(MOVIMIENTOS!$A$5:$A$400<>"")*(MOVIMIENTOS!$A$5:$A$400<=$A9)*MOVIMIENTOS!$E$5:$E$400)+SUMPRODUCT((MOVIMIENTOS!$B$5:$B$400="PROCESO")*(MOVIMIENTOS!$C$5:$C$400="A")*(MOVIMIENTOS!$D$5:$D$400="jabas")*(MOVIMIENTOS!$A$5:$A$400<>"")*(MOVIMIENTOS!$A$5:$A$400<=$A9)*MOVIMIENTOS!$E$5:$E$400)-SUMPRODUCT((MOVIMIENTOS!$B$5:$B$400="ENVÍO A SUPESA")*(MOVIMIENTOS!$C$5:$C$400="A")*(MOVIMIENTOS!$D$5:$D$400="jabas")*(MOVIMIENTOS!$A$5:$A$400<>"")*(MOVIMIENTOS!$A$5:$A$400<=$A9)*MOVIMIENTOS!$E$5:$E$400)+SUMPRODUCT((MOVIMIENTOS!$B$5:$B$400="DEVOLUCIÓN")*(MOVIMIENTOS!$C$5:$C$400="A")*(MOVIMIENTOS!$D$5:$D$400="jabas")*(MOVIMIENTOS!$A$5:$A$400<>"")*(MOVIMIENTOS!$A$5:$A$400<=$A9)*MOVIMIENTOS!$E$5:$E$400)-SUMPRODUCT((MOVIMIENTOS!$B$5:$B$400="TRASIEGO")*(MOVIMIENTOS!$C$5:$C$400="A")*(MOVIMIENTOS!$D$5:$D$400="jabas")*(MOVIMIENTOS!$A$5:$A$400<>"")*(MOVIMIENTOS!$A$5:$A$400<=$A9)*MOVIMIENTOS!$E$5:$E$400)-SUMPRODUCT((MOVIMIENTOS!$B$5:$B$400="REGALO")*(MOVIMIENTOS!$C$5:$C$400="A")*(MOVIMIENTOS!$D$5:$D$400="jabas")*(MOVIMIENTOS!$A$5:$A$400<>"")*(MOVIMIENTOS!$A$5:$A$400<=$A9)*MOVIMIENTOS!$E$5:$E$400)-SUMPRODUCT((MOVIMIENTOS!$B$5:$B$400="VENTA")*(MOVIMIENTOS!$C$5:$C$400="A")*(MOVIMIENTOS!$D$5:$D$400="jabas")*(MOVIMIENTOS!$A$5:$A$400<>"")*(MOVIMIENTOS!$A$5:$A$400<=$A9)*MOVIMIENTOS!$E$5:$E$400)+SUMPRODUCT((MOVIMIENTOS!$B$5:$B$400="AJUSTE")*(MOVIMIENTOS!$C$5:$C$400="A")*(MOVIMIENTOS!$D$5:$D$400="jabas")*(MOVIMIENTOS!$A$5:$A$400<>"")*(MOVIMIENTOS!$A$5:$A$400<=$A9)*MOVIMIENTOS!$E$5:$E$400)) -> 24 | C9: =IF($A9="","",SUMPRODUCT((MOVIMIENTOS!$B$5:$B$400="SALDO INICIAL")*(MOVIMIENTOS!$C$5:$C$400="P")*(MOVIMIENTOS!$D$5:$D$400="jabas")*(MOVIMIENTOS!$A$5:$A$400<>"")*(MOVIMIENTOS!$A$5:$A$400<=$A9)*MOVIMIENTOS!$E$5:$E$400)+SUMPRODUCT((MOVIMIENTOS!$B$5:$B$400="PROCESO")*(MOVIMIENTOS!$C$5:$C$400="P")*(MOVIMIENTOS!$D$5:$D$400="jabas")*(MOVIMIENTOS!$A$5:$A$400<>"")*(MOVIMIENTOS!$A$5:$A$400<=$A9)*MOVIMIENTOS!$E$5:$E$400)-SUMPRODUCT((MOVIMIENTOS!$B$5:$B$400="ENVÍO A SUPESA")*(MOVIMIENTOS!$C$5:$C$400="P")*(MOVIMIENTOS!$D$5:$D$400="jabas")*(MOVIMIENTOS!$A$5:$A$400<>"")*(MOVIMIENTOS!$A$5:$A$400<=$A9)*MOVIMIENTOS!$E$5:$E$400)+SUMPRODUCT((MOVIMIENTOS!$B$5:$B$400="DEVOLUCIÓN")*(MOVIMIENTOS!$C$5:$C$400="P")*(MOVIMIENTOS!$D$5:$D$400="jabas")*(MOVIMIENTOS!$A$5:$A$400<>"")*(MOVIMIENTOS!$A$5:$A$400<=$A9)*MOVIMIENTOS!$E$5:$E$400)-SUMPRODUCT((MOVIMIENTOS!$B$5:$B$400="TRASIEGO")*(MOVIMIENTOS!$C$5:$C$400="P")*(MOVIMIENTOS!$D$5:$D$400="jabas")*(MOVIMIENTOS!$A$5:$A$400<>"")*(MOVIMIENTOS!$A$5:$A$400<=$A9)*MOVIMIENTOS!$E$5:$E$400)-SUMPRODUCT((MOVIMIENTOS!$B$5:$B$400="REGALO")*(MOVIMIENTOS!$C$5:$C$400="P")*(MOVIMIENTOS!$D$5:$D$400="jabas")*(MOVIMIENTOS!$A$5:$A$400<>"")*(MOVIMIENTOS!$A$5:$A$400<=$A9)*MOVIMIENTOS!$E$5:$E$400)-SUMPRODUCT((MOVIMIENTOS!$B$5:$B$400="VENTA")*(MOVIMIENTOS!$C$5:$C$400="P")*(MOVIMIENTOS!$D$5:$D$400="jabas")*(MOVIMIENTOS!$A$5:$A$400<>"")*(MOVIMIENTOS!$A$5:$A$400<=$A9)*MOVIMIENTOS!$E$5:$E$400)+SUMPRODUCT((MOVIMIENTOS!$B$5:$B$400="AJUSTE")*(MOVIMIENTOS!$C$5:$C$400="P")*(MOVIMIENTOS!$D$5:$D$400="jabas")*(MOVIMIENTOS!$A$5:$A$400<>"")*(MOVIMIENTOS!$A$5:$A$400<=$A9)*MOVIMIENTOS!$E$5:$E$400)) -> 11 | D9: =IF($A9="","",SUMPRODUCT((MOVIMIENTOS!$B$5:$B$400="SALDO INICIAL")*(MOVIMIENTOS!$C$5:$C$400="C")*(MOVIMIENTOS!$D$5:$D$400="jabas")*(MOVIMIENTOS!$A$5:$A$400<>"")*(MOVIMIENTOS!$A$5:$A$400<=$A9)*MOVIMIENTOS!$E$5:$E$400)+SUMPRODUCT((MOVIMIENTOS!$B$5:$B$400="PROCESO")*(MOVIMIENTOS!$C$5:$C$400="C")*(MOVIMIENTOS!$D$5:$D$400="jabas")*(MOVIMIENTOS!$A$5:$A$400<>"")*(MOVIMIENTOS!$A$5:$A$400<=$A9)*MOVIMIENTOS!$E$5:$E$400)-SUMPRODUCT((MOVIMIENTOS!$B$5:$B$400="ENVÍO A SUPESA")*(MOVIMIENTOS!$C$5:$C$400="C")*(MOVIMIENTOS!$D$5:$D$400="jabas")*(MOVIMIENTOS!$A$5:$A$400<>"")*(MOVIMIENTOS!$A$5:$A$400<=$A9)*MOVIMIENTOS!$E$5:$E$400)+SUMPRODUCT((MOVIMIENTOS!$B$5:$B$400="DEVOLUCIÓN")*(MOVIMIENTOS!$C$5:$C$400="C")*(MOVIMIENTOS!$D$5:$D$400="jabas")*(MOVIMIENTOS!$A$5:$A$400<>"")*(MOVIMIENTOS!$A$5:$A$400<=$A9)*MOVIMIENTOS!$E$5:$E$400)-SUMPRODUCT((MOVIMIENTOS!$B$5:$B$400="TRASIEGO")*(MOVIMIENTOS!$C$5:$C$400="C")*(MOVIMIENTOS!$D$5:$D$400="jabas")*(MOVIMIENTOS!$A$5:$A$400<>"")*(MOVIMIENTOS!$A$5:$A$400<=$A9)*MOVIMIENTOS!$E$5:$E$400)-SUMPRODUCT((MOVIMIENTOS!$B$5:$B$400="REGALO")*(MOVIMIENTOS!$C$5:$C$400="C")*(MOVIMIENTOS!$D$5:$D$400="jabas")*(MOVIMIENTOS!$A$5:$A$400<>"")*(MOVIMIENTOS!$A$5:$A$400<=$A9)*MOVIMIENTOS!$E$5:$E$400)-SUMPRODUCT((MOVIMIENTOS!$B$5:$B$400="VENTA")*(MOVIMIENTOS!$C$5:$C$400="C")*(MOVIMIENTOS!$D$5:$D$400="jabas")*(MOVIMIENTOS!$A$5:$A$400<>"")*(MOVIMIENTOS!$A$5:$A$400<=$A9)*MOVIMIENTOS!$E$5:$E$400)+SUMPRODUCT((MOVIMIENTOS!$B$5:$B$400="AJUSTE")*(MOVIMIENTOS!$C$5:$C$400="C")*(MOVIMIENTOS!$D$5:$D$400="jabas")*(MOVIMIENTOS!$A$5:$A$400<>"")*(MOVIMIENTOS!$A$5:$A$400<=$A9)*MOVIMIENTOS!$E$5:$E$400)) -> 12 | E9: =IF($A9="","",SUMPRODUCT((MOVIMIENTOS!$B$5:$B$400="SALDO INICIAL")*(MOVIMIENTOS!$C$5:$C$400="M")*(MOVIMIENTOS!$D$5:$D$400="jabas")*(MOVIMIENTOS!$A$5:$A$400<>"")*(MOVIMIENTOS!$A$5:$A$400<=$A9)*MOVIMIENTOS!$E$5:$E$400)+SUMPRODUCT((MOVIMIENTOS!$B$5:$B$400="PROCESO")*(MOVIMIENTOS!$C$5:$C$400="M")*(MOVIMIENTOS!$D$5:$D$400="jabas")*(MOVIMIENTOS!$A$5:$A$400<>"")*(MOVIMIENTOS!$A$5:$A$400<=$A9)*MOVIMIENTOS!$E$5:$E$400)-SUMPRODUCT((MOVIMIENTOS!$B$5:$B$400="ENVÍO A SUPESA")*(MOVIMIENTOS!$C$5:$C$400="M")*(MOVIMIENTOS!$D$5:$D$400="jabas")*(MOVIMIENTOS!$A$5:$A$400<>"")*(MOVIMIENTOS!$A$5:$A$400<=$A9)*MOVIMIENTOS!$E$5:$E$400)+SUMPRODUCT((MOVIMIENTOS!$B$5:$B$400="DEVOLUCIÓN")*(MOVIMIENTOS!$C$5:$C$400="M")*(MOVIMIENTOS!$D$5:$D$400="jabas")*(MOVIMIENTOS!$A$5:$A$400<>"")*(MOVIMIENTOS!$A$5:$A$400<=$A9)*MOVIMIENTOS!$E$5:$E$400)-SUMPRODUCT((MOVIMIENTOS!$B$5:$B$400="TRASIEGO")*(MOVIMIENTOS!$C$5:$C$400="M")*(MOVIMIENTOS!$D$5:$D$400="jabas")*(MOVIMIENTOS!$A$5:$A$400<>"")*(MOVIMIENTOS!$A$5:$A$400<=$A9)*MOVIMIENTOS!$E$5:$E$400)-SUMPRODUCT((MOVIMIENTOS!$B$5:$B$400="REGALO")*(MOVIMIENTOS!$C$5:$C$400="M")*(MOVIMIENTOS!$D$5:$D$400="jabas")*(MOVIMIENTOS!$A$5:$A$400<>"")*(MOVIMIENTOS!$A$5:$A$400<=$A9)*MOVIMIENTOS!$E$5:$E$400)-SUMPRODUCT((MOVIMIENTOS!$B$5:$B$400="VENTA")*(MOVIMIENTOS!$C$5:$C$400="M")*(MOVIMIENTOS!$D$5:$D$400="jabas")*(MOVIMIENTOS!$A$5:$A$400<>"")*(MOVIMIENTOS!$A$5:$A$400<=$A9)*MOVIMIENTOS!$E$5:$E$400)+SUMPRODUCT((MOVIMIENTOS!$B$5:$B$400="AJUSTE")*(MOVIMIENTOS!$C$5:$C$400="M")*(MOVIMIENTOS!$D$5:$D$400="jabas")*(MOVIMIENTOS!$A$5:$A$400<>"")*(MOVIMIENTOS!$A$5:$A$400<=$A9)*MOVIMIENTOS!$E$5:$E$400)) -> 36 | F9: =IF($A9="","",SUMPRODUCT((MOVIMIENTOS!$B$5:$B$400="SALDO INICIAL")*(MOVIMIENTOS!$C$5:$C$400="Chancho")*(MOVIMIENTOS!$D$5:$D$400="sacos")*(MOVIMIENTOS!$A$5:$A$400<>"")*(MOVIMIENTOS!$A$5:$A$400<=$A9)*MOVIMIENTOS!$E$5:$E$400)+SUMPRODUCT((MOVIMIENTOS!$B$5:$B$400="PROCESO")*(MOVIMIENTOS!$C$5:$C$400="Chancho")*(MOVIMIENTOS!$D$5:$D$400="sacos")*(MOVIMIENTOS!$A$5:$A$400<>"")*(MOVIMIENTOS!$A$5:$A$400<=$A9)*MOVIMIENTOS!$E$5:$E$400)-SUMPRODUCT((MOVIMIENTOS!$B$5:$B$400="VENTA CHANCHO")*(MOVIMIENTOS!$C$5:$C$400="Chancho")*(MOVIMIENTOS!$D$5:$D$400="sacos")*(MOVIMIENTOS!$A$5:$A$400<>"")*(MOVIMIENTOS!$A$5:$A$400<=$A9)*MOVIMIENTOS!$E$5:$E$400)-SUMPRODUCT((MOVIMIENTOS!$B$5:$B$400="REGALO")*(MOVIMIENTOS!$C$5:$C$400="Chancho")*(MOVIMIENTOS!$D$5:$D$400="sacos")*(MOVIMIENTOS!$A$5:$A$400<>"")*(MOVIMIENTOS!$A$5:$A$400<=$A9)*MOVIMIENTOS!$E$5:$E$400)-SUMPRODUCT((MOVIMIENTOS!$B$5:$B$400="VENTA")*(MOVIMIENTOS!$C$5:$C$400="Chancho")*(MOVIMIENTOS!$D$5:$D$400="sacos")*(MOVIMIENTOS!$A$5:$A$400<>"")*(MOVIMIENTOS!$A$5:$A$400<=$A9)*MOVIMIENTOS!$E$5:$E$400)+SUMPRODUCT((MOVIMIENTOS!$B$5:$B$400="AJUSTE")*(MOVIMIENTOS!$C$5:$C$400="Chancho")*(MOVIMIENTOS!$D$5:$D$400="sacos")*(MOVIMIENTOS!$A$5:$A$400<>"")*(MOVIMIENTOS!$A$5:$A$400<=$A9)*MOVIMIENTOS!$E$5:$E$400)) -> 5 | G9: =IF($A9="","",SUM(B9:E9)) -> 83 | H9: =IF($A9="","",SUMPRODUCT((((MOVIMIENTOS!$B$5:$B$400="SALDO INICIAL")*(MOVIMIENTOS!$C$5:$C$400<>"Chancho"))+(MOVIMIENTOS!$B$5:$B$400="COMPRA")+(MOVIMIENTOS!$B$5:$B$400="REPROCESO")+(MOVIMIENTOS!$B$5:$B$400="DEVOLUCIÓN")+((MOVIMIENTOS!$B$5:$B$400="AJUSTE")*(MOVIMIENTOS!$C$5:$C$400<>"Chancho")))*(MOVIMIENTOS!$A$5:$A$400<>"")*(MOVIMIENTOS!$A$5:$A$400<=$A9)*MOVIMIENTOS!$I$5:$I$400)-SUMPRODUCT(((MOVIMIENTOS!$B$5:$B$400="ENVÍO A SUPESA")+(MOVIMIENTOS!$B$5:$B$400="ENVÍO A TOTTUS")+(MOVIMIENTOS!$B$5:$B$400="ENVIO A TOTTUS")+(MOVIMIENTOS!$B$5:$B$400="MALOGRADO")+(MOVIMIENTOS!$B$5:$B$400="OTRA SALIDA")+((MOVIMIENTOS!$B$5:$B$400="PROCESO")*(MOVIMIENTOS!$C$5:$C$400="Chancho"))+((MOVIMIENTOS!$B$5:$B$400="REGALO")*(MOVIMIENTOS!$C$5:$C$400<>"Chancho"))+((MOVIMIENTOS!$B$5:$B$400="VENTA")*(MOVIMIENTOS!$C$5:$C$400<>"Chancho")))*(MOVIMIENTOS!$A$5:$A$400<>"")*(MOVIMIENTOS!$A$5:$A$400<=$A9)*MOVIMIENTOS!$I$5:$I$400)) -> 1249 | J9: =IF(AND(MOVIMIENTOS!$A9<>"",COUNTIF(MOVIMIENTOS!$A$5:$A8,MOVIMIENTOS!$A9)=0),COUNT(J$4:J8)+1,"") -> 2 | K9: =MOVIMIENTOS!$A9 -> 46215
A10: =IFERROR(INDEX(K$5:K$400,MATCH(ROW()-4,J$5:J$400,0)),"") -> 46219 | B10: =IF($A10="","",SUMPRODUCT((MOVIMIENTOS!$B$5:$B$400="SALDO INICIAL")*(MOVIMIENTOS!$C$5:$C$400="A")*(MOVIMIENTOS!$D$5:$D$400="jabas")*(MOVIMIENTOS!$A$5:$A$400<>"")*(MOVIMIENTOS!$A$5:$A$400<=$A10)*MOVIMIENTOS!$E$5:$E$400)+SUMPRODUCT((MOVIMIENTOS!$B$5:$B$400="PROCESO")*(MOVIMIENTOS!$C$5:$C$400="A")*(MOVIMIENTOS!$D$5:$D$400="jabas")*(MOVIMIENTOS!$A$5:$A$400<>"")*(MOVIMIENTOS!$A$5:$A$400<=$A10)*MOVIMIENTOS!$E$5:$E$400)-SUMPRODUCT((MOVIMIENTOS!$B$5:$B$400="ENVÍO A SUPESA")*(MOVIMIENTOS!$C$5:$C$400="A")*(MOVIMIENTOS!$D$5:$D$400="jabas")*(MOVIMIENTOS!$A$5:$A$400<>"")*(MOVIMIENTOS!$A$5:$A$400<=$A10)*MOVIMIENTOS!$E$5:$E$400)+SUMPRODUCT((MOVIMIENTOS!$B$5:$B$400="DEVOLUCIÓN")*(MOVIMIENTOS!$C$5:$C$400="A")*(MOVIMIENTOS!$D$5:$D$400="jabas")*(MOVIMIENTOS!$A$5:$A$400<>"")*(MOVIMIENTOS!$A$5:$A$400<=$A10)*MOVIMIENTOS!$E$5:$E$400)-SUMPRODUCT((MOVIMIENTOS!$B$5:$B$400="TRASIEGO")*(MOVIMIENTOS!$C$5:$C$400="A")*(MOVIMIENTOS!$D$5:$D$400="jabas")*(MOVIMIENTOS!$A$5:$A$400<>"")*(MOVIMIENTOS!$A$5:$A$400<=$A10)*MOVIMIENTOS!$E$5:$E$400)-SUMPRODUCT((MOVIMIENTOS!$B$5:$B$400="REGALO")*(MOVIMIENTOS!$C$5:$C$400="A")*(MOVIMIENTOS!$D$5:$D$400="jabas")*(MOVIMIENTOS!$A$5:$A$400<>"")*(MOVIMIENTOS!$A$5:$A$400<=$A10)*MOVIMIENTOS!$E$5:$E$400)-SUMPRODUCT((MOVIMIENTOS!$B$5:$B$400="VENTA")*(MOVIMIENTOS!$C$5:$C$400="A")*(MOVIMIENTOS!$D$5:$D$400="jabas")*(MOVIMIENTOS!$A$5:$A$400<>"")*(MOVIMIENTOS!$A$5:$A$400<=$A10)*MOVIMIENTOS!$E$5:$E$400)+SUMPRODUCT((MOVIMIENTOS!$B$5:$B$400="AJUSTE")*(MOVIMIENTOS!$C$5:$C$400="A")*(MOVIMIENTOS!$D$5:$D$400="jabas")*(MOVIMIENTOS!$A$5:$A$400<>"")*(MOVIMIENTOS!$A$5:$A$400<=$A10)*MOVIMIENTOS!$E$5:$E$400)) -> 29 | C10: =IF($A10="","",SUMPRODUCT((MOVIMIENTOS!$B$5:$B$400="SALDO INICIAL")*(MOVIMIENTOS!$C$5:$C$400="P")*(MOVIMIENTOS!$D$5:$D$400="jabas")*(MOVIMIENTOS!$A$5:$A$400<>"")*(MOVIMIENTOS!$A$5:$A$400<=$A10)*MOVIMIENTOS!$E$5:$E$400)+SUMPRODUCT((MOVIMIENTOS!$B$5:$B$400="PROCESO")*(MOVIMIENTOS!$C$5:$C$400="P")*(MOVIMIENTOS!$D$5:$D$400="jabas")*(MOVIMIENTOS!$A$5:$A$400<>"")*(MOVIMIENTOS!$A$5:$A$400<=$A10)*MOVIMIENTOS!$E$5:$E$400)-SUMPRODUCT((MOVIMIENTOS!$B$5:$B$400="ENVÍO A SUPESA")*(MOVIMIENTOS!$C$5:$C$400="P")*(MOVIMIENTOS!$D$5:$D$400="jabas")*(MOVIMIENTOS!$A$5:$A$400<>"")*(MOVIMIENTOS!$A$5:$A$400<=$A10)*MOVIMIENTOS!$E$5:$E$400)+SUMPRODUCT((MOVIMIENTOS!$B$5:$B$400="DEVOLUCIÓN")*(MOVIMIENTOS!$C$5:$C$400="P")*(MOVIMIENTOS!$D$5:$D$400="jabas")*(MOVIMIENTOS!$A$5:$A$400<>"")*(MOVIMIENTOS!$A$5:$A$400<=$A10)*MOVIMIENTOS!$E$5:$E$400)-SUMPRODUCT((MOVIMIENTOS!$B$5:$B$400="TRASIEGO")*(MOVIMIENTOS!$C$5:$C$400="P")*(MOVIMIENTOS!$D$5:$D$400="jabas")*(MOVIMIENTOS!$A$5:$A$400<>"")*(MOVIMIENTOS!$A$5:$A$400<=$A10)*MOVIMIENTOS!$E$5:$E$400)-SUMPRODUCT((MOVIMIENTOS!$B$5:$B$400="REGALO")*(MOVIMIENTOS!$C$5:$C$400="P")*(MOVIMIENTOS!$D$5:$D$400="jabas")*(MOVIMIENTOS!$A$5:$A$400<>"")*(MOVIMIENTOS!$A$5:$A$400<=$A10)*MOVIMIENTOS!$E$5:$E$400)-SUMPRODUCT((MOVIMIENTOS!$B$5:$B$400="VENTA")*(MOVIMIENTOS!$C$5:$C$400="P")*(MOVIMIENTOS!$D$5:$D$400="jabas")*(MOVIMIENTOS!$A$5:$A$400<>"")*(MOVIMIENTOS!$A$5:$A$400<=$A10)*MOVIMIENTOS!$E$5:$E$400)+SUMPRODUCT((MOVIMIENTOS!$B$5:$B$400="AJUSTE")*(MOVIMIENTOS!$C$5:$C$400="P")*(MOVIMIENTOS!$D$5:$D$400="jabas")*(MOVIMIENTOS!$A$5:$A$400<>"")*(MOVIMIENTOS!$A$5:$A$400<=$A10)*MOVIMIENTOS!$E$5:$E$400)) -> 11 | D10: =IF($A10="","",SUMPRODUCT((MOVIMIENTOS!$B$5:$B$400="SALDO INICIAL")*(MOVIMIENTOS!$C$5:$C$400="C")*(MOVIMIENTOS!$D$5:$D$400="jabas")*(MOVIMIENTOS!$A$5:$A$400<>"")*(MOVIMIENTOS!$A$5:$A$400<=$A10)*MOVIMIENTOS!$E$5:$E$400)+SUMPRODUCT((MOVIMIENTOS!$B$5:$B$400="PROCESO")*(MOVIMIENTOS!$C$5:$C$400="C")*(MOVIMIENTOS!$D$5:$D$400="jabas")*(MOVIMIENTOS!$A$5:$A$400<>"")*(MOVIMIENTOS!$A$5:$A$400<=$A10)*MOVIMIENTOS!$E$5:$E$400)-SUMPRODUCT((MOVIMIENTOS!$B$5:$B$400="ENVÍO A SUPESA")*(MOVIMIENTOS!$C$5:$C$400="C")*(MOVIMIENTOS!$D$5:$D$400="jabas")*(MOVIMIENTOS!$A$5:$A$400<>"")*(MOVIMIENTOS!$A$5:$A$400<=$A10)*MOVIMIENTOS!$E$5:$E$400)+SUMPRODUCT((MOVIMIENTOS!$B$5:$B$400="DEVOLUCIÓN")*(MOVIMIENTOS!$C$5:$C$400="C")*(MOVIMIENTOS!$D$5:$D$400="jabas")*(MOVIMIENTOS!$A$5:$A$400<>"")*(MOVIMIENTOS!$A$5:$A$400<=$A10)*MOVIMIENTOS!$E$5:$E$400)-SUMPRODUCT((MOVIMIENTOS!$B$5:$B$400="TRASIEGO")*(MOVIMIENTOS!$C$5:$C$400="C")*(MOVIMIENTOS!$D$5:$D$400="jabas")*(MOVIMIENTOS!$A$5:$A$400<>"")*(MOVIMIENTOS!$A$5:$A$400<=$A10)*MOVIMIENTOS!$E$5:$E$400)-SUMPRODUCT((MOVIMIENTOS!$B$5:$B$400="REGALO")*(MOVIMIENTOS!$C$5:$C$400="C")*(MOVIMIENTOS!$D$5:$D$400="jabas")*(MOVIMIENTOS!$A$5:$A$400<>"")*(MOVIMIENTOS!$A$5:$A$400<=$A10)*MOVIMIENTOS!$E$5:$E$400)-SUMPRODUCT((MOVIMIENTOS!$B$5:$B$400="VENTA")*(MOVIMIENTOS!$C$5:$C$400="C")*(MOVIMIENTOS!$D$5:$D$400="jabas")*(MOVIMIENTOS!$A$5:$A$400<>"")*(MOVIMIENTOS!$A$5:$A$400<=$A10)*MOVIMIENTOS!$E$5:$E$400)+SUMPRODUCT((MOVIMIENTOS!$B$5:$B$400="AJUSTE")*(MOVIMIENTOS!$C$5:$C$400="C")*(MOVIMIENTOS!$D$5:$D$400="jabas")*(MOVIMIENTOS!$A$5:$A$400<>"")*(MOVIMIENTOS!$A$5:$A$400<=$A10)*MOVIMIENTOS!$E$5:$E$400)) -> 12 | E10: =IF($A10="","",SUMPRODUCT((MOVIMIENTOS!$B$5:$B$400="SALDO INICIAL")*(MOVIMIENTOS!$C$5:$C$400="M")*(MOVIMIENTOS!$D$5:$D$400="jabas")*(MOVIMIENTOS!$A$5:$A$400<>"")*(MOVIMIENTOS!$A$5:$A$400<=$A10)*MOVIMIENTOS!$E$5:$E$400)+SUMPRODUCT((MOVIMIENTOS!$B$5:$B$400="PROCESO")*(MOVIMIENTOS!$C$5:$C$400="M")*(MOVIMIENTOS!$D$5:$D$400="jabas")*(MOVIMIENTOS!$A$5:$A$400<>"")*(MOVIMIENTOS!$A$5:$A$400<=$A10)*MOVIMIENTOS!$E$5:$E$400)-SUMPRODUCT((MOVIMIENTOS!$B$5:$B$400="ENVÍO A SUPESA")*(MOVIMIENTOS!$C$5:$C$400="M")*(MOVIMIENTOS!$D$5:$D$400="jabas")*(MOVIMIENTOS!$A$5:$A$400<>"")*(MOVIMIENTOS!$A$5:$A$400<=$A10)*MOVIMIENTOS!$E$5:$E$400)+SUMPRODUCT((MOVIMIENTOS!$B$5:$B$400="DEVOLUCIÓN")*(MOVIMIENTOS!$C$5:$C$400="M")*(MOVIMIENTOS!$D$5:$D$400="jabas")*(MOVIMIENTOS!$A$5:$A$400<>"")*(MOVIMIENTOS!$A$5:$A$400<=$A10)*MOVIMIENTOS!$E$5:$E$400)-SUMPRODUCT((MOVIMIENTOS!$B$5:$B$400="TRASIEGO")*(MOVIMIENTOS!$C$5:$C$400="M")*(MOVIMIENTOS!$D$5:$D$400="jabas")*(MOVIMIENTOS!$A$5:$A$400<>"")*(MOVIMIENTOS!$A$5:$A$400<=$A10)*MOVIMIENTOS!$E$5:$E$400)-SUMPRODUCT((MOVIMIENTOS!$B$5:$B$400="REGALO")*(MOVIMIENTOS!$C$5:$C$400="M")*(MOVIMIENTOS!$D$5:$D$400="jabas")*(MOVIMIENTOS!$A$5:$A$400<>"")*(MOVIMIENTOS!$A$5:$A$400<=$A10)*MOVIMIENTOS!$E$5:$E$400)-SUMPRODUCT((MOVIMIENTOS!$B$5:$B$400="VENTA")*(MOVIMIENTOS!$C$5:$C$400="M")*(MOVIMIENTOS!$D$5:$D$400="jabas")*(MOVIMIENTOS!$A$5:$A$400<>"")*(MOVIMIENTOS!$A$5:$A$400<=$A10)*MOVIMIENTOS!$E$5:$E$400)+SUMPRODUCT((MOVIMIENTOS!$B$5:$B$400="AJUSTE")*(MOVIMIENTOS!$C$5:$C$400="M")*(MOVIMIENTOS!$D$5:$D$400="jabas")*(MOVIMIENTOS!$A$5:$A$400<>"")*(MOVIMIENTOS!$A$5:$A$400<=$A10)*MOVIMIENTOS!$E$5:$E$400)) -> 37 | F10: =IF($A10="","",SUMPRODUCT((MOVIMIENTOS!$B$5:$B$400="SALDO INICIAL")*(MOVIMIENTOS!$C$5:$C$400="Chancho")*(MOVIMIENTOS!$D$5:$D$400="sacos")*(MOVIMIENTOS!$A$5:$A$400<>"")*(MOVIMIENTOS!$A$5:$A$400<=$A10)*MOVIMIENTOS!$E$5:$E$400)+SUMPRODUCT((MOVIMIENTOS!$B$5:$B$400="PROCESO")*(MOVIMIENTOS!$C$5:$C$400="Chancho")*(MOVIMIENTOS!$D$5:$D$400="sacos")*(MOVIMIENTOS!$A$5:$A$400<>"")*(MOVIMIENTOS!$A$5:$A$400<=$A10)*MOVIMIENTOS!$E$5:$E$400)-SUMPRODUCT((MOVIMIENTOS!$B$5:$B$400="VENTA CHANCHO")*(MOVIMIENTOS!$C$5:$C$400="Chancho")*(MOVIMIENTOS!$D$5:$D$400="sacos")*(MOVIMIENTOS!$A$5:$A$400<>"")*(MOVIMIENTOS!$A$5:$A$400<=$A10)*MOVIMIENTOS!$E$5:$E$400)-SUMPRODUCT((MOVIMIENTOS!$B$5:$B$400="REGALO")*(MOVIMIENTOS!$C$5:$C$400="Chancho")*(MOVIMIENTOS!$D$5:$D$400="sacos")*(MOVIMIENTOS!$A$5:$A$400<>"")*(MOVIMIENTOS!$A$5:$A$400<=$A10)*MOVIMIENTOS!$E$5:$E$400)-SUMPRODUCT((MOVIMIENTOS!$B$5:$B$400="VENTA")*(MOVIMIENTOS!$C$5:$C$400="Chancho")*(MOVIMIENTOS!$D$5:$D$400="sacos")*(MOVIMIENTOS!$A$5:$A$400<>"")*(MOVIMIENTOS!$A$5:$A$400<=$A10)*MOVIMIENTOS!$E$5:$E$400)+SUMPRODUCT((MOVIMIENTOS!$B$5:$B$400="AJUSTE")*(MOVIMIENTOS!$C$5:$C$400="Chancho")*(MOVIMIENTOS!$D$5:$D$400="sacos")*(MOVIMIENTOS!$A$5:$A$400<>"")*(MOVIMIENTOS!$A$5:$A$400<=$A10)*MOVIMIENTOS!$E$5:$E$400)) -> 9 | G10: =IF($A10="","",SUM(B10:E10)) -> 89 | H10: =IF($A10="","",SUMPRODUCT((((MOVIMIENTOS!$B$5:$B$400="SALDO INICIAL")*(MOVIMIENTOS!$C$5:$C$400<>"Chancho"))+(MOVIMIENTOS!$B$5:$B$400="COMPRA")+(MOVIMIENTOS!$B$5:$B$400="REPROCESO")+(MOVIMIENTOS!$B$5:$B$400="DEVOLUCIÓN")+((MOVIMIENTOS!$B$5:$B$400="AJUSTE")*(MOVIMIENTOS!$C$5:$C$400<>"Chancho")))*(MOVIMIENTOS!$A$5:$A$400<>"")*(MOVIMIENTOS!$A$5:$A$400<=$A10)*MOVIMIENTOS!$I$5:$I$400)-SUMPRODUCT(((MOVIMIENTOS!$B$5:$B$400="ENVÍO A SUPESA")+(MOVIMIENTOS!$B$5:$B$400="ENVÍO A TOTTUS")+(MOVIMIENTOS!$B$5:$B$400="ENVIO A TOTTUS")+(MOVIMIENTOS!$B$5:$B$400="MALOGRADO")+(MOVIMIENTOS!$B$5:$B$400="OTRA SALIDA")+((MOVIMIENTOS!$B$5:$B$400="PROCESO")*(MOVIMIENTOS!$C$5:$C$400="Chancho"))+((MOVIMIENTOS!$B$5:$B$400="REGALO")*(MOVIMIENTOS!$C$5:$C$400<>"Chancho"))+((MOVIMIENTOS!$B$5:$B$400="VENTA")*(MOVIMIENTOS!$C$5:$C$400<>"Chancho")))*(MOVIMIENTOS!$A$5:$A$400<>"")*(MOVIMIENTOS!$A$5:$A$400<=$A10)*MOVIMIENTOS!$I$5:$I$400)) -> 1439 | J10: =IF(AND(MOVIMIENTOS!$A10<>"",COUNTIF(MOVIMIENTOS!$A$5:$A9,MOVIMIENTOS!$A10)=0),COUNT(J$4:J9)+1,"") | K10: =MOVIMIENTOS!$A10 -> 46215
A11: =IFERROR(INDEX(K$5:K$400,MATCH(ROW()-4,J$5:J$400,0)),"") -> 46220 | B11: =IF($A11="","",SUMPRODUCT((MOVIMIENTOS!$B$5:$B$400="SALDO INICIAL")*(MOVIMIENTOS!$C$5:$C$400="A")*(MOVIMIENTOS!$D$5:$D$400="jabas")*(MOVIMIENTOS!$A$5:$A$400<>"")*(MOVIMIENTOS!$A$5:$A$400<=$A11)*MOVIMIENTOS!$E$5:$E$400)+SUMPRODUCT((MOVIMIENTOS!$B$5:$B$400="PROCESO")*(MOVIMIENTOS!$C$5:$C$400="A")*(MOVIMIENTOS!$D$5:$D$400="jabas")*(MOVIMIENTOS!$A$5:$A$400<>"")*(MOVIMIENTOS!$A$5:$A$400<=$A11)*MOVIMIENTOS!$E$5:$E$400)-SUMPRODUCT((MOVIMIENTOS!$B$5:$B$400="ENVÍO A SUPESA")*(MOVIMIENTOS!$C$5:$C$400="A")*(MOVIMIENTOS!$D$5:$D$400="jabas")*(MOVIMIENTOS!$A$5:$A$400<>"")*(MOVIMIENTOS!$A$5:$A$400<=$A11)*MOVIMIENTOS!$E$5:$E$400)+SUMPRODUCT((MOVIMIENTOS!$B$5:$B$400="DEVOLUCIÓN")*(MOVIMIENTOS!$C$5:$C$400="A")*(MOVIMIENTOS!$D$5:$D$400="jabas")*(MOVIMIENTOS!$A$5:$A$400<>"")*(MOVIMIENTOS!$A$5:$A$400<=$A11)*MOVIMIENTOS!$E$5:$E$400)-SUMPRODUCT((MOVIMIENTOS!$B$5:$B$400="TRASIEGO")*(MOVIMIENTOS!$C$5:$C$400="A")*(MOVIMIENTOS!$D$5:$D$400="jabas")*(MOVIMIENTOS!$A$5:$A$400<>"")*(MOVIMIENTOS!$A$5:$A$400<=$A11)*MOVIMIENTOS!$E$5:$E$400)-SUMPRODUCT((MOVIMIENTOS!$B$5:$B$400="REGALO")*(MOVIMIENTOS!$C$5:$C$400="A")*(MOVIMIENTOS!$D$5:$D$400="jabas")*(MOVIMIENTOS!$A$5:$A$400<>"")*(MOVIMIENTOS!$A$5:$A$400<=$A11)*MOVIMIENTOS!$E$5:$E$400)-SUMPRODUCT((MOVIMIENTOS!$B$5:$B$400="VENTA")*(MOVIMIENTOS!$C$5:$C$400="A")*(MOVIMIENTOS!$D$5:$D$400="jabas")*(MOVIMIENTOS!$A$5:$A$400<>"")*(MOVIMIENTOS!$A$5:$A$400<=$A11)*MOVIMIENTOS!$E$5:$E$400)+SUMPRODUCT((MOVIMIENTOS!$B$5:$B$400="AJUSTE")*(MOVIMIENTOS!$C$5:$C$400="A")*(MOVIMIENTOS!$D$5:$D$400="jabas")*(MOVIMIENTOS!$A$5:$A$400<>"")*(MOVIMIENTOS!$A$5:$A$400<=$A11)*MOVIMIENTOS!$E$5:$E$400)) -> 65 | C11: =IF($A11="","",SUMPRODUCT((MOVIMIENTOS!$B$5:$B$400="SALDO INICIAL")*(MOVIMIENTOS!$C$5:$C$400="P")*(MOVIMIENTOS!$D$5:$D$400="jabas")*(MOVIMIENTOS!$A$5:$A$400<>"")*(MOVIMIENTOS!$A$5:$A$400<=$A11)*MOVIMIENTOS!$E$5:$E$400)+SUMPRODUCT((MOVIMIENTOS!$B$5:$B$400="PROCESO")*(MOVIMIENTOS!$C$5:$C$400="P")*(MOVIMIENTOS!$D$5:$D$400="jabas")*(MOVIMIENTOS!$A$5:$A$400<>"")*(MOVIMIENTOS!$A$5:$A$400<=$A11)*MOVIMIENTOS!$E$5:$E$400)-SUMPRODUCT((MOVIMIENTOS!$B$5:$B$400="ENVÍO A SUPESA")*(MOVIMIENTOS!$C$5:$C$400="P")*(MOVIMIENTOS!$D$5:$D$400="jabas")*(MOVIMIENTOS!$A$5:$A$400<>"")*(MOVIMIENTOS!$A$5:$A$400<=$A11)*MOVIMIENTOS!$E$5:$E$400)+SUMPRODUCT((MOVIMIENTOS!$B$5:$B$400="DEVOLUCIÓN")*(MOVIMIENTOS!$C$5:$C$400="P")*(MOVIMIENTOS!$D$5:$D$400="jabas")*(MOVIMIENTOS!$A$5:$A$400<>"")*(MOVIMIENTOS!$A$5:$A$400<=$A11)*MOVIMIENTOS!$E$5:$E$400)-SUMPRODUCT((MOVIMIENTOS!$B$5:$B$400="TRASIEGO")*(MOVIMIENTOS!$C$5:$C$400="P")*(MOVIMIENTOS!$D$5:$D$400="jabas")*(MOVIMIENTOS!$A$5:$A$400<>"")*(MOVIMIENTOS!$A$5:$A$400<=$A11)*MOVIMIENTOS!$E$5:$E$400)-SUMPRODUCT((MOVIMIENTOS!$B$5:$B$400="REGALO")*(MOVIMIENTOS!$C$5:$C$400="P")*(MOVIMIENTOS!$D$5:$D$400="jabas")*(MOVIMIENTOS!$A$5:$A$400<>"")*(MOVIMIENTOS!$A$5:$A$400<=$A11)*MOVIMIENTOS!$E$5:$E$400)-SUMPRODUCT((MOVIMIENTOS!$B$5:$B$400="VENTA")*(MOVIMIENTOS!$C$5:$C$400="P")*(MOVIMIENTOS!$D$5:$D$400="jabas")*(MOVIMIENTOS!$A$5:$A$400<>"")*(MOVIMIENTOS!$A$5:$A$400<=$A11)*MOVIMIENTOS!$E$5:$E$400)+SUMPRODUCT((MOVIMIENTOS!$B$5:$B$400="AJUSTE")*(MOVIMIENTOS!$C$5:$C$400="P")*(MOVIMIENTOS!$D$5:$D$400="jabas")*(MOVIMIENTOS!$A$5:$A$400<>"")*(MOVIMIENTOS!$A$5:$A$400<=$A11)*MOVIMIENTOS!$E$5:$E$400)) -> 4 | D11: =IF($A11="","",SUMPRODUCT((MOVIMIENTOS!$B$5:$B$400="SALDO INICIAL")*(MOVIMIENTOS!$C$5:$C$400="C")*(MOVIMIENTOS!$D$5:$D$400="jabas")*(MOVIMIENTOS!$A$5:$A$400<>"")*(MOVIMIENTOS!$A$5:$A$400<=$A11)*MOVIMIENTOS!$E$5:$E$400)+SUMPRODUCT((MOVIMIENTOS!$B$5:$B$400="PROCESO")*(MOVIMIENTOS!$C$5:$C$400="C")*(MOVIMIENTOS!$D$5:$D$400="jabas")*(MOVIMIENTOS!$A$5:$A$400<>"")*(MOVIMIENTOS!$A$5:$A$400<=$A11)*MOVIMIENTOS!$E$5:$E$400)-SUMPRODUCT((MOVIMIENTOS!$B$5:$B$400="ENVÍO A SUPESA")*(MOVIMIENTOS!$C$5:$C$400="C")*(MOVIMIENTOS!$D$5:$D$400="jabas")*(MOVIMIENTOS!$A$5:$A$400<>"")*(MOVIMIENTOS!$A$5:$A$400<=$A11)*MOVIMIENTOS!$E$5:$E$400)+SUMPRODUCT((MOVIMIENTOS!$B$5:$B$400="DEVOLUCIÓN")*(MOVIMIENTOS!$C$5:$C$400="C")*(MOVIMIENTOS!$D$5:$D$400="jabas")*(MOVIMIENTOS!$A$5:$A$400<>"")*(MOVIMIENTOS!$A$5:$A$400<=$A11)*MOVIMIENTOS!$E$5:$E$400)-SUMPRODUCT((MOVIMIENTOS!$B$5:$B$400="TRASIEGO")*(MOVIMIENTOS!$C$5:$C$400="C")*(MOVIMIENTOS!$D$5:$D$400="jabas")*(MOVIMIENTOS!$A$5:$A$400<>"")*(MOVIMIENTOS!$A$5:$A$400<=$A11)*MOVIMIENTOS!$E$5:$E$400)-SUMPRODUCT((MOVIMIENTOS!$B$5:$B$400="REGALO")*(MOVIMIENTOS!$C$5:$C$400="C")*(MOVIMIENTOS!$D$5:$D$400="jabas")*(MOVIMIENTOS!$A$5:$A$400<>"")*(MOVIMIENTOS!$A$5:$A$400<=$A11)*MOVIMIENTOS!$E$5:$E$400)-SUMPRODUCT((MOVIMIENTOS!$B$5:$B$400="VENTA")*(MOVIMIENTOS!$C$5:$C$400="C")*(MOVIMIENTOS!$D$5:$D$400="jabas")*(MOVIMIENTOS!$A$5:$A$400<>"")*(MOVIMIENTOS!$A$5:$A$400<=$A11)*MOVIMIENTOS!$E$5:$E$400)+SUMPRODUCT((MOVIMIENTOS!$B$5:$B$400="AJUSTE")*(MOVIMIENTOS!$C$5:$C$400="C")*(MOVIMIENTOS!$D$5:$D$400="jabas")*(MOVIMIENTOS!$A$5:$A$400<>"")*(MOVIMIENTOS!$A$5:$A$400<=$A11)*MOVIMIENTOS!$E$5:$E$400)) -> 9 | E11: =IF($A11="","",SUMPRODUCT((MOVIMIENTOS!$B$5:$B$400="SALDO INICIAL")*(MOVIMIENTOS!$C$5:$C$400="M")*(MOVIMIENTOS!$D$5:$D$400="jabas")*(MOVIMIENTOS!$A$5:$A$400<>"")*(MOVIMIENTOS!$A$5:$A$400<=$A11)*MOVIMIENTOS!$E$5:$E$400)+SUMPRODUCT((MOVIMIENTOS!$B$5:$B$400="PROCESO")*(MOVIMIENTOS!$C$5:$C$400="M")*(MOVIMIENTOS!$D$5:$D$400="jabas")*(MOVIMIENTOS!$A$5:$A$400<>"")*(MOVIMIENTOS!$A$5:$A$400<=$A11)*MOVIMIENTOS!$E$5:$E$400)-SUMPRODUCT((MOVIMIENTOS!$B$5:$B$400="ENVÍO A SUPESA")*(MOVIMIENTOS!$C$5:$C$400="M")*(MOVIMIENTOS!$D$5:$D$400="jabas")*(MOVIMIENTOS!$A$5:$A$400<>"")*(MOVIMIENTOS!$A$5:$A$400<=$A11)*MOVIMIENTOS!$E$5:$E$400)+SUMPRODUCT((MOVIMIENTOS!$B$5:$B$400="DEVOLUCIÓN")*(MOVIMIENTOS!$C$5:$C$400="M")*(MOVIMIENTOS!$D$5:$D$400="jabas")*(MOVIMIENTOS!$A$5:$A$400<>"")*(MOVIMIENTOS!$A$5:$A$400<=$A11)*MOVIMIENTOS!$E$5:$E$400)-SUMPRODUCT((MOVIMIENTOS!$B$5:$B$400="TRASIEGO")*(MOVIMIENTOS!$C$5:$C$400="M")*(MOVIMIENTOS!$D$5:$D$400="jabas")*(MOVIMIENTOS!$A$5:$A$400<>"")*(MOVIMIENTOS!$A$5:$A$400<=$A11)*MOVIMIENTOS!$E$5:$E$400)-SUMPRODUCT((MOVIMIENTOS!$B$5:$B$400="REGALO")*(MOVIMIENTOS!$C$5:$C$400="M")*(MOVIMIENTOS!$D$5:$D$400="jabas")*(MOVIMIENTOS!$A$5:$A$400<>"")*(MOVIMIENTOS!$A$5:$A$400<=$A11)*MOVIMIENTOS!$E$5:$E$400)-SUMPRODUCT((MOVIMIENTOS!$B$5:$B$400="VENTA")*(MOVIMIENTOS!$C$5:$C$400="M")*(MOVIMIENTOS!$D$5:$D$400="jabas")*(MOVIMIENTOS!$A$5:$A$400<>"")*(MOVIMIENTOS!$A$5:$A$400<=$A11)*MOVIMIENTOS!$E$5:$E$400)+SUMPRODUCT((MOVIMIENTOS!$B$5:$B$400="AJUSTE")*(MOVIMIENTOS!$C$5:$C$400="M")*(MOVIMIENTOS!$D$5:$D$400="jabas")*(MOVIMIENTOS!$A$5:$A$400<>"")*(MOVIMIENTOS!$A$5:$A$400<=$A11)*MOVIMIENTOS!$E$5:$E$400)) -> 115 | F11: =IF($A11="","",SUMPRODUCT((MOVIMIENTOS!$B$5:$B$400="SALDO INICIAL")*(MOVIMIENTOS!$C$5:$C$400="Chancho")*(MOVIMIENTOS!$D$5:$D$400="sacos")*(MOVIMIENTOS!$A$5:$A$400<>"")*(MOVIMIENTOS!$A$5:$A$400<=$A11)*MOVIMIENTOS!$E$5:$E$400)+SUMPRODUCT((MOVIMIENTOS!$B$5:$B$400="PROCESO")*(MOVIMIENTOS!$C$5:$C$400="Chancho")*(MOVIMIENTOS!$D$5:$D$400="sacos")*(MOVIMIENTOS!$A$5:$A$400<>"")*(MOVIMIENTOS!$A$5:$A$400<=$A11)*MOVIMIENTOS!$E$5:$E$400)-SUMPRODUCT((MOVIMIENTOS!$B$5:$B$400="VENTA CHANCHO")*(MOVIMIENTOS!$C$5:$C$400="Chancho")*(MOVIMIENTOS!$D$5:$D$400="sacos")*(MOVIMIENTOS!$A$5:$A$400<>"")*(MOVIMIENTOS!$A$5:$A$400<=$A11)*MOVIMIENTOS!$E$5:$E$400)-SUMPRODUCT((MOVIMIENTOS!$B$5:$B$400="REGALO")*(MOVIMIENTOS!$C$5:$C$400="Chancho")*(MOVIMIENTOS!$D$5:$D$400="sacos")*(MOVIMIENTOS!$A$5:$A$400<>"")*(MOVIMIENTOS!$A$5:$A$400<=$A11)*MOVIMIENTOS!$E$5:$E$400)-SUMPRODUCT((MOVIMIENTOS!$B$5:$B$400="VENTA")*(MOVIMIENTOS!$C$5:$C$400="Chancho")*(MOVIMIENTOS!$D$5:$D$400="sacos")*(MOVIMIENTOS!$A$5:$A$400<>"")*(MOVIMIENTOS!$A$5:$A$400<=$A11)*MOVIMIENTOS!$E$5:$E$400)+SUMPRODUCT((MOVIMIENTOS!$B$5:$B$400="AJUSTE")*(MOVIMIENTOS!$C$5:$C$400="Chancho")*(MOVIMIENTOS!$D$5:$D$400="sacos")*(MOVIMIENTOS!$A$5:$A$400<>"")*(MOVIMIENTOS!$A$5:$A$400<=$A11)*MOVIMIENTOS!$E$5:$E$400)) -> 5 | G11: =IF($A11="","",SUM(B11:E11)) -> 193 | H11: =IF($A11="","",SUMPRODUCT((((MOVIMIENTOS!$B$5:$B$400="SALDO INICIAL")*(MOVIMIENTOS!$C$5:$C$400<>"Chancho"))+(MOVIMIENTOS!$B$5:$B$400="COMPRA")+(MOVIMIENTOS!$B$5:$B$400="REPROCESO")+(MOVIMIENTOS!$B$5:$B$400="DEVOLUCIÓN")+((MOVIMIENTOS!$B$5:$B$400="AJUSTE")*(MOVIMIENTOS!$C$5:$C$400<>"Chancho")))*(MOVIMIENTOS!$A$5:$A$400<>"")*(MOVIMIENTOS!$A$5:$A$400<=$A11)*MOVIMIENTOS!$I$5:$I$400)-SUMPRODUCT(((MOVIMIENTOS!$B$5:$B$400="ENVÍO A SUPESA")+(MOVIMIENTOS!$B$5:$B$400="ENVÍO A TOTTUS")+(MOVIMIENTOS!$B$5:$B$400="ENVIO A TOTTUS")+(MOVIMIENTOS!$B$5:$B$400="MALOGRADO")+(MOVIMIENTOS!$B$5:$B$400="OTRA SALIDA")+((MOVIMIENTOS!$B$5:$B$400="PROCESO")*(MOVIMIENTOS!$C$5:$C$400="Chancho"))+((MOVIMIENTOS!$B$5:$B$400="REGALO")*(MOVIMIENTOS!$C$5:$C$400<>"Chancho"))+((MOVIMIENTOS!$B$5:$B$400="VENTA")*(MOVIMIENTOS!$C$5:$C$400<>"Chancho")))*(MOVIMIENTOS!$A$5:$A$400<>"")*(MOVIMIENTOS!$A$5:$A$400<=$A11)*MOVIMIENTOS!$I$5:$I$400)) -> 3264 | J11: =IF(AND(MOVIMIENTOS!$A11<>"",COUNTIF(MOVIMIENTOS!$A$5:$A10,MOVIMIENTOS!$A11)=0),COUNT(J$4:J10)+1,"") | K11: =MOVIMIENTOS!$A11 -> 46215
A12: =IFERROR(INDEX(K$5:K$400,MATCH(ROW()-4,J$5:J$400,0)),"") -> 46221 | B12: =IF($A12="","",SUMPRODUCT((MOVIMIENTOS!$B$5:$B$400="SALDO INICIAL")*(MOVIMIENTOS!$C$5:$C$400="A")*(MOVIMIENTOS!$D$5:$D$400="jabas")*(MOVIMIENTOS!$A$5:$A$400<>"")*(MOVIMIENTOS!$A$5:$A$400<=$A12)*MOVIMIENTOS!$E$5:$E$400)+SUMPRODUCT((MOVIMIENTOS!$B$5:$B$400="PROCESO")*(MOVIMIENTOS!$C$5:$C$400="A")*(MOVIMIENTOS!$D$5:$D$400="jabas")*(MOVIMIENTOS!$A$5:$A$400<>"")*(MOVIMIENTOS!$A$5:$A$400<=$A12)*MOVIMIENTOS!$E$5:$E$400)-SUMPRODUCT((MOVIMIENTOS!$B$5:$B$400="ENVÍO A SUPESA")*(MOVIMIENTOS!$C$5:$C$400="A")*(MOVIMIENTOS!$D$5:$D$400="jabas")*(MOVIMIENTOS!$A$5:$A$400<>"")*(MOVIMIENTOS!$A$5:$A$400<=$A12)*MOVIMIENTOS!$E$5:$E$400)+SUMPRODUCT((MOVIMIENTOS!$B$5:$B$400="DEVOLUCIÓN")*(MOVIMIENTOS!$C$5:$C$400="A")*(MOVIMIENTOS!$D$5:$D$400="jabas")*(MOVIMIENTOS!$A$5:$A$400<>"")*(MOVIMIENTOS!$A$5:$A$400<=$A12)*MOVIMIENTOS!$E$5:$E$400)-SUMPRODUCT((MOVIMIENTOS!$B$5:$B$400="TRASIEGO")*(MOVIMIENTOS!$C$5:$C$400="A")*(MOVIMIENTOS!$D$5:$D$400="jabas")*(MOVIMIENTOS!$A$5:$A$400<>"")*(MOVIMIENTOS!$A$5:$A$400<=$A12)*MOVIMIENTOS!$E$5:$E$400)-SUMPRODUCT((MOVIMIENTOS!$B$5:$B$400="REGALO")*(MOVIMIENTOS!$C$5:$C$400="A")*(MOVIMIENTOS!$D$5:$D$400="jabas")*(MOVIMIENTOS!$A$5:$A$400<>"")*(MOVIMIENTOS!$A$5:$A$400<=$A12)*MOVIMIENTOS!$E$5:$E$400)-SUMPRODUCT((MOVIMIENTOS!$B$5:$B$400="VENTA")*(MOVIMIENTOS!$C$5:$C$400="A")*(MOVIMIENTOS!$D$5:$D$400="jabas")*(MOVIMIENTOS!$A$5:$A$400<>"")*(MOVIMIENTOS!$A$5:$A$400<=$A12)*MOVIMIENTOS!$E$5:$E$400)+SUMPRODUCT((MOVIMIENTOS!$B$5:$B$400="AJUSTE")*(MOVIMIENTOS!$C$5:$C$400="A")*(MOVIMIENTOS!$D$5:$D$400="jabas")*(MOVIMIENTOS!$A$5:$A$400<>"")*(MOVIMIENTOS!$A$5:$A$400<=$A12)*MOVIMIENTOS!$E$5:$E$400)) -> 64 | C12: =IF($A12="","",SUMPRODUCT((MOVIMIENTOS!$B$5:$B$400="SALDO INICIAL")*(MOVIMIENTOS!$C$5:$C$400="P")*(MOVIMIENTOS!$D$5:$D$400="jabas")*(MOVIMIENTOS!$A$5:$A$400<>"")*(MOVIMIENTOS!$A$5:$A$400<=$A12)*MOVIMIENTOS!$E$5:$E$400)+SUMPRODUCT((MOVIMIENTOS!$B$5:$B$400="PROCESO")*(MOVIMIENTOS!$C$5:$C$400="P")*(MOVIMIENTOS!$D$5:$D$400="jabas")*(MOVIMIENTOS!$A$5:$A$400<>"")*(MOVIMIENTOS!$A$5:$A$400<=$A12)*MOVIMIENTOS!$E$5:$E$400)-SUMPRODUCT((MOVIMIENTOS!$B$5:$B$400="ENVÍO A SUPESA")*(MOVIMIENTOS!$C$5:$C$400="P")*(MOVIMIENTOS!$D$5:$D$400="jabas")*(MOVIMIENTOS!$A$5:$A$400<>"")*(MOVIMIENTOS!$A$5:$A$400<=$A12)*MOVIMIENTOS!$E$5:$E$400)+SUMPRODUCT((MOVIMIENTOS!$B$5:$B$400="DEVOLUCIÓN")*(MOVIMIENTOS!$C$5:$C$400="P")*(MOVIMIENTOS!$D$5:$D$400="jabas")*(MOVIMIENTOS!$A$5:$A$400<>"")*(MOVIMIENTOS!$A$5:$A$400<=$A12)*MOVIMIENTOS!$E$5:$E$400)-SUMPRODUCT((MOVIMIENTOS!$B$5:$B$400="TRASIEGO")*(MOVIMIENTOS!$C$5:$C$400="P")*(MOVIMIENTOS!$D$5:$D$400="jabas")*(MOVIMIENTOS!$A$5:$A$400<>"")*(MOVIMIENTOS!$A$5:$A$400<=$A12)*MOVIMIENTOS!$E$5:$E$400)-SUMPRODUCT((MOVIMIENTOS!$B$5:$B$400="REGALO")*(MOVIMIENTOS!$C$5:$C$400="P")*(MOVIMIENTOS!$D$5:$D$400="jabas")*(MOVIMIENTOS!$A$5:$A$400<>"")*(MOVIMIENTOS!$A$5:$A$400<=$A12)*MOVIMIENTOS!$E$5:$E$400)-SUMPRODUCT((MOVIMIENTOS!$B$5:$B$400="VENTA")*(MOVIMIENTOS!$C$5:$C$400="P")*(MOVIMIENTOS!$D$5:$D$400="jabas")*(MOVIMIENTOS!$A$5:$A$400<>"")*(MOVIMIENTOS!$A$5:$A$400<=$A12)*MOVIMIENTOS!$E$5:$E$400)+SUMPRODUCT((MOVIMIENTOS!$B$5:$B$400="AJUSTE")*(MOVIMIENTOS!$C$5:$C$400="P")*(MOVIMIENTOS!$D$5:$D$400="jabas")*(MOVIMIENTOS!$A$5:$A$400<>"")*(MOVIMIENTOS!$A$5:$A$400<=$A12)*MOVIMIENTOS!$E$5:$E$400)) -> 11 | D12: =IF($A12="","",SUMPRODUCT((MOVIMIENTOS!$B$5:$B$400="SALDO INICIAL")*(MOVIMIENTOS!$C$5:$C$400="C")*(MOVIMIENTOS!$D$5:$D$400="jabas")*(MOVIMIENTOS!$A$5:$A$400<>"")*(MOVIMIENTOS!$A$5:$A$400<=$A12)*MOVIMIENTOS!$E$5:$E$400)+SUMPRODUCT((MOVIMIENTOS!$B$5:$B$400="PROCESO")*(MOVIMIENTOS!$C$5:$C$400="C")*(MOVIMIENTOS!$D$5:$D$400="jabas")*(MOVIMIENTOS!$A$5:$A$400<>"")*(MOVIMIENTOS!$A$5:$A$400<=$A12)*MOVIMIENTOS!$E$5:$E$400)-SUMPRODUCT((MOVIMIENTOS!$B$5:$B$400="ENVÍO A SUPESA")*(MOVIMIENTOS!$C$5:$C$400="C")*(MOVIMIENTOS!$D$5:$D$400="jabas")*(MOVIMIENTOS!$A$5:$A$400<>"")*(MOVIMIENTOS!$A$5:$A$400<=$A12)*MOVIMIENTOS!$E$5:$E$400)+SUMPRODUCT((MOVIMIENTOS!$B$5:$B$400="DEVOLUCIÓN")*(MOVIMIENTOS!$C$5:$C$400="C")*(MOVIMIENTOS!$D$5:$D$400="jabas")*(MOVIMIENTOS!$A$5:$A$400<>"")*(MOVIMIENTOS!$A$5:$A$400<=$A12)*MOVIMIENTOS!$E$5:$E$400)-SUMPRODUCT((MOVIMIENTOS!$B$5:$B$400="TRASIEGO")*(MOVIMIENTOS!$C$5:$C$400="C")*(MOVIMIENTOS!$D$5:$D$400="jabas")*(MOVIMIENTOS!$A$5:$A$400<>"")*(MOVIMIENTOS!$A$5:$A$400<=$A12)*MOVIMIENTOS!$E$5:$E$400)-SUMPRODUCT((MOVIMIENTOS!$B$5:$B$400="REGALO")*(MOVIMIENTOS!$C$5:$C$400="C")*(MOVIMIENTOS!$D$5:$D$400="jabas")*(MOVIMIENTOS!$A$5:$A$400<>"")*(MOVIMIENTOS!$A$5:$A$400<=$A12)*MOVIMIENTOS!$E$5:$E$400)-SUMPRODUCT((MOVIMIENTOS!$B$5:$B$400="VENTA")*(MOVIMIENTOS!$C$5:$C$400="C")*(MOVIMIENTOS!$D$5:$D$400="jabas")*(MOVIMIENTOS!$A$5:$A$400<>"")*(MOVIMIENTOS!$A$5:$A$400<=$A12)*MOVIMIENTOS!$E$5:$E$400)+SUMPRODUCT((MOVIMIENTOS!$B$5:$B$400="AJUSTE")*(MOVIMIENTOS!$C$5:$C$400="C")*(MOVIMIENTOS!$D$5:$D$400="jabas")*(MOVIMIENTOS!$A$5:$A$400<>"")*(MOVIMIENTOS!$A$5:$A$400<=$A12)*MOVIMIENTOS!$E$5:$E$400)) -> 12 | E12: =IF($A12="","",SUMPRODUCT((MOVIMIENTOS!$B$5:$B$400="SALDO INICIAL")*(MOVIMIENTOS!$C$5:$C$400="M")*(MOVIMIENTOS!$D$5:$D$400="jabas")*(MOVIMIENTOS!$A$5:$A$400<>"")*(MOVIMIENTOS!$A$5:$A$400<=$A12)*MOVIMIENTOS!$E$5:$E$400)+SUMPRODUCT((MOVIMIENTOS!$B$5:$B$400="PROCESO")*(MOVIMIENTOS!$C$5:$C$400="M")*(MOVIMIENTOS!$D$5:$D$400="jabas")*(MOVIMIENTOS!$A$5:$A$400<>"")*(MOVIMIENTOS!$A$5:$A$400<=$A12)*MOVIMIENTOS!$E$5:$E$400)-SUMPRODUCT((MOVIMIENTOS!$B$5:$B$400="ENVÍO A SUPESA")*(MOVIMIENTOS!$C$5:$C$400="M")*(MOVIMIENTOS!$D$5:$D$400="jabas")*(MOVIMIENTOS!$A$5:$A$400<>"")*(MOVIMIENTOS!$A$5:$A$400<=$A12)*MOVIMIENTOS!$E$5:$E$400)+SUMPRODUCT((MOVIMIENTOS!$B$5:$B$400="DEVOLUCIÓN")*(MOVIMIENTOS!$C$5:$C$400="M")*(MOVIMIENTOS!$D$5:$D$400="jabas")*(MOVIMIENTOS!$A$5:$A$400<>"")*(MOVIMIENTOS!$A$5:$A$400<=$A12)*MOVIMIENTOS!$E$5:$E$400)-SUMPRODUCT((MOVIMIENTOS!$B$5:$B$400="TRASIEGO")*(MOVIMIENTOS!$C$5:$C$400="M")*(MOVIMIENTOS!$D$5:$D$400="jabas")*(MOVIMIENTOS!$A$5:$A$400<>"")*(MOVIMIENTOS!$A$5:$A$400<=$A12)*MOVIMIENTOS!$E$5:$E$400)-SUMPRODUCT((MOVIMIENTOS!$B$5:$B$400="REGALO")*(MOVIMIENTOS!$C$5:$C$400="M")*(MOVIMIENTOS!$D$5:$D$400="jabas")*(MOVIMIENTOS!$A$5:$A$400<>"")*(MOVIMIENTOS!$A$5:$A$400<=$A12)*MOVIMIENTOS!$E$5:$E$400)-SUMPRODUCT((MOVIMIENTOS!$B$5:$B$400="VENTA")*(MOVIMIENTOS!$C$5:$C$400="M")*(MOVIMIENTOS!$D$5:$D$400="jabas")*(MOVIMIENTOS!$A$5:$A$400<>"")*(MOVIMIENTOS!$A$5:$A$400<=$A12)*MOVIMIENTOS!$E$5:$E$400)+SUMPRODUCT((MOVIMIENTOS!$B$5:$B$400="AJUSTE")*(MOVIMIENTOS!$C$5:$C$400="M")*(MOVIMIENTOS!$D$5:$D$400="jabas")*(MOVIMIENTOS!$A$5:$A$400<>"")*(MOVIMIENTOS!$A$5:$A$400<=$A12)*MOVIMIENTOS!$E$5:$E$400)) -> 55 | F12: =IF($A12="","",SUMPRODUCT((MOVIMIENTOS!$B$5:$B$400="SALDO INICIAL")*(MOVIMIENTOS!$C$5:$C$400="Chancho")*(MOVIMIENTOS!$D$5:$D$400="sacos")*(MOVIMIENTOS!$A$5:$A$400<>"")*(MOVIMIENTOS!$A$5:$A$400<=$A12)*MOVIMIENTOS!$E$5:$E$400)+SUMPRODUCT((MOVIMIENTOS!$B$5:$B$400="PROCESO")*(MOVIMIENTOS!$C$5:$C$400="Chancho")*(MOVIMIENTOS!$D$5:$D$400="sacos")*(MOVIMIENTOS!$A$5:$A$400<>"")*(MOVIMIENTOS!$A$5:$A$400<=$A12)*MOVIMIENTOS!$E$5:$E$400)-SUMPRODUCT((MOVIMIENTOS!$B$5:$B$400="VENTA CHANCHO")*(MOVIMIENTOS!$C$5:$C$400="Chancho")*(MOVIMIENTOS!$D$5:$D$400="sacos")*(MOVIMIENTOS!$A$5:$A$400<>"")*(MOVIMIENTOS!$A$5:$A$400<=$A12)*MOVIMIENTOS!$E$5:$E$400)-SUMPRODUCT((MOVIMIENTOS!$B$5:$B$400="REGALO")*(MOVIMIENTOS!$C$5:$C$400="Chancho")*(MOVIMIENTOS!$D$5:$D$400="sacos")*(MOVIMIENTOS!$A$5:$A$400<>"")*(MOVIMIENTOS!$A$5:$A$400<=$A12)*MOVIMIENTOS!$E$5:$E$400)-SUMPRODUCT((MOVIMIENTOS!$B$5:$B$400="VENTA")*(MOVIMIENTOS!$C$5:$C$400="Chancho")*(MOVIMIENTOS!$D$5:$D$400="sacos")*(MOVIMIENTOS!$A$5:$A$400<>"")*(MOVIMIENTOS!$A$5:$A$400<=$A12)*MOVIMIENTOS!$E$5:$E$400)+SUMPRODUCT((MOVIMIENTOS!$B$5:$B$400="AJUSTE")*(MOVIMIENTOS!$C$5:$C$400="Chancho")*(MOVIMIENTOS!$D$5:$D$400="sacos")*(MOVIMIENTOS!$A$5:$A$400<>"")*(MOVIMIENTOS!$A$5:$A$400<=$A12)*MOVIMIENTOS!$E$5:$E$400)) -> 15 | G12: =IF($A12="","",SUM(B12:E12)) -> 142 | H12: =IF($A12="","",SUMPRODUCT((((MOVIMIENTOS!$B$5:$B$400="SALDO INICIAL")*(MOVIMIENTOS!$C$5:$C$400<>"Chancho"))+(MOVIMIENTOS!$B$5:$B$400="COMPRA")+(MOVIMIENTOS!$B$5:$B$400="REPROCESO")+(MOVIMIENTOS!$B$5:$B$400="DEVOLUCIÓN")+((MOVIMIENTOS!$B$5:$B$400="AJUSTE")*(MOVIMIENTOS!$C$5:$C$400<>"Chancho")))*(MOVIMIENTOS!$A$5:$A$400<>"")*(MOVIMIENTOS!$A$5:$A$400<=$A12)*MOVIMIENTOS!$I$5:$I$400)-SUMPRODUCT(((MOVIMIENTOS!$B$5:$B$400="ENVÍO A SUPESA")+(MOVIMIENTOS!$B$5:$B$400="ENVÍO A TOTTUS")+(MOVIMIENTOS!$B$5:$B$400="ENVIO A TOTTUS")+(MOVIMIENTOS!$B$5:$B$400="MALOGRADO")+(MOVIMIENTOS!$B$5:$B$400="OTRA SALIDA")+((MOVIMIENTOS!$B$5:$B$400="PROCESO")*(MOVIMIENTOS!$C$5:$C$400="Chancho"))+((MOVIMIENTOS!$B$5:$B$400="REGALO")*(MOVIMIENTOS!$C$5:$C$400<>"Chancho"))+((MOVIMIENTOS!$B$5:$B$400="VENTA")*(MOVIMIENTOS!$C$5:$C$400<>"Chancho")))*(MOVIMIENTOS!$A$5:$A$400<>"")*(MOVIMIENTOS!$A$5:$A$400<=$A12)*MOVIMIENTOS!$I$5:$I$400)) -> 2327 | J12: =IF(AND(MOVIMIENTOS!$A12<>"",COUNTIF(MOVIMIENTOS!$A$5:$A11,MOVIMIENTOS!$A12)=0),COUNT(J$4:J11)+1,"") | K12: =MOVIMIENTOS!$A12 -> 46215
A13: =IFERROR(INDEX(K$5:K$400,MATCH(ROW()-4,J$5:J$400,0)),"") -> 46222 | B13: =IF($A13="","",SUMPRODUCT((MOVIMIENTOS!$B$5:$B$400="SALDO INICIAL")*(MOVIMIENTOS!$C$5:$C$400="A")*(MOVIMIENTOS!$D$5:$D$400="jabas")*(MOVIMIENTOS!$A$5:$A$400<>"")*(MOVIMIENTOS!$A$5:$A$400<=$A13)*MOVIMIENTOS!$E$5:$E$400)+SUMPRODUCT((MOVIMIENTOS!$B$5:$B$400="PROCESO")*(MOVIMIENTOS!$C$5:$C$400="A")*(MOVIMIENTOS!$D$5:$D$400="jabas")*(MOVIMIENTOS!$A$5:$A$400<>"")*(MOVIMIENTOS!$A$5:$A$400<=$A13)*MOVIMIENTOS!$E$5:$E$400)-SUMPRODUCT((MOVIMIENTOS!$B$5:$B$400="ENVÍO A SUPESA")*(MOVIMIENTOS!$C$5:$C$400="A")*(MOVIMIENTOS!$D$5:$D$400="jabas")*(MOVIMIENTOS!$A$5:$A$400<>"")*(MOVIMIENTOS!$A$5:$A$400<=$A13)*MOVIMIENTOS!$E$5:$E$400)+SUMPRODUCT((MOVIMIENTOS!$B$5:$B$400="DEVOLUCIÓN")*(MOVIMIENTOS!$C$5:$C$400="A")*(MOVIMIENTOS!$D$5:$D$400="jabas")*(MOVIMIENTOS!$A$5:$A$400<>"")*(MOVIMIENTOS!$A$5:$A$400<=$A13)*MOVIMIENTOS!$E$5:$E$400)-SUMPRODUCT((MOVIMIENTOS!$B$5:$B$400="TRASIEGO")*(MOVIMIENTOS!$C$5:$C$400="A")*(MOVIMIENTOS!$D$5:$D$400="jabas")*(MOVIMIENTOS!$A$5:$A$400<>"")*(MOVIMIENTOS!$A$5:$A$400<=$A13)*MOVIMIENTOS!$E$5:$E$400)-SUMPRODUCT((MOVIMIENTOS!$B$5:$B$400="REGALO")*(MOVIMIENTOS!$C$5:$C$400="A")*(MOVIMIENTOS!$D$5:$D$400="jabas")*(MOVIMIENTOS!$A$5:$A$400<>"")*(MOVIMIENTOS!$A$5:$A$400<=$A13)*MOVIMIENTOS!$E$5:$E$400)-SUMPRODUCT((MOVIMIENTOS!$B$5:$B$400="VENTA")*(MOVIMIENTOS!$C$5:$C$400="A")*(MOVIMIENTOS!$D$5:$D$400="jabas")*(MOVIMIENTOS!$A$5:$A$400<>"")*(MOVIMIENTOS!$A$5:$A$400<=$A13)*MOVIMIENTOS!$E$5:$E$400)+SUMPRODUCT((MOVIMIENTOS!$B$5:$B$400="AJUSTE")*(MOVIMIENTOS!$C$5:$C$400="A")*(MOVIMIENTOS!$D$5:$D$400="jabas")*(MOVIMIENTOS!$A$5:$A$400<>"")*(MOVIMIENTOS!$A$5:$A$400<=$A13)*MOVIMIENTOS!$E$5:$E$400)) -> 37 | C13: =IF($A13="","",SUMPRODUCT((MOVIMIENTOS!$B$5:$B$400="SALDO INICIAL")*(MOVIMIENTOS!$C$5:$C$400="P")*(MOVIMIENTOS!$D$5:$D$400="jabas")*(MOVIMIENTOS!$A$5:$A$400<>"")*(MOVIMIENTOS!$A$5:$A$400<=$A13)*MOVIMIENTOS!$E$5:$E$400)+SUMPRODUCT((MOVIMIENTOS!$B$5:$B$400="PROCESO")*(MOVIMIENTOS!$C$5:$C$400="P")*(MOVIMIENTOS!$D$5:$D$400="jabas")*(MOVIMIENTOS!$A$5:$A$400<>"")*(MOVIMIENTOS!$A$5:$A$400<=$A13)*MOVIMIENTOS!$E$5:$E$400)-SUMPRODUCT((MOVIMIENTOS!$B$5:$B$400="ENVÍO A SUPESA")*(MOVIMIENTOS!$C$5:$C$400="P")*(MOVIMIENTOS!$D$5:$D$400="jabas")*(MOVIMIENTOS!$A$5:$A$400<>"")*(MOVIMIENTOS!$A$5:$A$400<=$A13)*MOVIMIENTOS!$E$5:$E$400)+SUMPRODUCT((MOVIMIENTOS!$B$5:$B$400="DEVOLUCIÓN")*(MOVIMIENTOS!$C$5:$C$400="P")*(MOVIMIENTOS!$D$5:$D$400="jabas")*(MOVIMIENTOS!$A$5:$A$400<>"")*(MOVIMIENTOS!$A$5:$A$400<=$A13)*MOVIMIENTOS!$E$5:$E$400)-SUMPRODUCT((MOVIMIENTOS!$B$5:$B$400="TRASIEGO")*(MOVIMIENTOS!$C$5:$C$400="P")*(MOVIMIENTOS!$D$5:$D$400="jabas")*(MOVIMIENTOS!$A$5:$A$400<>"")*(MOVIMIENTOS!$A$5:$A$400<=$A13)*MOVIMIENTOS!$E$5:$E$400)-SUMPRODUCT((MOVIMIENTOS!$B$5:$B$400="REGALO")*(MOVIMIENTOS!$C$5:$C$400="P")*(MOVIMIENTOS!$D$5:$D$400="jabas")*(MOVIMIENTOS!$A$5:$A$400<>"")*(MOVIMIENTOS!$A$5:$A$400<=$A13)*MOVIMIENTOS!$E$5:$E$400)-SUMPRODUCT((MOVIMIENTOS!$B$5:$B$400="VENTA")*(MOVIMIENTOS!$C$5:$C$400="P")*(MOVIMIENTOS!$D$5:$D$400="jabas")*(MOVIMIENTOS!$A$5:$A$400<>"")*(MOVIMIENTOS!$A$5:$A$400<=$A13)*MOVIMIENTOS!$E$5:$E$400)+SUMPRODUCT((MOVIMIENTOS!$B$5:$B$400="AJUSTE")*(MOVIMIENTOS!$C$5:$C$400="P")*(MOVIMIENTOS!$D$5:$D$400="jabas")*(MOVIMIENTOS!$A$5:$A$400<>"")*(MOVIMIENTOS!$A$5:$A$400<=$A13)*MOVIMIENTOS!$E$5:$E$400)) -> 0 | D13: =IF($A13="","",SUMPRODUCT((MOVIMIENTOS!$B$5:$B$400="SALDO INICIAL")*(MOVIMIENTOS!$C$5:$C$400="C")*(MOVIMIENTOS!$D$5:$D$400="jabas")*(MOVIMIENTOS!$A$5:$A$400<>"")*(MOVIMIENTOS!$A$5:$A$400<=$A13)*MOVIMIENTOS!$E$5:$E$400)+SUMPRODUCT((MOVIMIENTOS!$B$5:$B$400="PROCESO")*(MOVIMIENTOS!$C$5:$C$400="C")*(MOVIMIENTOS!$D$5:$D$400="jabas")*(MOVIMIENTOS!$A$5:$A$400<>"")*(MOVIMIENTOS!$A$5:$A$400<=$A13)*MOVIMIENTOS!$E$5:$E$400)-SUMPRODUCT((MOVIMIENTOS!$B$5:$B$400="ENVÍO A SUPESA")*(MOVIMIENTOS!$C$5:$C$400="C")*(MOVIMIENTOS!$D$5:$D$400="jabas")*(MOVIMIENTOS!$A$5:$A$400<>"")*(MOVIMIENTOS!$A$5:$A$400<=$A13)*MOVIMIENTOS!$E$5:$E$400)+SUMPRODUCT((MOVIMIENTOS!$B$5:$B$400="DEVOLUCIÓN")*(MOVIMIENTOS!$C$5:$C$400="C")*(MOVIMIENTOS!$D$5:$D$400="jabas")*(MOVIMIENTOS!$A$5:$A$400<>"")*(MOVIMIENTOS!$A$5:$A$400<=$A13)*MOVIMIENTOS!$E$5:$E$400)-SUMPRODUCT((MOVIMIENTOS!$B$5:$B$400="TRASIEGO")*(MOVIMIENTOS!$C$5:$C$400="C")*(MOVIMIENTOS!$D$5:$D$400="jabas")*(MOVIMIENTOS!$A$5:$A$400<>"")*(MOVIMIENTOS!$A$5:$A$400<=$A13)*MOVIMIENTOS!$E$5:$E$400)-SUMPRODUCT((MOVIMIENTOS!$B$5:$B$400="REGALO")*(MOVIMIENTOS!$C$5:$C$400="C")*(MOVIMIENTOS!$D$5:$D$400="jabas")*(MOVIMIENTOS!$A$5:$A$400<>"")*(MOVIMIENTOS!$A$5:$A$400<=$A13)*MOVIMIENTOS!$E$5:$E$400)-SUMPRODUCT((MOVIMIENTOS!$B$5:$B$400="VENTA")*(MOVIMIENTOS!$C$5:$C$400="C")*(MOVIMIENTOS!$D$5:$D$400="jabas")*(MOVIMIENTOS!$A$5:$A$400<>"")*(MOVIMIENTOS!$A$5:$A$400<=$A13)*MOVIMIENTOS!$E$5:$E$400)+SUMPRODUCT((MOVIMIENTOS!$B$5:$B$400="AJUSTE")*(MOVIMIENTOS!$C$5:$C$400="C")*(MOVIMIENTOS!$D$5:$D$400="jabas")*(MOVIMIENTOS!$A$5:$A$400<>"")*(MOVIMIENTOS!$A$5:$A$400<=$A13)*MOVIMIENTOS!$E$5:$E$400)) -> 0 | E13: =IF($A13="","",SUMPRODUCT((MOVIMIENTOS!$B$5:$B$400="SALDO INICIAL")*(MOVIMIENTOS!$C$5:$C$400="M")*(MOVIMIENTOS!$D$5:$D$400="jabas")*(MOVIMIENTOS!$A$5:$A$400<>"")*(MOVIMIENTOS!$A$5:$A$400<=$A13)*MOVIMIENTOS!$E$5:$E$400)+SUMPRODUCT((MOVIMIENTOS!$B$5:$B$400="PROCESO")*(MOVIMIENTOS!$C$5:$C$400="M")*(MOVIMIENTOS!$D$5:$D$400="jabas")*(MOVIMIENTOS!$A$5:$A$400<>"")*(MOVIMIENTOS!$A$5:$A$400<=$A13)*MOVIMIENTOS!$E$5:$E$400)-SUMPRODUCT((MOVIMIENTOS!$B$5:$B$400="ENVÍO A SUPESA")*(MOVIMIENTOS!$C$5:$C$400="M")*(MOVIMIENTOS!$D$5:$D$400="jabas")*(MOVIMIENTOS!$A$5:$A$400<>"")*(MOVIMIENTOS!$A$5:$A$400<=$A13)*MOVIMIENTOS!$E$5:$E$400)+SUMPRODUCT((MOVIMIENTOS!$B$5:$B$400="DEVOLUCIÓN")*(MOVIMIENTOS!$C$5:$C$400="M")*(MOVIMIENTOS!$D$5:$D$400="jabas")*(MOVIMIENTOS!$A$5:$A$400<>"")*(MOVIMIENTOS!$A$5:$A$400<=$A13)*MOVIMIENTOS!$E$5:$E$400)-SUMPRODUCT((MOVIMIENTOS!$B$5:$B$400="TRASIEGO")*(MOVIMIENTOS!$C$5:$C$400="M")*(MOVIMIENTOS!$D$5:$D$400="jabas")*(MOVIMIENTOS!$A$5:$A$400<>"")*(MOVIMIENTOS!$A$5:$A$400<=$A13)*MOVIMIENTOS!$E$5:$E$400)-SUMPRODUCT((MOVIMIENTOS!$B$5:$B$400="REGALO")*(MOVIMIENTOS!$C$5:$C$400="M")*(MOVIMIENTOS!$D$5:$D$400="jabas")*(MOVIMIENTOS!$A$5:$A$400<>"")*(MOVIMIENTOS!$A$5:$A$400<=$A13)*MOVIMIENTOS!$E$5:$E$400)-SUMPRODUCT((MOVIMIENTOS!$B$5:$B$400="VENTA")*(MOVIMIENTOS!$C$5:$C$400="M")*(MOVIMIENTOS!$D$5:$D$400="jabas")*(MOVIMIENTOS!$A$5:$A$400<>"")*(MOVIMIENTOS!$A$5:$A$400<=$A13)*MOVIMIENTOS!$E$5:$E$400)+SUMPRODUCT((MOVIMIENTOS!$B$5:$B$400="AJUSTE")*(MOVIMIENTOS!$C$5:$C$400="M")*(MOVIMIENTOS!$D$5:$D$400="jabas")*(MOVIMIENTOS!$A$5:$A$400<>"")*(MOVIMIENTOS!$A$5:$A$400<=$A13)*MOVIMIENTOS!$E$5:$E$400)) -> 61 | F13: =IF($A13="","",SUMPRODUCT((MOVIMIENTOS!$B$5:$B$400="SALDO INICIAL")*(MOVIMIENTOS!$C$5:$C$400="Chancho")*(MOVIMIENTOS!$D$5:$D$400="sacos")*(MOVIMIENTOS!$A$5:$A$400<>"")*(MOVIMIENTOS!$A$5:$A$400<=$A13)*MOVIMIENTOS!$E$5:$E$400)+SUMPRODUCT((MOVIMIENTOS!$B$5:$B$400="PROCESO")*(MOVIMIENTOS!$C$5:$C$400="Chancho")*(MOVIMIENTOS!$D$5:$D$400="sacos")*(MOVIMIENTOS!$A$5:$A$400<>"")*(MOVIMIENTOS!$A$5:$A$400<=$A13)*MOVIMIENTOS!$E$5:$E$400)-SUMPRODUCT((MOVIMIENTOS!$B$5:$B$400="VENTA CHANCHO")*(MOVIMIENTOS!$C$5:$C$400="Chancho")*(MOVIMIENTOS!$D$5:$D$400="sacos")*(MOVIMIENTOS!$A$5:$A$400<>"")*(MOVIMIENTOS!$A$5:$A$400<=$A13)*MOVIMIENTOS!$E$5:$E$400)-SUMPRODUCT((MOVIMIENTOS!$B$5:$B$400="REGALO")*(MOVIMIENTOS!$C$5:$C$400="Chancho")*(MOVIMIENTOS!$D$5:$D$400="sacos")*(MOVIMIENTOS!$A$5:$A$400<>"")*(MOVIMIENTOS!$A$5:$A$400<=$A13)*MOVIMIENTOS!$E$5:$E$400)-SUMPRODUCT((MOVIMIENTOS!$B$5:$B$400="VENTA")*(MOVIMIENTOS!$C$5:$C$400="Chancho")*(MOVIMIENTOS!$D$5:$D$400="sacos")*(MOVIMIENTOS!$A$5:$A$400<>"")*(MOVIMIENTOS!$A$5:$A$400<=$A13)*MOVIMIENTOS!$E$5:$E$400)+SUMPRODUCT((MOVIMIENTOS!$B$5:$B$400="AJUSTE")*(MOVIMIENTOS!$C$5:$C$400="Chancho")*(MOVIMIENTOS!$D$5:$D$400="sacos")*(MOVIMIENTOS!$A$5:$A$400<>"")*(MOVIMIENTOS!$A$5:$A$400<=$A13)*MOVIMIENTOS!$E$5:$E$400)) -> 18 | G13: =IF($A13="","",SUM(B13:E13)) -> 98 | H13: =IF($A13="","",SUMPRODUCT((((MOVIMIENTOS!$B$5:$B$400="SALDO INICIAL")*(MOVIMIENTOS!$C$5:$C$400<>"Chancho"))+(MOVIMIENTOS!$B$5:$B$400="COMPRA")+(MOVIMIENTOS!$B$5:$B$400="REPROCESO")+(MOVIMIENTOS!$B$5:$B$400="DEVOLUCIÓN")+((MOVIMIENTOS!$B$5:$B$400="AJUSTE")*(MOVIMIENTOS!$C$5:$C$400<>"Chancho")))*(MOVIMIENTOS!$A$5:$A$400<>"")*(MOVIMIENTOS!$A$5:$A$400<=$A13)*MOVIMIENTOS!$I$5:$I$400)-SUMPRODUCT(((MOVIMIENTOS!$B$5:$B$400="ENVÍO A SUPESA")+(MOVIMIENTOS!$B$5:$B$400="ENVÍO A TOTTUS")+(MOVIMIENTOS!$B$5:$B$400="ENVIO A TOTTUS")+(MOVIMIENTOS!$B$5:$B$400="MALOGRADO")+(MOVIMIENTOS!$B$5:$B$400="OTRA SALIDA")+((MOVIMIENTOS!$B$5:$B$400="PROCESO")*(MOVIMIENTOS!$C$5:$C$400="Chancho"))+((MOVIMIENTOS!$B$5:$B$400="REGALO")*(MOVIMIENTOS!$C$5:$C$400<>"Chancho"))+((MOVIMIENTOS!$B$5:$B$400="VENTA")*(MOVIMIENTOS!$C$5:$C$400<>"Chancho")))*(MOVIMIENTOS!$A$5:$A$400<>"")*(MOVIMIENTOS!$A$5:$A$400<=$A13)*MOVIMIENTOS!$I$5:$I$400)) -> 1802 | J13: =IF(AND(MOVIMIENTOS!$A13<>"",COUNTIF(MOVIMIENTOS!$A$5:$A12,MOVIMIENTOS!$A13)=0),COUNT(J$4:J12)+1,"") | K13: =MOVIMIENTOS!$A13 -> 46215
A14: =IFERROR(INDEX(K$5:K$400,MATCH(ROW()-4,J$5:J$400,0)),"") -> 46223 | B14: =IF($A14="","",SUMPRODUCT((MOVIMIENTOS!$B$5:$B$400="SALDO INICIAL")*(MOVIMIENTOS!$C$5:$C$400="A")*(MOVIMIENTOS!$D$5:$D$400="jabas")*(MOVIMIENTOS!$A$5:$A$400<>"")*(MOVIMIENTOS!$A$5:$A$400<=$A14)*MOVIMIENTOS!$E$5:$E$400)+SUMPRODUCT((MOVIMIENTOS!$B$5:$B$400="PROCESO")*(MOVIMIENTOS!$C$5:$C$400="A")*(MOVIMIENTOS!$D$5:$D$400="jabas")*(MOVIMIENTOS!$A$5:$A$400<>"")*(MOVIMIENTOS!$A$5:$A$400<=$A14)*MOVIMIENTOS!$E$5:$E$400)-SUMPRODUCT((MOVIMIENTOS!$B$5:$B$400="ENVÍO A SUPESA")*(MOVIMIENTOS!$C$5:$C$400="A")*(MOVIMIENTOS!$D$5:$D$400="jabas")*(MOVIMIENTOS!$A$5:$A$400<>"")*(MOVIMIENTOS!$A$5:$A$400<=$A14)*MOVIMIENTOS!$E$5:$E$400)+SUMPRODUCT((MOVIMIENTOS!$B$5:$B$400="DEVOLUCIÓN")*(MOVIMIENTOS!$C$5:$C$400="A")*(MOVIMIENTOS!$D$5:$D$400="jabas")*(MOVIMIENTOS!$A$5:$A$400<>"")*(MOVIMIENTOS!$A$5:$A$400<=$A14)*MOVIMIENTOS!$E$5:$E$400)-SUMPRODUCT((MOVIMIENTOS!$B$5:$B$400="TRASIEGO")*(MOVIMIENTOS!$C$5:$C$400="A")*(MOVIMIENTOS!$D$5:$D$400="jabas")*(MOVIMIENTOS!$A$5:$A$400<>"")*(MOVIMIENTOS!$A$5:$A$400<=$A14)*MOVIMIENTOS!$E$5:$E$400)-SUMPRODUCT((MOVIMIENTOS!$B$5:$B$400="REGALO")*(MOVIMIENTOS!$C$5:$C$400="A")*(MOVIMIENTOS!$D$5:$D$400="jabas")*(MOVIMIENTOS!$A$5:$A$400<>"")*(MOVIMIENTOS!$A$5:$A$400<=$A14)*MOVIMIENTOS!$E$5:$E$400)-SUMPRODUCT((MOVIMIENTOS!$B$5:$B$400="VENTA")*(MOVIMIENTOS!$C$5:$C$400="A")*(MOVIMIENTOS!$D$5:$D$400="jabas")*(MOVIMIENTOS!$A$5:$A$400<>"")*(MOVIMIENTOS!$A$5:$A$400<=$A14)*MOVIMIENTOS!$E$5:$E$400)+SUMPRODUCT((MOVIMIENTOS!$B$5:$B$400="AJUSTE")*(MOVIMIENTOS!$C$5:$C$400="A")*(MOVIMIENTOS!$D$5:$D$400="jabas")*(MOVIMIENTOS!$A$5:$A$400<>"")*(MOVIMIENTOS!$A$5:$A$400<=$A14)*MOVIMIENTOS!$E$5:$E$400)) -> 38 | C14: =IF($A14="","",SUMPRODUCT((MOVIMIENTOS!$B$5:$B$400="SALDO INICIAL")*(MOVIMIENTOS!$C$5:$C$400="P")*(MOVIMIENTOS!$D$5:$D$400="jabas")*(MOVIMIENTOS!$A$5:$A$400<>"")*(MOVIMIENTOS!$A$5:$A$400<=$A14)*MOVIMIENTOS!$E$5:$E$400)+SUMPRODUCT((MOVIMIENTOS!$B$5:$B$400="PROCESO")*(MOVIMIENTOS!$C$5:$C$400="P")*(MOVIMIENTOS!$D$5:$D$400="jabas")*(MOVIMIENTOS!$A$5:$A$400<>"")*(MOVIMIENTOS!$A$5:$A$400<=$A14)*MOVIMIENTOS!$E$5:$E$400)-SUMPRODUCT((MOVIMIENTOS!$B$5:$B$400="ENVÍO A SUPESA")*(MOVIMIENTOS!$C$5:$C$400="P")*(MOVIMIENTOS!$D$5:$D$400="jabas")*(MOVIMIENTOS!$A$5:$A$400<>"")*(MOVIMIENTOS!$A$5:$A$400<=$A14)*MOVIMIENTOS!$E$5:$E$400)+SUMPRODUCT((MOVIMIENTOS!$B$5:$B$400="DEVOLUCIÓN")*(MOVIMIENTOS!$C$5:$C$400="P")*(MOVIMIENTOS!$D$5:$D$400="jabas")*(MOVIMIENTOS!$A$5:$A$400<>"")*(MOVIMIENTOS!$A$5:$A$400<=$A14)*MOVIMIENTOS!$E$5:$E$400)-SUMPRODUCT((MOVIMIENTOS!$B$5:$B$400="TRASIEGO")*(MOVIMIENTOS!$C$5:$C$400="P")*(MOVIMIENTOS!$D$5:$D$400="jabas")*(MOVIMIENTOS!$A$5:$A$400<>"")*(MOVIMIENTOS!$A$5:$A$400<=$A14)*MOVIMIENTOS!$E$5:$E$400)-SUMPRODUCT((MOVIMIENTOS!$B$5:$B$400="REGALO")*(MOVIMIENTOS!$C$5:$C$400="P")*(MOVIMIENTOS!$D$5:$D$400="jabas")*(MOVIMIENTOS!$A$5:$A$400<>"")*(MOVIMIENTOS!$A$5:$A$400<=$A14)*MOVIMIENTOS!$E$5:$E$400)-SUMPRODUCT((MOVIMIENTOS!$B$5:$B$400="VENTA")*(MOVIMIENTOS!$C$5:$C$400="P")*(MOVIMIENTOS!$D$5:$D$400="jabas")*(MOVIMIENTOS!$A$5:$A$400<>"")*(MOVIMIENTOS!$A$5:$A$400<=$A14)*MOVIMIENTOS!$E$5:$E$400)+SUMPRODUCT((MOVIMIENTOS!$B$5:$B$400="AJUSTE")*(MOVIMIENTOS!$C$5:$C$400="P")*(MOVIMIENTOS!$D$5:$D$400="jabas")*(MOVIMIENTOS!$A$5:$A$400<>"")*(MOVIMIENTOS!$A$5:$A$400<=$A14)*MOVIMIENTOS!$E$5:$E$400)) -> 11 | D14: =IF($A14="","",SUMPRODUCT((MOVIMIENTOS!$B$5:$B$400="SALDO INICIAL")*(MOVIMIENTOS!$C$5:$C$400="C")*(MOVIMIENTOS!$D$5:$D$400="jabas")*(MOVIMIENTOS!$A$5:$A$400<>"")*(MOVIMIENTOS!$A$5:$A$400<=$A14)*MOVIMIENTOS!$E$5:$E$400)+SUMPRODUCT((MOVIMIENTOS!$B$5:$B$400="PROCESO")*(MOVIMIENTOS!$C$5:$C$400="C")*(MOVIMIENTOS!$D$5:$D$400="jabas")*(MOVIMIENTOS!$A$5:$A$400<>"")*(MOVIMIENTOS!$A$5:$A$400<=$A14)*MOVIMIENTOS!$E$5:$E$400)-SUMPRODUCT((MOVIMIENTOS!$B$5:$B$400="ENVÍO A SUPESA")*(MOVIMIENTOS!$C$5:$C$400="C")*(MOVIMIENTOS!$D$5:$D$400="jabas")*(MOVIMIENTOS!$A$5:$A$400<>"")*(MOVIMIENTOS!$A$5:$A$400<=$A14)*MOVIMIENTOS!$E$5:$E$400)+SUMPRODUCT((MOVIMIENTOS!$B$5:$B$400="DEVOLUCIÓN")*(MOVIMIENTOS!$C$5:$C$400="C")*(MOVIMIENTOS!$D$5:$D$400="jabas")*(MOVIMIENTOS!$A$5:$A$400<>"")*(MOVIMIENTOS!$A$5:$A$400<=$A14)*MOVIMIENTOS!$E$5:$E$400)-SUMPRODUCT((MOVIMIENTOS!$B$5:$B$400="TRASIEGO")*(MOVIMIENTOS!$C$5:$C$400="C")*(MOVIMIENTOS!$D$5:$D$400="jabas")*(MOVIMIENTOS!$A$5:$A$400<>"")*(MOVIMIENTOS!$A$5:$A$400<=$A14)*MOVIMIENTOS!$E$5:$E$400)-SUMPRODUCT((MOVIMIENTOS!$B$5:$B$400="REGALO")*(MOVIMIENTOS!$C$5:$C$400="C")*(MOVIMIENTOS!$D$5:$D$400="jabas")*(MOVIMIENTOS!$A$5:$A$400<>"")*(MOVIMIENTOS!$A$5:$A$400<=$A14)*MOVIMIENTOS!$E$5:$E$400)-SUMPRODUCT((MOVIMIENTOS!$B$5:$B$400="VENTA")*(MOVIMIENTOS!$C$5:$C$400="C")*(MOVIMIENTOS!$D$5:$D$400="jabas")*(MOVIMIENTOS!$A$5:$A$400<>"")*(MOVIMIENTOS!$A$5:$A$400<=$A14)*MOVIMIENTOS!$E$5:$E$400)+SUMPRODUCT((MOVIMIENTOS!$B$5:$B$400="AJUSTE")*(MOVIMIENTOS!$C$5:$C$400="C")*(MOVIMIENTOS!$D$5:$D$400="jabas")*(MOVIMIENTOS!$A$5:$A$400<>"")*(MOVIMIENTOS!$A$5:$A$400<=$A14)*MOVIMIENTOS!$E$5:$E$400)) -> 10 | E14: =IF($A14="","",SUMPRODUCT((MOVIMIENTOS!$B$5:$B$400="SALDO INICIAL")*(MOVIMIENTOS!$C$5:$C$400="M")*(MOVIMIENTOS!$D$5:$D$400="jabas")*(MOVIMIENTOS!$A$5:$A$400<>"")*(MOVIMIENTOS!$A$5:$A$400<=$A14)*MOVIMIENTOS!$E$5:$E$400)+SUMPRODUCT((MOVIMIENTOS!$B$5:$B$400="PROCESO")*(MOVIMIENTOS!$C$5:$C$400="M")*(MOVIMIENTOS!$D$5:$D$400="jabas")*(MOVIMIENTOS!$A$5:$A$400<>"")*(MOVIMIENTOS!$A$5:$A$400<=$A14)*MOVIMIENTOS!$E$5:$E$400)-SUMPRODUCT((MOVIMIENTOS!$B$5:$B$400="ENVÍO A SUPESA")*(MOVIMIENTOS!$C$5:$C$400="M")*(MOVIMIENTOS!$D$5:$D$400="jabas")*(MOVIMIENTOS!$A$5:$A$400<>"")*(MOVIMIENTOS!$A$5:$A$400<=$A14)*MOVIMIENTOS!$E$5:$E$400)+SUMPRODUCT((MOVIMIENTOS!$B$5:$B$400="DEVOLUCIÓN")*(MOVIMIENTOS!$C$5:$C$400="M")*(MOVIMIENTOS!$D$5:$D$400="jabas")*(MOVIMIENTOS!$A$5:$A$400<>"")*(MOVIMIENTOS!$A$5:$A$400<=$A14)*MOVIMIENTOS!$E$5:$E$400)-SUMPRODUCT((MOVIMIENTOS!$B$5:$B$400="TRASIEGO")*(MOVIMIENTOS!$C$5:$C$400="M")*(MOVIMIENTOS!$D$5:$D$400="jabas")*(MOVIMIENTOS!$A$5:$A$400<>"")*(MOVIMIENTOS!$A$5:$A$400<=$A14)*MOVIMIENTOS!$E$5:$E$400)-SUMPRODUCT((MOVIMIENTOS!$B$5:$B$400="REGALO")*(MOVIMIENTOS!$C$5:$C$400="M")*(MOVIMIENTOS!$D$5:$D$400="jabas")*(MOVIMIENTOS!$A$5:$A$400<>"")*(MOVIMIENTOS!$A$5:$A$400<=$A14)*MOVIMIENTOS!$E$5:$E$400)-SUMPRODUCT((MOVIMIENTOS!$B$5:$B$400="VENTA")*(MOVIMIENTOS!$C$5:$C$400="M")*(MOVIMIENTOS!$D$5:$D$400="jabas")*(MOVIMIENTOS!$A$5:$A$400<>"")*(MOVIMIENTOS!$A$5:$A$400<=$A14)*MOVIMIENTOS!$E$5:$E$400)+SUMPRODUCT((MOVIMIENTOS!$B$5:$B$400="AJUSTE")*(MOVIMIENTOS!$C$5:$C$400="M")*(MOVIMIENTOS!$D$5:$D$400="jabas")*(MOVIMIENTOS!$A$5:$A$400<>"")*(MOVIMIENTOS!$A$5:$A$400<=$A14)*MOVIMIENTOS!$E$5:$E$400)) -> 79 | F14: =IF($A14="","",SUMPRODUCT((MOVIMIENTOS!$B$5:$B$400="SALDO INICIAL")*(MOVIMIENTOS!$C$5:$C$400="Chancho")*(MOVIMIENTOS!$D$5:$D$400="sacos")*(MOVIMIENTOS!$A$5:$A$400<>"")*(MOVIMIENTOS!$A$5:$A$400<=$A14)*MOVIMIENTOS!$E$5:$E$400)+SUMPRODUCT((MOVIMIENTOS!$B$5:$B$400="PROCESO")*(MOVIMIENTOS!$C$5:$C$400="Chancho")*(MOVIMIENTOS!$D$5:$D$400="sacos")*(MOVIMIENTOS!$A$5:$A$400<>"")*(MOVIMIENTOS!$A$5:$A$400<=$A14)*MOVIMIENTOS!$E$5:$E$400)-SUMPRODUCT((MOVIMIENTOS!$B$5:$B$400="VENTA CHANCHO")*(MOVIMIENTOS!$C$5:$C$400="Chancho")*(MOVIMIENTOS!$D$5:$D$400="sacos")*(MOVIMIENTOS!$A$5:$A$400<>"")*(MOVIMIENTOS!$A$5:$A$400<=$A14)*MOVIMIENTOS!$E$5:$E$400)-SUMPRODUCT((MOVIMIENTOS!$B$5:$B$400="REGALO")*(MOVIMIENTOS!$C$5:$C$400="Chancho")*(MOVIMIENTOS!$D$5:$D$400="sacos")*(MOVIMIENTOS!$A$5:$A$400<>"")*(MOVIMIENTOS!$A$5:$A$400<=$A14)*MOVIMIENTOS!$E$5:$E$400)-SUMPRODUCT((MOVIMIENTOS!$B$5:$B$400="VENTA")*(MOVIMIENTOS!$C$5:$C$400="Chancho")*(MOVIMIENTOS!$D$5:$D$400="sacos")*(MOVIMIENTOS!$A$5:$A$400<>"")*(MOVIMIENTOS!$A$5:$A$400<=$A14)*MOVIMIENTOS!$E$5:$E$400)+SUMPRODUCT((MOVIMIENTOS!$B$5:$B$400="AJUSTE")*(MOVIMIENTOS!$C$5:$C$400="Chancho")*(MOVIMIENTOS!$D$5:$D$400="sacos")*(MOVIMIENTOS!$A$5:$A$400<>"")*(MOVIMIENTOS!$A$5:$A$400<=$A14)*MOVIMIENTOS!$E$5:$E$400)) -> 6.5 | G14: =IF($A14="","",SUM(B14:E14)) -> 138 | H14: =IF($A14="","",SUMPRODUCT((((MOVIMIENTOS!$B$5:$B$400="SALDO INICIAL")*(MOVIMIENTOS!$C$5:$C$400<>"Chancho"))+(MOVIMIENTOS!$B$5:$B$400="COMPRA")+(MOVIMIENTOS!$B$5:$B$400="REPROCESO")+(MOVIMIENTOS!$B$5:$B$400="DEVOLUCIÓN")+((MOVIMIENTOS!$B$5:$B$400="AJUSTE")*(MOVIMIENTOS!$C$5:$C$400<>"Chancho")))*(MOVIMIENTOS!$A$5:$A$400<>"")*(MOVIMIENTOS!$A$5:$A$400<=$A14)*MOVIMIENTOS!$I$5:$I$400)-SUMPRODUCT(((MOVIMIENTOS!$B$5:$B$400="ENVÍO A SUPESA")+(MOVIMIENTOS!$B$5:$B$400="ENVÍO A TOTTUS")+(MOVIMIENTOS!$B$5:$B$400="ENVIO A TOTTUS")+(MOVIMIENTOS!$B$5:$B$400="MALOGRADO")+(MOVIMIENTOS!$B$5:$B$400="OTRA SALIDA")+((MOVIMIENTOS!$B$5:$B$400="PROCESO")*(MOVIMIENTOS!$C$5:$C$400="Chancho"))+((MOVIMIENTOS!$B$5:$B$400="REGALO")*(MOVIMIENTOS!$C$5:$C$400<>"Chancho"))+((MOVIMIENTOS!$B$5:$B$400="VENTA")*(MOVIMIENTOS!$C$5:$C$400<>"Chancho")))*(MOVIMIENTOS!$A$5:$A$400<>"")*(MOVIMIENTOS!$A$5:$A$400<=$A14)*MOVIMIENTOS!$I$5:$I$400)) -> 4667.5 | J14: =IF(AND(MOVIMIENTOS!$A14<>"",COUNTIF(MOVIMIENTOS!$A$5:$A13,MOVIMIENTOS!$A14)=0),COUNT(J$4:J13)+1,"") | K14: =MOVIMIENTOS!$A14 -> 46215
A15: =IFERROR(INDEX(K$5:K$400,MATCH(ROW()-4,J$5:J$400,0)),"") -> 46224 | B15: =IF($A15="","",SUMPRODUCT((MOVIMIENTOS!$B$5:$B$400="SALDO INICIAL")*(MOVIMIENTOS!$C$5:$C$400="A")*(MOVIMIENTOS!$D$5:$D$400="jabas")*(MOVIMIENTOS!$A$5:$A$400<>"")*(MOVIMIENTOS!$A$5:$A$400<=$A15)*MOVIMIENTOS!$E$5:$E$400)+SUMPRODUCT((MOVIMIENTOS!$B$5:$B$400="PROCESO")*(MOVIMIENTOS!$C$5:$C$400="A")*(MOVIMIENTOS!$D$5:$D$400="jabas")*(MOVIMIENTOS!$A$5:$A$400<>"")*(MOVIMIENTOS!$A$5:$A$400<=$A15)*MOVIMIENTOS!$E$5:$E$400)-SUMPRODUCT((MOVIMIENTOS!$B$5:$B$400="ENVÍO A SUPESA")*(MOVIMIENTOS!$C$5:$C$400="A")*(MOVIMIENTOS!$D$5:$D$400="jabas")*(MOVIMIENTOS!$A$5:$A$400<>"")*(MOVIMIENTOS!$A$5:$A$400<=$A15)*MOVIMIENTOS!$E$5:$E$400)+SUMPRODUCT((MOVIMIENTOS!$B$5:$B$400="DEVOLUCIÓN")*(MOVIMIENTOS!$C$5:$C$400="A")*(MOVIMIENTOS!$D$5:$D$400="jabas")*(MOVIMIENTOS!$A$5:$A$400<>"")*(MOVIMIENTOS!$A$5:$A$400<=$A15)*MOVIMIENTOS!$E$5:$E$400)-SUMPRODUCT((MOVIMIENTOS!$B$5:$B$400="TRASIEGO")*(MOVIMIENTOS!$C$5:$C$400="A")*(MOVIMIENTOS!$D$5:$D$400="jabas")*(MOVIMIENTOS!$A$5:$A$400<>"")*(MOVIMIENTOS!$A$5:$A$400<=$A15)*MOVIMIENTOS!$E$5:$E$400)-SUMPRODUCT((MOVIMIENTOS!$B$5:$B$400="REGALO")*(MOVIMIENTOS!$C$5:$C$400="A")*(MOVIMIENTOS!$D$5:$D$400="jabas")*(MOVIMIENTOS!$A$5:$A$400<>"")*(MOVIMIENTOS!$A$5:$A$400<=$A15)*MOVIMIENTOS!$E$5:$E$400)-SUMPRODUCT((MOVIMIENTOS!$B$5:$B$400="VENTA")*(MOVIMIENTOS!$C$5:$C$400="A")*(MOVIMIENTOS!$D$5:$D$400="jabas")*(MOVIMIENTOS!$A$5:$A$400<>"")*(MOVIMIENTOS!$A$5:$A$400<=$A15)*MOVIMIENTOS!$E$5:$E$400)+SUMPRODUCT((MOVIMIENTOS!$B$5:$B$400="AJUSTE")*(MOVIMIENTOS!$C$5:$C$400="A")*(MOVIMIENTOS!$D$5:$D$400="jabas")*(MOVIMIENTOS!$A$5:$A$400<>"")*(MOVIMIENTOS!$A$5:$A$400<=$A15)*MOVIMIENTOS!$E$5:$E$400)) -> 60 | C15: =IF($A15="","",SUMPRODUCT((MOVIMIENTOS!$B$5:$B$400="SALDO INICIAL")*(MOVIMIENTOS!$C$5:$C$400="P")*(MOVIMIENTOS!$D$5:$D$400="jabas")*(MOVIMIENTOS!$A$5:$A$400<>"")*(MOVIMIENTOS!$A$5:$A$400<=$A15)*MOVIMIENTOS!$E$5:$E$400)+SUMPRODUCT((MOVIMIENTOS!$B$5:$B$400="PROCESO")*(MOVIMIENTOS!$C$5:$C$400="P")*(MOVIMIENTOS!$D$5:$D$400="jabas")*(MOVIMIENTOS!$A$5:$A$400<>"")*(MOVIMIENTOS!$A$5:$A$400<=$A15)*MOVIMIENTOS!$E$5:$E$400)-SUMPRODUCT((MOVIMIENTOS!$B$5:$B$400="ENVÍO A SUPESA")*(MOVIMIENTOS!$C$5:$C$400="P")*(MOVIMIENTOS!$D$5:$D$400="jabas")*(MOVIMIENTOS!$A$5:$A$400<>"")*(MOVIMIENTOS!$A$5:$A$400<=$A15)*MOVIMIENTOS!$E$5:$E$400)+SUMPRODUCT((MOVIMIENTOS!$B$5:$B$400="DEVOLUCIÓN")*(MOVIMIENTOS!$C$5:$C$400="P")*(MOVIMIENTOS!$D$5:$D$400="jabas")*(MOVIMIENTOS!$A$5:$A$400<>"")*(MOVIMIENTOS!$A$5:$A$400<=$A15)*MOVIMIENTOS!$E$5:$E$400)-SUMPRODUCT((MOVIMIENTOS!$B$5:$B$400="TRASIEGO")*(MOVIMIENTOS!$C$5:$C$400="P")*(MOVIMIENTOS!$D$5:$D$400="jabas")*(MOVIMIENTOS!$A$5:$A$400<>"")*(MOVIMIENTOS!$A$5:$A$400<=$A15)*MOVIMIENTOS!$E$5:$E$400)-SUMPRODUCT((MOVIMIENTOS!$B$5:$B$400="REGALO")*(MOVIMIENTOS!$C$5:$C$400="P")*(MOVIMIENTOS!$D$5:$D$400="jabas")*(MOVIMIENTOS!$A$5:$A$400<>"")*(MOVIMIENTOS!$A$5:$A$400<=$A15)*MOVIMIENTOS!$E$5:$E$400)-SUMPRODUCT((MOVIMIENTOS!$B$5:$B$400="VENTA")*(MOVIMIENTOS!$C$5:$C$400="P")*(MOVIMIENTOS!$D$5:$D$400="jabas")*(MOVIMIENTOS!$A$5:$A$400<>"")*(MOVIMIENTOS!$A$5:$A$400<=$A15)*MOVIMIENTOS!$E$5:$E$400)+SUMPRODUCT((MOVIMIENTOS!$B$5:$B$400="AJUSTE")*(MOVIMIENTOS!$C$5:$C$400="P")*(MOVIMIENTOS!$D$5:$D$400="jabas")*(MOVIMIENTOS!$A$5:$A$400<>"")*(MOVIMIENTOS!$A$5:$A$400<=$A15)*MOVIMIENTOS!$E$5:$E$400)) -> 11 | D15: =IF($A15="","",SUMPRODUCT((MOVIMIENTOS!$B$5:$B$400="SALDO INICIAL")*(MOVIMIENTOS!$C$5:$C$400="C")*(MOVIMIENTOS!$D$5:$D$400="jabas")*(MOVIMIENTOS!$A$5:$A$400<>"")*(MOVIMIENTOS!$A$5:$A$400<=$A15)*MOVIMIENTOS!$E$5:$E$400)+SUMPRODUCT((MOVIMIENTOS!$B$5:$B$400="PROCESO")*(MOVIMIENTOS!$C$5:$C$400="C")*(MOVIMIENTOS!$D$5:$D$400="jabas")*(MOVIMIENTOS!$A$5:$A$400<>"")*(MOVIMIENTOS!$A$5:$A$400<=$A15)*MOVIMIENTOS!$E$5:$E$400)-SUMPRODUCT((MOVIMIENTOS!$B$5:$B$400="ENVÍO A SUPESA")*(MOVIMIENTOS!$C$5:$C$400="C")*(MOVIMIENTOS!$D$5:$D$400="jabas")*(MOVIMIENTOS!$A$5:$A$400<>"")*(MOVIMIENTOS!$A$5:$A$400<=$A15)*MOVIMIENTOS!$E$5:$E$400)+SUMPRODUCT((MOVIMIENTOS!$B$5:$B$400="DEVOLUCIÓN")*(MOVIMIENTOS!$C$5:$C$400="C")*(MOVIMIENTOS!$D$5:$D$400="jabas")*(MOVIMIENTOS!$A$5:$A$400<>"")*(MOVIMIENTOS!$A$5:$A$400<=$A15)*MOVIMIENTOS!$E$5:$E$400)-SUMPRODUCT((MOVIMIENTOS!$B$5:$B$400="TRASIEGO")*(MOVIMIENTOS!$C$5:$C$400="C")*(MOVIMIENTOS!$D$5:$D$400="jabas")*(MOVIMIENTOS!$A$5:$A$400<>"")*(MOVIMIENTOS!$A$5:$A$400<=$A15)*MOVIMIENTOS!$E$5:$E$400)-SUMPRODUCT((MOVIMIENTOS!$B$5:$B$400="REGALO")*(MOVIMIENTOS!$C$5:$C$400="C")*(MOVIMIENTOS!$D$5:$D$400="jabas")*(MOVIMIENTOS!$A$5:$A$400<>"")*(MOVIMIENTOS!$A$5:$A$400<=$A15)*MOVIMIENTOS!$E$5:$E$400)-SUMPRODUCT((MOVIMIENTOS!$B$5:$B$400="VENTA")*(MOVIMIENTOS!$C$5:$C$400="C")*(MOVIMIENTOS!$D$5:$D$400="jabas")*(MOVIMIENTOS!$A$5:$A$400<>"")*(MOVIMIENTOS!$A$5:$A$400<=$A15)*MOVIMIENTOS!$E$5:$E$400)+SUMPRODUCT((MOVIMIENTOS!$B$5:$B$400="AJUSTE")*(MOVIMIENTOS!$C$5:$C$400="C")*(MOVIMIENTOS!$D$5:$D$400="jabas")*(MOVIMIENTOS!$A$5:$A$400<>"")*(MOVIMIENTOS!$A$5:$A$400<=$A15)*MOVIMIENTOS!$E$5:$E$400)) -> 12 | E15: =IF($A15="","",SUMPRODUCT((MOVIMIENTOS!$B$5:$B$400="SALDO INICIAL")*(MOVIMIENTOS!$C$5:$C$400="M")*(MOVIMIENTOS!$D$5:$D$400="jabas")*(MOVIMIENTOS!$A$5:$A$400<>"")*(MOVIMIENTOS!$A$5:$A$400<=$A15)*MOVIMIENTOS!$E$5:$E$400)+SUMPRODUCT((MOVIMIENTOS!$B$5:$B$400="PROCESO")*(MOVIMIENTOS!$C$5:$C$400="M")*(MOVIMIENTOS!$D$5:$D$400="jabas")*(MOVIMIENTOS!$A$5:$A$400<>"")*(MOVIMIENTOS!$A$5:$A$400<=$A15)*MOVIMIENTOS!$E$5:$E$400)-SUMPRODUCT((MOVIMIENTOS!$B$5:$B$400="ENVÍO A SUPESA")*(MOVIMIENTOS!$C$5:$C$400="M")*(MOVIMIENTOS!$D$5:$D$400="jabas")*(MOVIMIENTOS!$A$5:$A$400<>"")*(MOVIMIENTOS!$A$5:$A$400<=$A15)*MOVIMIENTOS!$E$5:$E$400)+SUMPRODUCT((MOVIMIENTOS!$B$5:$B$400="DEVOLUCIÓN")*(MOVIMIENTOS!$C$5:$C$400="M")*(MOVIMIENTOS!$D$5:$D$400="jabas")*(MOVIMIENTOS!$A$5:$A$400<>"")*(MOVIMIENTOS!$A$5:$A$400<=$A15)*MOVIMIENTOS!$E$5:$E$400)-SUMPRODUCT((MOVIMIENTOS!$B$5:$B$400="TRASIEGO")*(MOVIMIENTOS!$C$5:$C$400="M")*(MOVIMIENTOS!$D$5:$D$400="jabas")*(MOVIMIENTOS!$A$5:$A$400<>"")*(MOVIMIENTOS!$A$5:$A$400<=$A15)*MOVIMIENTOS!$E$5:$E$400)-SUMPRODUCT((MOVIMIENTOS!$B$5:$B$400="REGALO")*(MOVIMIENTOS!$C$5:$C$400="M")*(MOVIMIENTOS!$D$5:$D$400="jabas")*(MOVIMIENTOS!$A$5:$A$400<>"")*(MOVIMIENTOS!$A$5:$A$400<=$A15)*MOVIMIENTOS!$E$5:$E$400)-SUMPRODUCT((MOVIMIENTOS!$B$5:$B$400="VENTA")*(MOVIMIENTOS!$C$5:$C$400="M")*(MOVIMIENTOS!$D$5:$D$400="jabas")*(MOVIMIENTOS!$A$5:$A$400<>"")*(MOVIMIENTOS!$A$5:$A$400<=$A15)*MOVIMIENTOS!$E$5:$E$400)+SUMPRODUCT((MOVIMIENTOS!$B$5:$B$400="AJUSTE")*(MOVIMIENTOS!$C$5:$C$400="M")*(MOVIMIENTOS!$D$5:$D$400="jabas")*(MOVIMIENTOS!$A$5:$A$400<>"")*(MOVIMIENTOS!$A$5:$A$400<=$A15)*MOVIMIENTOS!$E$5:$E$400)) -> 111 | F15: =IF($A15="","",SUMPRODUCT((MOVIMIENTOS!$B$5:$B$400="SALDO INICIAL")*(MOVIMIENTOS!$C$5:$C$400="Chancho")*(MOVIMIENTOS!$D$5:$D$400="sacos")*(MOVIMIENTOS!$A$5:$A$400<>"")*(MOVIMIENTOS!$A$5:$A$400<=$A15)*MOVIMIENTOS!$E$5:$E$400)+SUMPRODUCT((MOVIMIENTOS!$B$5:$B$400="PROCESO")*(MOVIMIENTOS!$C$5:$C$400="Chancho")*(MOVIMIENTOS!$D$5:$D$400="sacos")*(MOVIMIENTOS!$A$5:$A$400<>"")*(MOVIMIENTOS!$A$5:$A$400<=$A15)*MOVIMIENTOS!$E$5:$E$400)-SUMPRODUCT((MOVIMIENTOS!$B$5:$B$400="VENTA CHANCHO")*(MOVIMIENTOS!$C$5:$C$400="Chancho")*(MOVIMIENTOS!$D$5:$D$400="sacos")*(MOVIMIENTOS!$A$5:$A$400<>"")*(MOVIMIENTOS!$A$5:$A$400<=$A15)*MOVIMIENTOS!$E$5:$E$400)-SUMPRODUCT((MOVIMIENTOS!$B$5:$B$400="REGALO")*(MOVIMIENTOS!$C$5:$C$400="Chancho")*(MOVIMIENTOS!$D$5:$D$400="sacos")*(MOVIMIENTOS!$A$5:$A$400<>"")*(MOVIMIENTOS!$A$5:$A$400<=$A15)*MOVIMIENTOS!$E$5:$E$400)-SUMPRODUCT((MOVIMIENTOS!$B$5:$B$400="VENTA")*(MOVIMIENTOS!$C$5:$C$400="Chancho")*(MOVIMIENTOS!$D$5:$D$400="sacos")*(MOVIMIENTOS!$A$5:$A$400<>"")*(MOVIMIENTOS!$A$5:$A$400<=$A15)*MOVIMIENTOS!$E$5:$E$400)+SUMPRODUCT((MOVIMIENTOS!$B$5:$B$400="AJUSTE")*(MOVIMIENTOS!$C$5:$C$400="Chancho")*(MOVIMIENTOS!$D$5:$D$400="sacos")*(MOVIMIENTOS!$A$5:$A$400<>"")*(MOVIMIENTOS!$A$5:$A$400<=$A15)*MOVIMIENTOS!$E$5:$E$400)) -> 13.5 | G15: =IF($A15="","",SUM(B15:E15)) -> 194 | H15: =IF($A15="","",SUMPRODUCT((((MOVIMIENTOS!$B$5:$B$400="SALDO INICIAL")*(MOVIMIENTOS!$C$5:$C$400<>"Chancho"))+(MOVIMIENTOS!$B$5:$B$400="COMPRA")+(MOVIMIENTOS!$B$5:$B$400="REPROCESO")+(MOVIMIENTOS!$B$5:$B$400="DEVOLUCIÓN")+((MOVIMIENTOS!$B$5:$B$400="AJUSTE")*(MOVIMIENTOS!$C$5:$C$400<>"Chancho")))*(MOVIMIENTOS!$A$5:$A$400<>"")*(MOVIMIENTOS!$A$5:$A$400<=$A15)*MOVIMIENTOS!$I$5:$I$400)-SUMPRODUCT(((MOVIMIENTOS!$B$5:$B$400="ENVÍO A SUPESA")+(MOVIMIENTOS!$B$5:$B$400="ENVÍO A TOTTUS")+(MOVIMIENTOS!$B$5:$B$400="ENVIO A TOTTUS")+(MOVIMIENTOS!$B$5:$B$400="MALOGRADO")+(MOVIMIENTOS!$B$5:$B$400="OTRA SALIDA")+((MOVIMIENTOS!$B$5:$B$400="PROCESO")*(MOVIMIENTOS!$C$5:$C$400="Chancho"))+((MOVIMIENTOS!$B$5:$B$400="REGALO")*(MOVIMIENTOS!$C$5:$C$400<>"Chancho"))+((MOVIMIENTOS!$B$5:$B$400="VENTA")*(MOVIMIENTOS!$C$5:$C$400<>"Chancho")))*(MOVIMIENTOS!$A$5:$A$400<>"")*(MOVIMIENTOS!$A$5:$A$400<=$A15)*MOVIMIENTOS!$I$5:$I$400)) -> 7535.5 | J15: =IF(AND(MOVIMIENTOS!$A15<>"",COUNTIF(MOVIMIENTOS!$A$5:$A14,MOVIMIENTOS!$A15)=0),COUNT(J$4:J14)+1,"") | K15: =MOVIMIENTOS!$A15 -> 46215
A16: =IFERROR(INDEX(K$5:K$400,MATCH(ROW()-4,J$5:J$400,0)),"") -> 46225 | B16: =IF($A16="","",SUMPRODUCT((MOVIMIENTOS!$B$5:$B$400="SALDO INICIAL")*(MOVIMIENTOS!$C$5:$C$400="A")*(MOVIMIENTOS!$D$5:$D$400="jabas")*(MOVIMIENTOS!$A$5:$A$400<>"")*(MOVIMIENTOS!$A$5:$A$400<=$A16)*MOVIMIENTOS!$E$5:$E$400)+SUMPRODUCT((MOVIMIENTOS!$B$5:$B$400="PROCESO")*(MOVIMIENTOS!$C$5:$C$400="A")*(MOVIMIENTOS!$D$5:$D$400="jabas")*(MOVIMIENTOS!$A$5:$A$400<>"")*(MOVIMIENTOS!$A$5:$A$400<=$A16)*MOVIMIENTOS!$E$5:$E$400)-SUMPRODUCT((MOVIMIENTOS!$B$5:$B$400="ENVÍO A SUPESA")*(MOVIMIENTOS!$C$5:$C$400="A")*(MOVIMIENTOS!$D$5:$D$400="jabas")*(MOVIMIENTOS!$A$5:$A$400<>"")*(MOVIMIENTOS!$A$5:$A$400<=$A16)*MOVIMIENTOS!$E$5:$E$400)+SUMPRODUCT((MOVIMIENTOS!$B$5:$B$400="DEVOLUCIÓN")*(MOVIMIENTOS!$C$5:$C$400="A")*(MOVIMIENTOS!$D$5:$D$400="jabas")*(MOVIMIENTOS!$A$5:$A$400<>"")*(MOVIMIENTOS!$A$5:$A$400<=$A16)*MOVIMIENTOS!$E$5:$E$400)-SUMPRODUCT((MOVIMIENTOS!$B$5:$B$400="TRASIEGO")*(MOVIMIENTOS!$C$5:$C$400="A")*(MOVIMIENTOS!$D$5:$D$400="jabas")*(MOVIMIENTOS!$A$5:$A$400<>"")*(MOVIMIENTOS!$A$5:$A$400<=$A16)*MOVIMIENTOS!$E$5:$E$400)-SUMPRODUCT((MOVIMIENTOS!$B$5:$B$400="REGALO")*(MOVIMIENTOS!$C$5:$C$400="A")*(MOVIMIENTOS!$D$5:$D$400="jabas")*(MOVIMIENTOS!$A$5:$A$400<>"")*(MOVIMIENTOS!$A$5:$A$400<=$A16)*MOVIMIENTOS!$E$5:$E$400)-SUMPRODUCT((MOVIMIENTOS!$B$5:$B$400="VENTA")*(MOVIMIENTOS!$C$5:$C$400="A")*(MOVIMIENTOS!$D$5:$D$400="jabas")*(MOVIMIENTOS!$A$5:$A$400<>"")*(MOVIMIENTOS!$A$5:$A$400<=$A16)*MOVIMIENTOS!$E$5:$E$400)+SUMPRODUCT((MOVIMIENTOS!$B$5:$B$400="AJUSTE")*(MOVIMIENTOS!$C$5:$C$400="A")*(MOVIMIENTOS!$D$5:$D$400="jabas")*(MOVIMIENTOS!$A$5:$A$400<>"")*(MOVIMIENTOS!$A$5:$A$400<=$A16)*MOVIMIENTOS!$E$5:$E$400)) -> 56 | C16: =IF($A16="","",SUMPRODUCT((MOVIMIENTOS!$B$5:$B$400="SALDO INICIAL")*(MOVIMIENTOS!$C$5:$C$400="P")*(MOVIMIENTOS!$D$5:$D$400="jabas")*(MOVIMIENTOS!$A$5:$A$400<>"")*(MOVIMIENTOS!$A$5:$A$400<=$A16)*MOVIMIENTOS!$E$5:$E$400)+SUMPRODUCT((MOVIMIENTOS!$B$5:$B$400="PROCESO")*(MOVIMIENTOS!$C$5:$C$400="P")*(MOVIMIENTOS!$D$5:$D$400="jabas")*(MOVIMIENTOS!$A$5:$A$400<>"")*(MOVIMIENTOS!$A$5:$A$400<=$A16)*MOVIMIENTOS!$E$5:$E$400)-SUMPRODUCT((MOVIMIENTOS!$B$5:$B$400="ENVÍO A SUPESA")*(MOVIMIENTOS!$C$5:$C$400="P")*(MOVIMIENTOS!$D$5:$D$400="jabas")*(MOVIMIENTOS!$A$5:$A$400<>"")*(MOVIMIENTOS!$A$5:$A$400<=$A16)*MOVIMIENTOS!$E$5:$E$400)+SUMPRODUCT((MOVIMIENTOS!$B$5:$B$400="DEVOLUCIÓN")*(MOVIMIENTOS!$C$5:$C$400="P")*(MOVIMIENTOS!$D$5:$D$400="jabas")*(MOVIMIENTOS!$A$5:$A$400<>"")*(MOVIMIENTOS!$A$5:$A$400<=$A16)*MOVIMIENTOS!$E$5:$E$400)-SUMPRODUCT((MOVIMIENTOS!$B$5:$B$400="TRASIEGO")*(MOVIMIENTOS!$C$5:$C$400="P")*(MOVIMIENTOS!$D$5:$D$400="jabas")*(MOVIMIENTOS!$A$5:$A$400<>"")*(MOVIMIENTOS!$A$5:$A$400<=$A16)*MOVIMIENTOS!$E$5:$E$400)-SUMPRODUCT((MOVIMIENTOS!$B$5:$B$400="REGALO")*(MOVIMIENTOS!$C$5:$C$400="P")*(MOVIMIENTOS!$D$5:$D$400="jabas")*(MOVIMIENTOS!$A$5:$A$400<>"")*(MOVIMIENTOS!$A$5:$A$400<=$A16)*MOVIMIENTOS!$E$5:$E$400)-SUMPRODUCT((MOVIMIENTOS!$B$5:$B$400="VENTA")*(MOVIMIENTOS!$C$5:$C$400="P")*(MOVIMIENTOS!$D$5:$D$400="jabas")*(MOVIMIENTOS!$A$5:$A$400<>"")*(MOVIMIENTOS!$A$5:$A$400<=$A16)*MOVIMIENTOS!$E$5:$E$400)+SUMPRODUCT((MOVIMIENTOS!$B$5:$B$400="AJUSTE")*(MOVIMIENTOS!$C$5:$C$400="P")*(MOVIMIENTOS!$D$5:$D$400="jabas")*(MOVIMIENTOS!$A$5:$A$400<>"")*(MOVIMIENTOS!$A$5:$A$400<=$A16)*MOVIMIENTOS!$E$5:$E$400)) -> 11 | D16: =IF($A16="","",SUMPRODUCT((MOVIMIENTOS!$B$5:$B$400="SALDO INICIAL")*(MOVIMIENTOS!$C$5:$C$400="C")*(MOVIMIENTOS!$D$5:$D$400="jabas")*(MOVIMIENTOS!$A$5:$A$400<>"")*(MOVIMIENTOS!$A$5:$A$400<=$A16)*MOVIMIENTOS!$E$5:$E$400)+SUMPRODUCT((MOVIMIENTOS!$B$5:$B$400="PROCESO")*(MOVIMIENTOS!$C$5:$C$400="C")*(MOVIMIENTOS!$D$5:$D$400="jabas")*(MOVIMIENTOS!$A$5:$A$400<>"")*(MOVIMIENTOS!$A$5:$A$400<=$A16)*MOVIMIENTOS!$E$5:$E$400)-SUMPRODUCT((MOVIMIENTOS!$B$5:$B$400="ENVÍO A SUPESA")*(MOVIMIENTOS!$C$5:$C$400="C")*(MOVIMIENTOS!$D$5:$D$400="jabas")*(MOVIMIENTOS!$A$5:$A$400<>"")*(MOVIMIENTOS!$A$5:$A$400<=$A16)*MOVIMIENTOS!$E$5:$E$400)+SUMPRODUCT((MOVIMIENTOS!$B$5:$B$400="DEVOLUCIÓN")*(MOVIMIENTOS!$C$5:$C$400="C")*(MOVIMIENTOS!$D$5:$D$400="jabas")*(MOVIMIENTOS!$A$5:$A$400<>"")*(MOVIMIENTOS!$A$5:$A$400<=$A16)*MOVIMIENTOS!$E$5:$E$400)-SUMPRODUCT((MOVIMIENTOS!$B$5:$B$400="TRASIEGO")*(MOVIMIENTOS!$C$5:$C$400="C")*(MOVIMIENTOS!$D$5:$D$400="jabas")*(MOVIMIENTOS!$A$5:$A$400<>"")*(MOVIMIENTOS!$A$5:$A$400<=$A16)*MOVIMIENTOS!$E$5:$E$400)-SUMPRODUCT((MOVIMIENTOS!$B$5:$B$400="REGALO")*(MOVIMIENTOS!$C$5:$C$400="C")*(MOVIMIENTOS!$D$5:$D$400="jabas")*(MOVIMIENTOS!$A$5:$A$400<>"")*(MOVIMIENTOS!$A$5:$A$400<=$A16)*MOVIMIENTOS!$E$5:$E$400)-SUMPRODUCT((MOVIMIENTOS!$B$5:$B$400="VENTA")*(MOVIMIENTOS!$C$5:$C$400="C")*(MOVIMIENTOS!$D$5:$D$400="jabas")*(MOVIMIENTOS!$A$5:$A$400<>"")*(MOVIMIENTOS!$A$5:$A$400<=$A16)*MOVIMIENTOS!$E$5:$E$400)+SUMPRODUCT((MOVIMIENTOS!$B$5:$B$400="AJUSTE")*(MOVIMIENTOS!$C$5:$C$400="C")*(MOVIMIENTOS!$D$5:$D$400="jabas")*(MOVIMIENTOS!$A$5:$A$400<>"")*(MOVIMIENTOS!$A$5:$A$400<=$A16)*MOVIMIENTOS!$E$5:$E$400)) -> 12 | E16: =IF($A16="","",SUMPRODUCT((MOVIMIENTOS!$B$5:$B$400="SALDO INICIAL")*(MOVIMIENTOS!$C$5:$C$400="M")*(MOVIMIENTOS!$D$5:$D$400="jabas")*(MOVIMIENTOS!$A$5:$A$400<>"")*(MOVIMIENTOS!$A$5:$A$400<=$A16)*MOVIMIENTOS!$E$5:$E$400)+SUMPRODUCT((MOVIMIENTOS!$B$5:$B$400="PROCESO")*(MOVIMIENTOS!$C$5:$C$400="M")*(MOVIMIENTOS!$D$5:$D$400="jabas")*(MOVIMIENTOS!$A$5:$A$400<>"")*(MOVIMIENTOS!$A$5:$A$400<=$A16)*MOVIMIENTOS!$E$5:$E$400)-SUMPRODUCT((MOVIMIENTOS!$B$5:$B$400="ENVÍO A SUPESA")*(MOVIMIENTOS!$C$5:$C$400="M")*(MOVIMIENTOS!$D$5:$D$400="jabas")*(MOVIMIENTOS!$A$5:$A$400<>"")*(MOVIMIENTOS!$A$5:$A$400<=$A16)*MOVIMIENTOS!$E$5:$E$400)+SUMPRODUCT((MOVIMIENTOS!$B$5:$B$400="DEVOLUCIÓN")*(MOVIMIENTOS!$C$5:$C$400="M")*(MOVIMIENTOS!$D$5:$D$400="jabas")*(MOVIMIENTOS!$A$5:$A$400<>"")*(MOVIMIENTOS!$A$5:$A$400<=$A16)*MOVIMIENTOS!$E$5:$E$400)-SUMPRODUCT((MOVIMIENTOS!$B$5:$B$400="TRASIEGO")*(MOVIMIENTOS!$C$5:$C$400="M")*(MOVIMIENTOS!$D$5:$D$400="jabas")*(MOVIMIENTOS!$A$5:$A$400<>"")*(MOVIMIENTOS!$A$5:$A$400<=$A16)*MOVIMIENTOS!$E$5:$E$400)-SUMPRODUCT((MOVIMIENTOS!$B$5:$B$400="REGALO")*(MOVIMIENTOS!$C$5:$C$400="M")*(MOVIMIENTOS!$D$5:$D$400="jabas")*(MOVIMIENTOS!$A$5:$A$400<>"")*(MOVIMIENTOS!$A$5:$A$400<=$A16)*MOVIMIENTOS!$E$5:$E$400)-SUMPRODUCT((MOVIMIENTOS!$B$5:$B$400="VENTA")*(MOVIMIENTOS!$C$5:$C$400="M")*(MOVIMIENTOS!$D$5:$D$400="jabas")*(MOVIMIENTOS!$A$5:$A$400<>"")*(MOVIMIENTOS!$A$5:$A$400<=$A16)*MOVIMIENTOS!$E$5:$E$400)+SUMPRODUCT((MOVIMIENTOS!$B$5:$B$400="AJUSTE")*(MOVIMIENTOS!$C$5:$C$400="M")*(MOVIMIENTOS!$D$5:$D$400="jabas")*(MOVIMIENTOS!$A$5:$A$400<>"")*(MOVIMIENTOS!$A$5:$A$400<=$A16)*MOVIMIENTOS!$E$5:$E$400)) -> 120 | F16: =IF($A16="","",SUMPRODUCT((MOVIMIENTOS!$B$5:$B$400="SALDO INICIAL")*(MOVIMIENTOS!$C$5:$C$400="Chancho")*(MOVIMIENTOS!$D$5:$D$400="sacos")*(MOVIMIENTOS!$A$5:$A$400<>"")*(MOVIMIENTOS!$A$5:$A$400<=$A16)*MOVIMIENTOS!$E$5:$E$400)+SUMPRODUCT((MOVIMIENTOS!$B$5:$B$400="PROCESO")*(MOVIMIENTOS!$C$5:$C$400="Chancho")*(MOVIMIENTOS!$D$5:$D$400="sacos")*(MOVIMIENTOS!$A$5:$A$400<>"")*(MOVIMIENTOS!$A$5:$A$400<=$A16)*MOVIMIENTOS!$E$5:$E$400)-SUMPRODUCT((MOVIMIENTOS!$B$5:$B$400="VENTA CHANCHO")*(MOVIMIENTOS!$C$5:$C$400="Chancho")*(MOVIMIENTOS!$D$5:$D$400="sacos")*(MOVIMIENTOS!$A$5:$A$400<>"")*(MOVIMIENTOS!$A$5:$A$400<=$A16)*MOVIMIENTOS!$E$5:$E$400)-SUMPRODUCT((MOVIMIENTOS!$B$5:$B$400="REGALO")*(MOVIMIENTOS!$C$5:$C$400="Chancho")*(MOVIMIENTOS!$D$5:$D$400="sacos")*(MOVIMIENTOS!$A$5:$A$400<>"")*(MOVIMIENTOS!$A$5:$A$400<=$A16)*MOVIMIENTOS!$E$5:$E$400)-SUMPRODUCT((MOVIMIENTOS!$B$5:$B$400="VENTA")*(MOVIMIENTOS!$C$5:$C$400="Chancho")*(MOVIMIENTOS!$D$5:$D$400="sacos")*(MOVIMIENTOS!$A$5:$A$400<>"")*(MOVIMIENTOS!$A$5:$A$400<=$A16)*MOVIMIENTOS!$E$5:$E$400)+SUMPRODUCT((MOVIMIENTOS!$B$5:$B$400="AJUSTE")*(MOVIMIENTOS!$C$5:$C$400="Chancho")*(MOVIMIENTOS!$D$5:$D$400="sacos")*(MOVIMIENTOS!$A$5:$A$400<>"")*(MOVIMIENTOS!$A$5:$A$400<=$A16)*MOVIMIENTOS!$E$5:$E$400)) -> 11.5 | G16: =IF($A16="","",SUM(B16:E16)) -> 199 | H16: =IF($A16="","",SUMPRODUCT((((MOVIMIENTOS!$B$5:$B$400="SALDO INICIAL")*(MOVIMIENTOS!$C$5:$C$400<>"Chancho"))+(MOVIMIENTOS!$B$5:$B$400="COMPRA")+(MOVIMIENTOS!$B$5:$B$400="REPROCESO")+(MOVIMIENTOS!$B$5:$B$400="DEVOLUCIÓN")+((MOVIMIENTOS!$B$5:$B$400="AJUSTE")*(MOVIMIENTOS!$C$5:$C$400<>"Chancho")))*(MOVIMIENTOS!$A$5:$A$400<>"")*(MOVIMIENTOS!$A$5:$A$400<=$A16)*MOVIMIENTOS!$I$5:$I$400)-SUMPRODUCT(((MOVIMIENTOS!$B$5:$B$400="ENVÍO A SUPESA")+(MOVIMIENTOS!$B$5:$B$400="ENVÍO A TOTTUS")+(MOVIMIENTOS!$B$5:$B$400="ENVIO A TOTTUS")+(MOVIMIENTOS!$B$5:$B$400="MALOGRADO")+(MOVIMIENTOS!$B$5:$B$400="OTRA SALIDA")+((MOVIMIENTOS!$B$5:$B$400="PROCESO")*(MOVIMIENTOS!$C$5:$C$400="Chancho"))+((MOVIMIENTOS!$B$5:$B$400="REGALO")*(MOVIMIENTOS!$C$5:$C$400<>"Chancho"))+((MOVIMIENTOS!$B$5:$B$400="VENTA")*(MOVIMIENTOS!$C$5:$C$400<>"Chancho")))*(MOVIMIENTOS!$A$5:$A$400<>"")*(MOVIMIENTOS!$A$5:$A$400<=$A16)*MOVIMIENTOS!$I$5:$I$400)) -> 7457.5 | J16: =IF(AND(MOVIMIENTOS!$A16<>"",COUNTIF(MOVIMIENTOS!$A$5:$A15,MOVIMIENTOS!$A16)=0),COUNT(J$4:J15)+1,"") | K16: =MOVIMIENTOS!$A16 -> 46215
A17: =IFERROR(INDEX(K$5:K$400,MATCH(ROW()-4,J$5:J$400,0)),"") -> 46226 | B17: =IF($A17="","",SUMPRODUCT((MOVIMIENTOS!$B$5:$B$400="SALDO INICIAL")*(MOVIMIENTOS!$C$5:$C$400="A")*(MOVIMIENTOS!$D$5:$D$400="jabas")*(MOVIMIENTOS!$A$5:$A$400<>"")*(MOVIMIENTOS!$A$5:$A$400<=$A17)*MOVIMIENTOS!$E$5:$E$400)+SUMPRODUCT((MOVIMIENTOS!$B$5:$B$400="PROCESO")*(MOVIMIENTOS!$C$5:$C$400="A")*(MOVIMIENTOS!$D$5:$D$400="jabas")*(MOVIMIENTOS!$A$5:$A$400<>"")*(MOVIMIENTOS!$A$5:$A$400<=$A17)*MOVIMIENTOS!$E$5:$E$400)-SUMPRODUCT((MOVIMIENTOS!$B$5:$B$400="ENVÍO A SUPESA")*(MOVIMIENTOS!$C$5:$C$400="A")*(MOVIMIENTOS!$D$5:$D$400="jabas")*(MOVIMIENTOS!$A$5:$A$400<>"")*(MOVIMIENTOS!$A$5:$A$400<=$A17)*MOVIMIENTOS!$E$5:$E$400)+SUMPRODUCT((MOVIMIENTOS!$B$5:$B$400="DEVOLUCIÓN")*(MOVIMIENTOS!$C$5:$C$400="A")*(MOVIMIENTOS!$D$5:$D$400="jabas")*(MOVIMIENTOS!$A$5:$A$400<>"")*(MOVIMIENTOS!$A$5:$A$400<=$A17)*MOVIMIENTOS!$E$5:$E$400)-SUMPRODUCT((MOVIMIENTOS!$B$5:$B$400="TRASIEGO")*(MOVIMIENTOS!$C$5:$C$400="A")*(MOVIMIENTOS!$D$5:$D$400="jabas")*(MOVIMIENTOS!$A$5:$A$400<>"")*(MOVIMIENTOS!$A$5:$A$400<=$A17)*MOVIMIENTOS!$E$5:$E$400)-SUMPRODUCT((MOVIMIENTOS!$B$5:$B$400="REGALO")*(MOVIMIENTOS!$C$5:$C$400="A")*(MOVIMIENTOS!$D$5:$D$400="jabas")*(MOVIMIENTOS!$A$5:$A$400<>"")*(MOVIMIENTOS!$A$5:$A$400<=$A17)*MOVIMIENTOS!$E$5:$E$400)-SUMPRODUCT((MOVIMIENTOS!$B$5:$B$400="VENTA")*(MOVIMIENTOS!$C$5:$C$400="A")*(MOVIMIENTOS!$D$5:$D$400="jabas")*(MOVIMIENTOS!$A$5:$A$400<>"")*(MOVIMIENTOS!$A$5:$A$400<=$A17)*MOVIMIENTOS!$E$5:$E$400)+SUMPRODUCT((MOVIMIENTOS!$B$5:$B$400="AJUSTE")*(MOVIMIENTOS!$C$5:$C$400="A")*(MOVIMIENTOS!$D$5:$D$400="jabas")*(MOVIMIENTOS!$A$5:$A$400<>"")*(MOVIMIENTOS!$A$5:$A$400<=$A17)*MOVIMIENTOS!$E$5:$E$400)) -> 67 | C17: =IF($A17="","",SUMPRODUCT((MOVIMIENTOS!$B$5:$B$400="SALDO INICIAL")*(MOVIMIENTOS!$C$5:$C$400="P")*(MOVIMIENTOS!$D$5:$D$400="jabas")*(MOVIMIENTOS!$A$5:$A$400<>"")*(MOVIMIENTOS!$A$5:$A$400<=$A17)*MOVIMIENTOS!$E$5:$E$400)+SUMPRODUCT((MOVIMIENTOS!$B$5:$B$400="PROCESO")*(MOVIMIENTOS!$C$5:$C$400="P")*(MOVIMIENTOS!$D$5:$D$400="jabas")*(MOVIMIENTOS!$A$5:$A$400<>"")*(MOVIMIENTOS!$A$5:$A$400<=$A17)*MOVIMIENTOS!$E$5:$E$400)-SUMPRODUCT((MOVIMIENTOS!$B$5:$B$400="ENVÍO A SUPESA")*(MOVIMIENTOS!$C$5:$C$400="P")*(MOVIMIENTOS!$D$5:$D$400="jabas")*(MOVIMIENTOS!$A$5:$A$400<>"")*(MOVIMIENTOS!$A$5:$A$400<=$A17)*MOVIMIENTOS!$E$5:$E$400)+SUMPRODUCT((MOVIMIENTOS!$B$5:$B$400="DEVOLUCIÓN")*(MOVIMIENTOS!$C$5:$C$400="P")*(MOVIMIENTOS!$D$5:$D$400="jabas")*(MOVIMIENTOS!$A$5:$A$400<>"")*(MOVIMIENTOS!$A$5:$A$400<=$A17)*MOVIMIENTOS!$E$5:$E$400)-SUMPRODUCT((MOVIMIENTOS!$B$5:$B$400="TRASIEGO")*(MOVIMIENTOS!$C$5:$C$400="P")*(MOVIMIENTOS!$D$5:$D$400="jabas")*(MOVIMIENTOS!$A$5:$A$400<>"")*(MOVIMIENTOS!$A$5:$A$400<=$A17)*MOVIMIENTOS!$E$5:$E$400)-SUMPRODUCT((MOVIMIENTOS!$B$5:$B$400="REGALO")*(MOVIMIENTOS!$C$5:$C$400="P")*(MOVIMIENTOS!$D$5:$D$400="jabas")*(MOVIMIENTOS!$A$5:$A$400<>"")*(MOVIMIENTOS!$A$5:$A$400<=$A17)*MOVIMIENTOS!$E$5:$E$400)-SUMPRODUCT((MOVIMIENTOS!$B$5:$B$400="VENTA")*(MOVIMIENTOS!$C$5:$C$400="P")*(MOVIMIENTOS!$D$5:$D$400="jabas")*(MOVIMIENTOS!$A$5:$A$400<>"")*(MOVIMIENTOS!$A$5:$A$400<=$A17)*MOVIMIENTOS!$E$5:$E$400)+SUMPRODUCT((MOVIMIENTOS!$B$5:$B$400="AJUSTE")*(MOVIMIENTOS!$C$5:$C$400="P")*(MOVIMIENTOS!$D$5:$D$400="jabas")*(MOVIMIENTOS!$A$5:$A$400<>"")*(MOVIMIENTOS!$A$5:$A$400<=$A17)*MOVIMIENTOS!$E$5:$E$400)) -> 11 | D17: =IF($A17="","",SUMPRODUCT((MOVIMIENTOS!$B$5:$B$400="SALDO INICIAL")*(MOVIMIENTOS!$C$5:$C$400="C")*(MOVIMIENTOS!$D$5:$D$400="jabas")*(MOVIMIENTOS!$A$5:$A$400<>"")*(MOVIMIENTOS!$A$5:$A$400<=$A17)*MOVIMIENTOS!$E$5:$E$400)+SUMPRODUCT((MOVIMIENTOS!$B$5:$B$400="PROCESO")*(MOVIMIENTOS!$C$5:$C$400="C")*(MOVIMIENTOS!$D$5:$D$400="jabas")*(MOVIMIENTOS!$A$5:$A$400<>"")*(MOVIMIENTOS!$A$5:$A$400<=$A17)*MOVIMIENTOS!$E$5:$E$400)-SUMPRODUCT((MOVIMIENTOS!$B$5:$B$400="ENVÍO A SUPESA")*(MOVIMIENTOS!$C$5:$C$400="C")*(MOVIMIENTOS!$D$5:$D$400="jabas")*(MOVIMIENTOS!$A$5:$A$400<>"")*(MOVIMIENTOS!$A$5:$A$400<=$A17)*MOVIMIENTOS!$E$5:$E$400)+SUMPRODUCT((MOVIMIENTOS!$B$5:$B$400="DEVOLUCIÓN")*(MOVIMIENTOS!$C$5:$C$400="C")*(MOVIMIENTOS!$D$5:$D$400="jabas")*(MOVIMIENTOS!$A$5:$A$400<>"")*(MOVIMIENTOS!$A$5:$A$400<=$A17)*MOVIMIENTOS!$E$5:$E$400)-SUMPRODUCT((MOVIMIENTOS!$B$5:$B$400="TRASIEGO")*(MOVIMIENTOS!$C$5:$C$400="C")*(MOVIMIENTOS!$D$5:$D$400="jabas")*(MOVIMIENTOS!$A$5:$A$400<>"")*(MOVIMIENTOS!$A$5:$A$400<=$A17)*MOVIMIENTOS!$E$5:$E$400)-SUMPRODUCT((MOVIMIENTOS!$B$5:$B$400="REGALO")*(MOVIMIENTOS!$C$5:$C$400="C")*(MOVIMIENTOS!$D$5:$D$400="jabas")*(MOVIMIENTOS!$A$5:$A$400<>"")*(MOVIMIENTOS!$A$5:$A$400<=$A17)*MOVIMIENTOS!$E$5:$E$400)-SUMPRODUCT((MOVIMIENTOS!$B$5:$B$400="VENTA")*(MOVIMIENTOS!$C$5:$C$400="C")*(MOVIMIENTOS!$D$5:$D$400="jabas")*(MOVIMIENTOS!$A$5:$A$400<>"")*(MOVIMIENTOS!$A$5:$A$400<=$A17)*MOVIMIENTOS!$E$5:$E$400)+SUMPRODUCT((MOVIMIENTOS!$B$5:$B$400="AJUSTE")*(MOVIMIENTOS!$C$5:$C$400="C")*(MOVIMIENTOS!$D$5:$D$400="jabas")*(MOVIMIENTOS!$A$5:$A$400<>"")*(MOVIMIENTOS!$A$5:$A$400<=$A17)*MOVIMIENTOS!$E$5:$E$400)) -> 12 | E17: =IF($A17="","",SUMPRODUCT((MOVIMIENTOS!$B$5:$B$400="SALDO INICIAL")*(MOVIMIENTOS!$C$5:$C$400="M")*(MOVIMIENTOS!$D$5:$D$400="jabas")*(MOVIMIENTOS!$A$5:$A$400<>"")*(MOVIMIENTOS!$A$5:$A$400<=$A17)*MOVIMIENTOS!$E$5:$E$400)+SUMPRODUCT((MOVIMIENTOS!$B$5:$B$400="PROCESO")*(MOVIMIENTOS!$C$5:$C$400="M")*(MOVIMIENTOS!$D$5:$D$400="jabas")*(MOVIMIENTOS!$A$5:$A$400<>"")*(MOVIMIENTOS!$A$5:$A$400<=$A17)*MOVIMIENTOS!$E$5:$E$400)-SUMPRODUCT((MOVIMIENTOS!$B$5:$B$400="ENVÍO A SUPESA")*(MOVIMIENTOS!$C$5:$C$400="M")*(MOVIMIENTOS!$D$5:$D$400="jabas")*(MOVIMIENTOS!$A$5:$A$400<>"")*(MOVIMIENTOS!$A$5:$A$400<=$A17)*MOVIMIENTOS!$E$5:$E$400)+SUMPRODUCT((MOVIMIENTOS!$B$5:$B$400="DEVOLUCIÓN")*(MOVIMIENTOS!$C$5:$C$400="M")*(MOVIMIENTOS!$D$5:$D$400="jabas")*(MOVIMIENTOS!$A$5:$A$400<>"")*(MOVIMIENTOS!$A$5:$A$400<=$A17)*MOVIMIENTOS!$E$5:$E$400)-SUMPRODUCT((MOVIMIENTOS!$B$5:$B$400="TRASIEGO")*(MOVIMIENTOS!$C$5:$C$400="M")*(MOVIMIENTOS!$D$5:$D$400="jabas")*(MOVIMIENTOS!$A$5:$A$400<>"")*(MOVIMIENTOS!$A$5:$A$400<=$A17)*MOVIMIENTOS!$E$5:$E$400)-SUMPRODUCT((MOVIMIENTOS!$B$5:$B$400="REGALO")*(MOVIMIENTOS!$C$5:$C$400="M")*(MOVIMIENTOS!$D$5:$D$400="jabas")*(MOVIMIENTOS!$A$5:$A$400<>"")*(MOVIMIENTOS!$A$5:$A$400<=$A17)*MOVIMIENTOS!$E$5:$E$400)-SUMPRODUCT((MOVIMIENTOS!$B$5:$B$400="VENTA")*(MOVIMIENTOS!$C$5:$C$400="M")*(MOVIMIENTOS!$D$5:$D$400="jabas")*(MOVIMIENTOS!$A$5:$A$400<>"")*(MOVIMIENTOS!$A$5:$A$400<=$A17)*MOVIMIENTOS!$E$5:$E$400)+SUMPRODUCT((MOVIMIENTOS!$B$5:$B$400="AJUSTE")*(MOVIMIENTOS!$C$5:$C$400="M")*(MOVIMIENTOS!$D$5:$D$400="jabas")*(MOVIMIENTOS!$A$5:$A$400<>"")*(MOVIMIENTOS!$A$5:$A$400<=$A17)*MOVIMIENTOS!$E$5:$E$400)) -> 96 | F17: =IF($A17="","",SUMPRODUCT((MOVIMIENTOS!$B$5:$B$400="SALDO INICIAL")*(MOVIMIENTOS!$C$5:$C$400="Chancho")*(MOVIMIENTOS!$D$5:$D$400="sacos")*(MOVIMIENTOS!$A$5:$A$400<>"")*(MOVIMIENTOS!$A$5:$A$400<=$A17)*MOVIMIENTOS!$E$5:$E$400)+SUMPRODUCT((MOVIMIENTOS!$B$5:$B$400="PROCESO")*(MOVIMIENTOS!$C$5:$C$400="Chancho")*(MOVIMIENTOS!$D$5:$D$400="sacos")*(MOVIMIENTOS!$A$5:$A$400<>"")*(MOVIMIENTOS!$A$5:$A$400<=$A17)*MOVIMIENTOS!$E$5:$E$400)-SUMPRODUCT((MOVIMIENTOS!$B$5:$B$400="VENTA CHANCHO")*(MOVIMIENTOS!$C$5:$C$400="Chancho")*(MOVIMIENTOS!$D$5:$D$400="sacos")*(MOVIMIENTOS!$A$5:$A$400<>"")*(MOVIMIENTOS!$A$5:$A$400<=$A17)*MOVIMIENTOS!$E$5:$E$400)-SUMPRODUCT((MOVIMIENTOS!$B$5:$B$400="REGALO")*(MOVIMIENTOS!$C$5:$C$400="Chancho")*(MOVIMIENTOS!$D$5:$D$400="sacos")*(MOVIMIENTOS!$A$5:$A$400<>"")*(MOVIMIENTOS!$A$5:$A$400<=$A17)*MOVIMIENTOS!$E$5:$E$400)-SUMPRODUCT((MOVIMIENTOS!$B$5:$B$400="VENTA")*(MOVIMIENTOS!$C$5:$C$400="Chancho")*(MOVIMIENTOS!$D$5:$D$400="sacos")*(MOVIMIENTOS!$A$5:$A$400<>"")*(MOVIMIENTOS!$A$5:$A$400<=$A17)*MOVIMIENTOS!$E$5:$E$400)+SUMPRODUCT((MOVIMIENTOS!$B$5:$B$400="AJUSTE")*(MOVIMIENTOS!$C$5:$C$400="Chancho")*(MOVIMIENTOS!$D$5:$D$400="sacos")*(MOVIMIENTOS!$A$5:$A$400<>"")*(MOVIMIENTOS!$A$5:$A$400<=$A17)*MOVIMIENTOS!$E$5:$E$400)) -> 18 | G17: =IF($A17="","",SUM(B17:E17)) -> 186 | H17: =IF($A17="","",SUMPRODUCT((((MOVIMIENTOS!$B$5:$B$400="SALDO INICIAL")*(MOVIMIENTOS!$C$5:$C$400<>"Chancho"))+(MOVIMIENTOS!$B$5:$B$400="COMPRA")+(MOVIMIENTOS!$B$5:$B$400="REPROCESO")+(MOVIMIENTOS!$B$5:$B$400="DEVOLUCIÓN")+((MOVIMIENTOS!$B$5:$B$400="AJUSTE")*(MOVIMIENTOS!$C$5:$C$400<>"Chancho")))*(MOVIMIENTOS!$A$5:$A$400<>"")*(MOVIMIENTOS!$A$5:$A$400<=$A17)*MOVIMIENTOS!$I$5:$I$400)-SUMPRODUCT(((MOVIMIENTOS!$B$5:$B$400="ENVÍO A SUPESA")+(MOVIMIENTOS!$B$5:$B$400="ENVÍO A TOTTUS")+(MOVIMIENTOS!$B$5:$B$400="ENVIO A TOTTUS")+(MOVIMIENTOS!$B$5:$B$400="MALOGRADO")+(MOVIMIENTOS!$B$5:$B$400="OTRA SALIDA")+((MOVIMIENTOS!$B$5:$B$400="PROCESO")*(MOVIMIENTOS!$C$5:$C$400="Chancho"))+((MOVIMIENTOS!$B$5:$B$400="REGALO")*(MOVIMIENTOS!$C$5:$C$400<>"Chancho"))+((MOVIMIENTOS!$B$5:$B$400="VENTA")*(MOVIMIENTOS!$C$5:$C$400<>"Chancho")))*(MOVIMIENTOS!$A$5:$A$400<>"")*(MOVIMIENTOS!$A$5:$A$400<=$A17)*MOVIMIENTOS!$I$5:$I$400)) -> 11174 | J17: =IF(AND(MOVIMIENTOS!$A17<>"",COUNTIF(MOVIMIENTOS!$A$5:$A16,MOVIMIENTOS!$A17)=0),COUNT(J$4:J16)+1,"") | K17: =MOVIMIENTOS!$A17 -> 46215
... A69: =IFERROR(INDEX(K$5:K$400,MATCH(ROW()-4,J$5:J$400,0)),"") | B69: =IF($A69="","",SUMPRODUCT((MOVIMIENTOS!$B$5:$B$400="SALDO INICIAL")*(MOVIMIENTOS!$C$5:$C$400="A")*(MOVIMIENTOS!$D$5:$D$400="jabas")*(MOVIMIENTOS!$A$5:$A$400<>"")*(MOVIMIENTOS!$A$5:$A$400<=$A69)*MOVIMIENTOS!$E$5:$E$400)+SUMPRODUCT((MOVIMIENTOS!$B$5:$B$400="PROCESO")*(MOVIMIENTOS!$C$5:$C$400="A")*(MOVIMIENTOS!$D$5:$D$400="jabas")*(MOVIMIENTOS!$A$5:$A$400<>"")*(MOVIMIENTOS!$A$5:$A$400<=$A69)*MOVIMIENTOS!$E$5:$E$400)-SUMPRODUCT((MOVIMIENTOS!$B$5:$B$400="ENVÍO A SUPESA")*(MOVIMIENTOS!$C$5:$C$400="A")*(MOVIMIENTOS!$D$5:$D$400="jabas")*(MOVIMIENTOS!$A$5:$A$400<>"")*(MOVIMIENTOS!$A$5:$A$400<=$A69)*MOVIMIENTOS!$E$5:$E$400)+SUMPRODUCT((MOVIMIENTOS!$B$5:$B$400="DEVOLUCIÓN")*(MOVIMIENTOS!$C$5:$C$400="A")*(MOVIMIENTOS!$D$5:$D$400="jabas")*(MOVIMIENTOS!$A$5:$A$400<>"")*(MOVIMIENTOS!$A$5:$A$400<=$A69)*MOVIMIENTOS!$E$5:$E$400)-SUMPRODUCT((MOVIMIENTOS!$B$5:$B$400="TRASIEGO")*(MOVIMIENTOS!$C$5:$C$400="A")*(MOVIMIENTOS!$D$5:$D$400="jabas")*(MOVIMIENTOS!$A$5:$A$400<>"")*(MOVIMIENTOS!$A$5:$A$400<=$A69)*MOVIMIENTOS!$E$5:$E$400)-SUMPRODUCT((MOVIMIENTOS!$B$5:$B$400="REGALO")*(MOVIMIENTOS!$C$5:$C$400="A")*(MOVIMIENTOS!$D$5:$D$400="jabas")*(MOVIMIENTOS!$A$5:$A$400<>"")*(MOVIMIENTOS!$A$5:$A$400<=$A69)*MOVIMIENTOS!$E$5:$E$400)-SUMPRODUCT((MOVIMIENTOS!$B$5:$B$400="VENTA")*(MOVIMIENTOS!$C$5:$C$400="A")*(MOVIMIENTOS!$D$5:$D$400="jabas")*(MOVIMIENTOS!$A$5:$A$400<>"")*(MOVIMIENTOS!$A$5:$A$400<=$A69)*MOVIMIENTOS!$E$5:$E$400)+SUMPRODUCT((MOVIMIENTOS!$B$5:$B$400="AJUSTE")*(MOVIMIENTOS!$C$5:$C$400="A")*(MOVIMIENTOS!$D$5:$D$400="jabas")*(MOVIMIENTOS!$A$5:$A$400<>"")*(MOVIMIENTOS!$A$5:$A$400<=$A69)*MOVIMIENTOS!$E$5:$E$400)) | C69: =IF($A69="","",SUMPRODUCT((MOVIMIENTOS!$B$5:$B$400="SALDO INICIAL")*(MOVIMIENTOS!$C$5:$C$400="P")*(MOVIMIENTOS!$D$5:$D$400="jabas")*(MOVIMIENTOS!$A$5:$A$400<>"")*(MOVIMIENTOS!$A$5:$A$400<=$A69)*MOVIMIENTOS!$E$5:$E$400)+SUMPRODUCT((MOVIMIENTOS!$B$5:$B$400="PROCESO")*(MOVIMIENTOS!$C$5:$C$400="P")*(MOVIMIENTOS!$D$5:$D$400="jabas")*(MOVIMIENTOS!$A$5:$A$400<>"")*(MOVIMIENTOS!$A$5:$A$400<=$A69)*MOVIMIENTOS!$E$5:$E$400)-SUMPRODUCT((MOVIMIENTOS!$B$5:$B$400="ENVÍO A SUPESA")*(MOVIMIENTOS!$C$5:$C$400="P")*(MOVIMIENTOS!$D$5:$D$400="jabas")*(MOVIMIENTOS!$A$5:$A$400<>"")*(MOVIMIENTOS!$A$5:$A$400<=$A69)*MOVIMIENTOS!$E$5:$E$400)+SUMPRODUCT((MOVIMIENTOS!$B$5:$B$400="DEVOLUCIÓN")*(MOVIMIENTOS!$C$5:$C$400="P")*(MOVIMIENTOS!$D$5:$D$400="jabas")*(MOVIMIENTOS!$A$5:$A$400<>"")*(MOVIMIENTOS!$A$5:$A$400<=$A69)*MOVIMIENTOS!$E$5:$E$400)-SUMPRODUCT((MOVIMIENTOS!$B$5:$B$400="TRASIEGO")*(MOVIMIENTOS!$C$5:$C$400="P")*(MOVIMIENTOS!$D$5:$D$400="jabas")*(MOVIMIENTOS!$A$5:$A$400<>"")*(MOVIMIENTOS!$A$5:$A$400<=$A69)*MOVIMIENTOS!$E$5:$E$400)-SUMPRODUCT((MOVIMIENTOS!$B$5:$B$400="REGALO")*(MOVIMIENTOS!$C$5:$C$400="P")*(MOVIMIENTOS!$D$5:$D$400="jabas")*(MOVIMIENTOS!$A$5:$A$400<>"")*(MOVIMIENTOS!$A$5:$A$400<=$A69)*MOVIMIENTOS!$E$5:$E$400)-SUMPRODUCT((MOVIMIENTOS!$B$5:$B$400="VENTA")*(MOVIMIENTOS!$C$5:$C$400="P")*(MOVIMIENTOS!$D$5:$D$400="jabas")*(MOVIMIENTOS!$A$5:$A$400<>"")*(MOVIMIENTOS!$A$5:$A$400<=$A69)*MOVIMIENTOS!$E$5:$E$400)+SUMPRODUCT((MOVIMIENTOS!$B$5:$B$400="AJUSTE")*(MOVIMIENTOS!$C$5:$C$400="P")*(MOVIMIENTOS!$D$5:$D$400="jabas")*(MOVIMIENTOS!$A$5:$A$400<>"")*(MOVIMIENTOS!$A$5:$A$400<=$A69)*MOVIMIENTOS!$E$5:$E$400)) | D69: =IF($A69="","",SUMPRODUCT((MOVIMIENTOS!$B$5:$B$400="SALDO INICIAL")*(MOVIMIENTOS!$C$5:$C$400="C")*(MOVIMIENTOS!$D$5:$D$400="jabas")*(MOVIMIENTOS!$A$5:$A$400<>"")*(MOVIMIENTOS!$A$5:$A$400<=$A69)*MOVIMIENTOS!$E$5:$E$400)+SUMPRODUCT((MOVIMIENTOS!$B$5:$B$400="PROCESO")*(MOVIMIENTOS!$C$5:$C$400="C")*(MOVIMIENTOS!$D$5:$D$400="jabas")*(MOVIMIENTOS!$A$5:$A$400<>"")*(MOVIMIENTOS!$A$5:$A$400<=$A69)*MOVIMIENTOS!$E$5:$E$400)-SUMPRODUCT((MOVIMIENTOS!$B$5:$B$400="ENVÍO A SUPESA")*(MOVIMIENTOS!$C$5:$C$400="C")*(MOVIMIENTOS!$D$5:$D$400="jabas")*(MOVIMIENTOS!$A$5:$A$400<>"")*(MOVIMIENTOS!$A$5:$A$400<=$A69)*MOVIMIENTOS!$E$5:$E$400)+SUMPRODUCT((MOVIMIENTOS!$B$5:$B$400="DEVOLUCIÓN")*(MOVIMIENTOS!$C$5:$C$400="C")*(MOVIMIENTOS!$D$5:$D$400="jabas")*(MOVIMIENTOS!$A$5:$A$400<>"")*(MOVIMIENTOS!$A$5:$A$400<=$A69)*MOVIMIENTOS!$E$5:$E$400)-SUMPRODUCT((MOVIMIENTOS!$B$5:$B$400="TRASIEGO")*(MOVIMIENTOS!$C$5:$C$400="C")*(MOVIMIENTOS!$D$5:$D$400="jabas")*(MOVIMIENTOS!$A$5:$A$400<>"")*(MOVIMIENTOS!$A$5:$A$400<=$A69)*MOVIMIENTOS!$E$5:$E$400)-SUMPRODUCT((MOVIMIENTOS!$B$5:$B$400="REGALO")*(MOVIMIENTOS!$C$5:$C$400="C")*(MOVIMIENTOS!$D$5:$D$400="jabas")*(MOVIMIENTOS!$A$5:$A$400<>"")*(MOVIMIENTOS!$A$5:$A$400<=$A69)*MOVIMIENTOS!$E$5:$E$400)-SUMPRODUCT((MOVIMIENTOS!$B$5:$B$400="VENTA")*(MOVIMIENTOS!$C$5:$C$400="C")*(MOVIMIENTOS!$D$5:$D$400="jabas")*(MOVIMIENTOS!$A$5:$A$400<>"")*(MOVIMIENTOS!$A$5:$A$400<=$A69)*MOVIMIENTOS!$E$5:$E$400)+SUMPRODUCT((MOVIMIENTOS!$B$5:$B$400="AJUSTE")*(MOVIMIENTOS!$C$5:$C$400="C")*(MOVIMIENTOS!$D$5:$D$400="jabas")*(MOVIMIENTOS!$A$5:$A$400<>"")*(MOVIMIENTOS!$A$5:$A$400<=$A69)*MOVIMIENTOS!$E$5:$E$400)) | E69: =IF($A69="","",SUMPRODUCT((MOVIMIENTOS!$B$5:$B$400="SALDO INICIAL")*(MOVIMIENTOS!$C$5:$C$400="M")*(MOVIMIENTOS!$D$5:$D$400="jabas")*(MOVIMIENTOS!$A$5:$A$400<>"")*(MOVIMIENTOS!$A$5:$A$400<=$A69)*MOVIMIENTOS!$E$5:$E$400)+SUMPRODUCT((MOVIMIENTOS!$B$5:$B$400="PROCESO")*(MOVIMIENTOS!$C$5:$C$400="M")*(MOVIMIENTOS!$D$5:$D$400="jabas")*(MOVIMIENTOS!$A$5:$A$400<>"")*(MOVIMIENTOS!$A$5:$A$400<=$A69)*MOVIMIENTOS!$E$5:$E$400)-SUMPRODUCT((MOVIMIENTOS!$B$5:$B$400="ENVÍO A SUPESA")*(MOVIMIENTOS!$C$5:$C$400="M")*(MOVIMIENTOS!$D$5:$D$400="jabas")*(MOVIMIENTOS!$A$5:$A$400<>"")*(MOVIMIENTOS!$A$5:$A$400<=$A69)*MOVIMIENTOS!$E$5:$E$400)+SUMPRODUCT((MOVIMIENTOS!$B$5:$B$400="DEVOLUCIÓN")*(MOVIMIENTOS!$C$5:$C$400="M")*(MOVIMIENTOS!$D$5:$D$400="jabas")*(MOVIMIENTOS!$A$5:$A$400<>"")*(MOVIMIENTOS!$A$5:$A$400<=$A69)*MOVIMIENTOS!$E$5:$E$400)-SUMPRODUCT((MOVIMIENTOS!$B$5:$B$400="TRASIEGO")*(MOVIMIENTOS!$C$5:$C$400="M")*(MOVIMIENTOS!$D$5:$D$400="jabas")*(MOVIMIENTOS!$A$5:$A$400<>"")*(MOVIMIENTOS!$A$5:$A$400<=$A69)*MOVIMIENTOS!$E$5:$E$400)-SUMPRODUCT((MOVIMIENTOS!$B$5:$B$400="REGALO")*(MOVIMIENTOS!$C$5:$C$400="M")*(MOVIMIENTOS!$D$5:$D$400="jabas")*(MOVIMIENTOS!$A$5:$A$400<>"")*(MOVIMIENTOS!$A$5:$A$400<=$A69)*MOVIMIENTOS!$E$5:$E$400)-SUMPRODUCT((MOVIMIENTOS!$B$5:$B$400="VENTA")*(MOVIMIENTOS!$C$5:$C$400="M")*(MOVIMIENTOS!$D$5:$D$400="jabas")*(MOVIMIENTOS!$A$5:$A$400<>"")*(MOVIMIENTOS!$A$5:$A$400<=$A69)*MOVIMIENTOS!$E$5:$E$400)+SUMPRODUCT((MOVIMIENTOS!$B$5:$B$400="AJUSTE")*(MOVIMIENTOS!$C$5:$C$400="M")*(MOVIMIENTOS!$D$5:$D$400="jabas")*(MOVIMIENTOS!$A$5:$A$400<>"")*(MOVIMIENTOS!$A$5:$A$400<=$A69)*MOVIMIENTOS!$E$5:$E$400)) | F69: =IF($A69="","",SUMPRODUCT((MOVIMIENTOS!$B$5:$B$400="SALDO INICIAL")*(MOVIMIENTOS!$C$5:$C$400="Chancho")*(MOVIMIENTOS!$D$5:$D$400="sacos")*(MOVIMIENTOS!$A$5:$A$400<>"")*(MOVIMIENTOS!$A$5:$A$400<=$A69)*MOVIMIENTOS!$E$5:$E$400)+SUMPRODUCT((MOVIMIENTOS!$B$5:$B$400="PROCESO")*(MOVIMIENTOS!$C$5:$C$400="Chancho")*(MOVIMIENTOS!$D$5:$D$400="sacos")*(MOVIMIENTOS!$A$5:$A$400<>"")*(MOVIMIENTOS!$A$5:$A$400<=$A69)*MOVIMIENTOS!$E$5:$E$400)-SUMPRODUCT((MOVIMIENTOS!$B$5:$B$400="VENTA CHANCHO")*(MOVIMIENTOS!$C$5:$C$400="Chancho")*(MOVIMIENTOS!$D$5:$D$400="sacos")*(MOVIMIENTOS!$A$5:$A$400<>"")*(MOVIMIENTOS!$A$5:$A$400<=$A69)*MOVIMIENTOS!$E$5:$E$400)-SUMPRODUCT((MOVIMIENTOS!$B$5:$B$400="REGALO")*(MOVIMIENTOS!$C$5:$C$400="Chancho")*(MOVIMIENTOS!$D$5:$D$400="sacos")*(MOVIMIENTOS!$A$5:$A$400<>"")*(MOVIMIENTOS!$A$5:$A$400<=$A69)*MOVIMIENTOS!$E$5:$E$400)-SUMPRODUCT((MOVIMIENTOS!$B$5:$B$400="VENTA")*(MOVIMIENTOS!$C$5:$C$400="Chancho")*(MOVIMIENTOS!$D$5:$D$400="sacos")*(MOVIMIENTOS!$A$5:$A$400<>"")*(MOVIMIENTOS!$A$5:$A$400<=$A69)*MOVIMIENTOS!$E$5:$E$400)+SUMPRODUCT((MOVIMIENTOS!$B$5:$B$400="AJUSTE")*(MOVIMIENTOS!$C$5:$C$400="Chancho")*(MOVIMIENTOS!$D$5:$D$400="sacos")*(MOVIMIENTOS!$A$5:$A$400<>"")*(MOVIMIENTOS!$A$5:$A$400<=$A69)*MOVIMIENTOS!$E$5:$E$400)) | G69: =IF($A69="","",SUM(B69:E69)) | H69: =IF($A69="","",SUMPRODUCT((((MOVIMIENTOS!$B$5:$B$400="SALDO INICIAL")*(MOVIMIENTOS!$C$5:$C$400<>"Chancho"))+(MOVIMIENTOS!$B$5:$B$400="COMPRA")+(MOVIMIENTOS!$B$5:$B$400="REPROCESO")+(MOVIMIENTOS!$B$5:$B$400="DEVOLUCIÓN")+((MOVIMIENTOS!$B$5:$B$400="AJUSTE")*(MOVIMIENTOS!$C$5:$C$400<>"Chancho")))*(MOVIMIENTOS!$A$5:$A$400<>"")*(MOVIMIENTOS!$A$5:$A$400<=$A69)*MOVIMIENTOS!$I$5:$I$400)-SUMPRODUCT(((MOVIMIENTOS!$B$5:$B$400="ENVÍO A SUPESA")+(MOVIMIENTOS!$B$5:$B$400="ENVÍO A TOTTUS")+(MOVIMIENTOS!$B$5:$B$400="ENVIO A TOTTUS")+(MOVIMIENTOS!$B$5:$B$400="MALOGRADO")+(MOVIMIENTOS!$B$5:$B$400="OTRA SALIDA")+((MOVIMIENTOS!$B$5:$B$400="PROCESO")*(MOVIMIENTOS!$C$5:$C$400="Chancho"))+((MOVIMIENTOS!$B$5:$B$400="REGALO")*(MOVIMIENTOS!$C$5:$C$400<>"Chancho"))+((MOVIMIENTOS!$B$5:$B$400="VENTA")*(MOVIMIENTOS!$C$5:$C$400<>"Chancho")))*(MOVIMIENTOS!$A$5:$A$400<>"")*(MOVIMIENTOS!$A$5:$A$400<=$A69)*MOVIMIENTOS!$I$5:$I$400)) | J69: =IF(AND(MOVIMIENTOS!$A69<>"",COUNTIF(MOVIMIENTOS!$A$5:$A68,MOVIMIENTOS!$A69)=0),COUNT(J$4:J68)+1,"") | K69: =MOVIMIENTOS!$A69 -> 46220
J70: =IF(AND(MOVIMIENTOS!$A70<>"",COUNTIF(MOVIMIENTOS!$A$5:$A69,MOVIMIENTOS!$A70)=0),COUNT(J$4:J69)+1,"") | K70: =MOVIMIENTOS!$A70 -> 46220
J71: =IF(AND(MOVIMIENTOS!$A71<>"",COUNTIF(MOVIMIENTOS!$A$5:$A70,MOVIMIENTOS!$A71)=0),COUNT(J$4:J70)+1,"") | K71: =MOVIMIENTOS!$A71 -> 46220
J72: =IF(AND(MOVIMIENTOS!$A72<>"",COUNTIF(MOVIMIENTOS!$A$5:$A71,MOVIMIENTOS!$A72)=0),COUNT(J$4:J71)+1,"") | K72: =MOVIMIENTOS!$A72 -> 46220
J73: =IF(AND(MOVIMIENTOS!$A73<>"",COUNTIF(MOVIMIENTOS!$A$5:$A72,MOVIMIENTOS!$A73)=0),COUNT(J$4:J72)+1,"") | K73: =MOVIMIENTOS!$A73 -> 46220
J74: =IF(AND(MOVIMIENTOS!$A74<>"",COUNTIF(MOVIMIENTOS!$A$5:$A73,MOVIMIENTOS!$A74)=0),COUNT(J$4:J73)+1,"") | K74: =MOVIMIENTOS!$A74 -> 46220
J75: =IF(AND(MOVIMIENTOS!$A75<>"",COUNTIF(MOVIMIENTOS!$A$5:$A74,MOVIMIENTOS!$A75)=0),COUNT(J$4:J74)+1,"") -> 8 | K75: =MOVIMIENTOS!$A75 -> 46221
J76: =IF(AND(MOVIMIENTOS!$A76<>"",COUNTIF(MOVIMIENTOS!$A$5:$A75,MOVIMIENTOS!$A76)=0),COUNT(J$4:J75)+1,"") | K76: =MOVIMIENTOS!$A76 -> 46221
J77: =IF(AND(MOVIMIENTOS!$A77<>"",COUNTIF(MOVIMIENTOS!$A$5:$A76,MOVIMIENTOS!$A77)=0),COUNT(J$4:J76)+1,"") | K77: =MOVIMIENTOS!$A77 -> 46221
J78: =IF(AND(MOVIMIENTOS!$A78<>"",COUNTIF(MOVIMIENTOS!$A$5:$A77,MOVIMIENTOS!$A78)=0),COUNT(J$4:J77)+1,"") | K78: =MOVIMIENTOS!$A78 -> 46221
J79: =IF(AND(MOVIMIENTOS!$A79<>"",COUNTIF(MOVIMIENTOS!$A$5:$A78,MOVIMIENTOS!$A79)=0),COUNT(J$4:J78)+1,"") | K79: =MOVIMIENTOS!$A79 -> 46221
J80: =IF(AND(MOVIMIENTOS!$A80<>"",COUNTIF(MOVIMIENTOS!$A$5:$A79,MOVIMIENTOS!$A80)=0),COUNT(J$4:J79)+1,"") | K80: =MOVIMIENTOS!$A80 -> 46221
J81: =IF(AND(MOVIMIENTOS!$A81<>"",COUNTIF(MOVIMIENTOS!$A$5:$A80,MOVIMIENTOS!$A81)=0),COUNT(J$4:J80)+1,"") | K81: =MOVIMIENTOS!$A81 -> 46221
... J400: =IF(AND(MOVIMIENTOS!$A400<>"",COUNTIF(MOVIMIENTOS!$A$5:$A399,MOVIMIENTOS!$A400)=0),COUNT(J$4:J399)+1,"") | K400: =MOVIMIENTOS!$A400 -> 0

Sheet KARDEX
A1: AGRO PACAYALES · PLANTA CAMOTE 2026 | KARDEX — Ingreso, Procesado y Enviado de camote (kg) por día
A2: Cada día empieza con una fila de RESUMEN en negrita: Ingreso (compra), Procesado (selección + chancho) y Enviado a SUPESA, además del Stock Kg al cierre del día. Debajo va el detalle de cada movimiento. SELECCIÓN y RECHAZO son informativos (no restan del Stock Kg): SELECCIÓN es cuánto se clasificó en A/P/C/M ese día, RECHAZO son jabas que van a reproceso. El chancho sí sale del Stock Kg (pasa a su propio conteo en sacos).
C4: INGRESO | D4: PROCESADO | E4: SALIDAS
A5: Fecha | B5: Detalle | C5: Ingreso Kg | D5: Procesado Kg | E5: Salidas Kg | F5: N. Guía / Nota | G5: Stock Kg
A6: 46214 | B6: 📅 RESUMEN DEL DÍA | C6: =SUMPRODUCT((MOVIMIENTOS!$A$5:$A$400=DATE(2026,7,11))*(MOVIMIENTOS!$B$5:$B$400="COMPRA")*MOVIMIENTOS!$I$5:$I$400) -> 0 | D6: =SUMPRODUCT((MOVIMIENTOS!$A$5:$A$400=DATE(2026,7,11))*(MOVIMIENTOS!$B$5:$B$400="PROCESO")*MOVIMIENTOS!$I$5:$I$400) -> 0 | E6: =SUMPRODUCT((MOVIMIENTOS!$A$5:$A$400=DATE(2026,7,11))*((MOVIMIENTOS!$B$5:$B$400="ENVÍO A SUPESA")+(MOVIMIENTOS!$B$5:$B$400="ENVÍO A TOTTUS")+(MOVIMIENTOS!$B$5:$B$400="ENVIO A TOTTUS"))*MOVIMIENTOS!$I$5:$I$400) -> 0 | F6: ="Selección: "&TEXT(SUMPRODUCT((MOVIMIENTOS!$A$5:$A$400=DATE(2026,7,11))*(MOVIMIENTOS!$B$5:$B$400="PROCESO")*(MOVIMIENTOS!$C$5:$C$400<>"Chancho")*MOVIMIENTOS!$I$5:$I$400),"#,##0")&" kg · Chancho: "&TEXT(SUMPRODUCT((MOVIMIENTOS!$A$5:$A$400=DATE(2026,7,11))*(MOVIMIENTOS!$B$5:$B$400="PROCESO")*(MOVIMIENTOS!$C$5:$C$400="Chancho")*MOVIMIENTOS!$I$5:$I$400),"#,##0")&" kg"&IF(C6>0," · "&TEXT(D6/C6,"0%")&" del ingreso","") -> Selección: 0 kg · Chancho: 0 kg | G6: =N(G8) -> 166
A7: 46214 | B7: AJUSTE | C7: =N(MOVIMIENTOS!$I5)+N(MOVIMIENTOS!$I6) -> 47 | F7: Cal. A+M | G7: =N(0)+N(C7)-N(E7) -> 47
A8: 46214 | B8: APERTURA (M) | C8: =N(MOVIMIENTOS!$I7) -> 119 | F8: =TRIM(IF(MOVIMIENTOS!$G7<>"",MOVIMIENTOS!$G7&" ","")&IF(N(MOVIMIENTOS!$E7)>0,MOVIMIENTOS!$E7&" "&MOVIMIENTOS!$D7&" ","")&IF(MOVIMIENTOS!$H7<>"",MOVIMIENTOS!$H7,"")) -> 7 jabas | G8: =N(G7)+N(C8)-N(E8) -> 166
A9: 46215 | B9: 📅 RESUMEN DEL DÍA | C9: =SUMPRODUCT((MOVIMIENTOS!$A$5:$A$400=DATE(2026,7,12))*(MOVIMIENTOS!$B$5:$B$400="COMPRA")*MOVIMIENTOS!$I$5:$I$400) -> 2910 | D9: =SUMPRODUCT((MOVIMIENTOS!$A$5:$A$400=DATE(2026,7,12))*(MOVIMIENTOS!$B$5:$B$400="PROCESO")*MOVIMIENTOS!$I$5:$I$400) -> 2957 | E9: =SUMPRODUCT((MOVIMIENTOS!$A$5:$A$400=DATE(2026,7,12))*((MOVIMIENTOS!$B$5:$B$400="ENVÍO A SUPESA")+(MOVIMIENTOS!$B$5:$B$400="ENVÍO A TOTTUS")+(MOVIMIENTOS!$B$5:$B$400="ENVIO A TOTTUS"))*MOVIMIENTOS!$I$5:$I$400) -> 2121 | F9: ="Selección: "&TEXT(SUMPRODUCT((MOVIMIENTOS!$A$5:$A$400=DATE(2026,7,12))*(MOVIMIENTOS!$B$5:$B$400="PROCESO")*(MOVIMIENTOS!$C$5:$C$400<>"Chancho")*MOVIMIENTOS!$I$5:$I$400),"#,##0")&" kg · Chancho: "&TEXT(SUMPRODUCT((MOVIMIENTOS!$A$5:$A$400=DATE(2026,7,12))*(MOVIMIENTOS!$B$5:$B$400="PROCESO")*(MOVIMIENTOS!$C$5:$C$400="Chancho")*MOVIMIENTOS!$I$5:$I$400),"#,##0")&" kg"&IF(C9>0," · "&TEXT(D9/C9,"0%")&" del ingreso","") -> Selección: 2,375 kg · Chancho: 582 kg · 102% del ingreso | G9: =N(G13) -> 373
A10: 46215 | B10: INGRESO (compra) | C10: =N(MOVIMIENTOS!$I9) -> 2910 | F10: =TRIM(IF(MOVIMIENTOS!$G9<>"",MOVIMIENTOS!$G9&" ","")&IF(N(MOVIMIENTOS!$E9)>0,MOVIMIENTOS!$E9&" "&MOVIMIENTOS!$D9&" ","")&IF(MOVIMIENTOS!$H9<>"",MOVIMIENTOS!$H9,"")) -> 30 sacos peso aprox 95 kg/saco | G10: =N(G8)+N(C10)-N(E10) -> 3076
A11: 46215 | B11: SELECCIÓN (proceso) | D11: =SUMPRODUCT((MOVIMIENTOS!$A$5:$A$400=DATE(2026,7,12))*(MOVIMIENTOS!$B$5:$B$400="PROCESO")*(MOVIMIENTOS!$C$5:$C$400<>"Chancho")*MOVIMIENTOS!$I$5:$I$400) -> 2375 | F11: A=59j · P=11j · C=12j · M=64j | G11: =N(G10) -> 3076
A12: 46215 | B12: CHANCHO (proceso) | D12: =N(MOVIMIENTOS!$I14) -> 582 | E12: =N(MOVIMIENTOS!$I14) -> 582 | F12: =TRIM(IF(MOVIMIENTOS!$G14<>"",MOVIMIENTOS!$G14&" ","")&IF(N(MOVIMIENTOS!$E14)>0,MOVIMIENTOS!$E14&" "&MOVIMIENTOS!$D14&" ","")&IF(MOVIMIENTOS!$H14<>"",MOVIMIENTOS!$H14,"")) -> 6 sacos | G12: =N(G11)+N(C12)-N(E12) -> 2494
A13: 46215 | B13: ENVÍO A SUPESA | E13: =N(MOVIMIENTOS!$I15)+N(MOVIMIENTOS!$I16)+N(MOVIMIENTOS!$I17)+N(MOVIMIENTOS!$I18) -> 2121 | F13: Cal. A+C+M+P · 2977 | G13: =N(G12)+N(C13)-N(E13) -> 373
A14: 46216 | B14: 📅 RESUMEN DEL DÍA | C14: =SUMPRODUCT((MOVIMIENTOS!$A$5:$A$400=DATE(2026,7,13))*(MOVIMIENTOS!$B$5:$B$400="COMPRA")*MOVIMIENTOS!$I$5:$I$400) -> 3880 | D14: =SUMPRODUCT((MOVIMIENTOS!$A$5:$A$400=DATE(2026,7,13))*(MOVIMIENTOS!$B$5:$B$400="PROCESO")*MOVIMIENTOS!$I$5:$I$400) -> 4071 | E14: =SUMPRODUCT((MOVIMIENTOS!$A$5:$A$400=DATE(2026,7,13))*((MOVIMIENTOS!$B$5:$B$400="ENVÍO A SUPESA")+(MOVIMIENTOS!$B$5:$B$400="ENVÍO A TOTTUS")+(MOVIMIENTOS!$B$5:$B$400="ENVIO A TOTTUS"))*MOVIMIENTOS!$I$5:$I$400) -> 3056 | F14: ="Selección: "&TEXT(SUMPRODUCT((MOVIMIENTOS!$A$5:$A$400=DATE(2026,7,13))*(MOVIMIENTOS!$B$5:$B$400="PROCESO")*(MOVIMIENTOS!$C$5:$C$400<>"Chancho")*MOVIMIENTOS!$I$5:$I$400),"#,##0")&" kg · Chancho: "&TEXT(SUMPRODUCT((MOVIMIENTOS!$A$5:$A$400=DATE(2026,7,13))*(MOVIMIENTOS!$B$5:$B$400="PROCESO")*(MOVIMIENTOS!$C$5:$C$400="Chancho")*MOVIMIENTOS!$I$5:$I$400),"#,##0")&" kg"&IF(C14>0," · "&TEXT(D14/C14,"0%")&" del ingreso","") -> Selección: 3,877 kg · Chancho: 194 kg · 105% del ingreso | G14: =N(G18) -> 1003
A15: 46216 | B15: INGRESO (compra) | C15: =N(MOVIMIENTOS!$I19) -> 3880 | F15: =TRIM(IF(MOVIMIENTOS!$G19<>"",MOVIMIENTOS!$G19&" ","")&IF(N(MOVIMIENTOS!$E19)>0,MOVIMIENTOS!$E19&" "&MOVIMIENTOS!$D19&" ","")&IF(MOVIMIENTOS!$H19<>"",MOVIMIENTOS!$H19,"")) -> 40 sacos peso aprox 95 kg/saco | G15: =N(G13)+N(C15)-N(E15) -> 4253
A16: 46216 | B16: SELECCIÓN (proceso) | D16: =SUMPRODUCT((MOVIMIENTOS!$A$5:$A$400=DATE(2026,7,13))*(MOVIMIENTOS!$B$5:$B$400="PROCESO")*(MOVIMIENTOS!$C$5:$C$400<>"Chancho")*MOVIMIENTOS!$I$5:$I$400) -> 3877 | F16: A=107j · P=11j · C=12j · M=110j | G16: =N(G15) -> 4253
A17: 46216 | B17: CHANCHO (proceso) | D17: =N(MOVIMIENTOS!$I24) -> 194 | E17: =N(MOVIMIENTOS!$I24) -> 194 | F17: =TRIM(IF(MOVIMIENTOS!$G24<>"",MOVIMIENTOS!$G24&" ","")&IF(N(MOVIMIENTOS!$E24)>0,MOVIMIENTOS!$E24&" "&MOVIMIENTOS!$D24&" ","")&IF(MOVIMIENTOS!$H24<>"",MOVIMIENTOS!$H24,"")) -> 2 sacos | G17: =N(G16)+N(C17)-N(E17) -> 4059
A18: 46216 | B18: ENVÍO A SUPESA | E18: =N(MOVIMIENTOS!$I25)+N(MOVIMIENTOS!$I26)+N(MOVIMIENTOS!$I27)+N(MOVIMIENTOS!$I28) -> 3056 | F18: Cal. A+C+M+P · 2980 | G18: =N(G17)+N(C18)-N(E18) -> 1003
A19: 46217 | B19: 📅 RESUMEN DEL DÍA | C19: =SUMPRODUCT((MOVIMIENTOS!$A$5:$A$400=DATE(2026,7,14))*(MOVIMIENTOS!$B$5:$B$400="COMPRA")*MOVIMIENTOS!$I$5:$I$400) -> 3880 | D19: =SUMPRODUCT((MOVIMIENTOS!$A$5:$A$400=DATE(2026,7,14))*(MOVIMIENTOS!$B$5:$B$400="PROCESO")*MOVIMIENTOS!$I$5:$I$400) -> 3813 | E19: =SUMPRODUCT((MOVIMIENTOS!$A$5:$A$400=DATE(2026,7,14))*((MOVIMIENTOS!$B$5:$B$400="ENVÍO A SUPESA")+(MOVIMIENTOS!$B$5:$B$400="ENVÍO A TOTTUS")+(MOVIMIENTOS!$B$5:$B$400="ENVIO A TOTTUS"))*MOVIMIENTOS!$I$5:$I$400) -> 3379 | F19: ="Selección: "&TEXT(SUMPRODUCT((MOVIMIENTOS!$A$5:$A$400=DATE(2026,7,14))*(MOVIMIENTOS!$B$5:$B$400="PROCESO")*(MOVIMIENTOS!$C$5:$C$400<>"Chancho")*MOVIMIENTOS!$I$5:$I$400),"#,##0")&" kg · Chancho: "&TEXT(SUMPRODUCT((MOVIMIENTOS!$A$5:$A$400=DATE(2026,7,14))*(MOVIMIENTOS!$B$5:$B$400="PROCESO")*(MOVIMIENTOS!$C$5:$C$400="Chancho")*MOVIMIENTOS!$I$5:$I$400),"#,##0")&" kg"&IF(C19>0," · "&TEXT(D19/C19,"0%")&" del ingreso","") -> Selección: 3,134 kg · Chancho: 679 kg · 98% del ingreso | G19: =N(G23) -> 825
A20: 46217 | B20: INGRESO (compra) | C20: =N(MOVIMIENTOS!$I29) -> 3880 | F20: =TRIM(IF(MOVIMIENTOS!$G29<>"",MOVIMIENTOS!$G29&" ","")&IF(N(MOVIMIENTOS!$E29)>0,MOVIMIENTOS!$E29&" "&MOVIMIENTOS!$D29&" ","")&IF(MOVIMIENTOS!$H29<>"",MOVIMIENTOS!$H29,"")) -> 40 sacos peso aprox 95 kg/saco | G20: =N(G18)+N(C20)-N(E20) -> 4883
A21: 46217 | B21: SELECCIÓN (proceso) | D21: =SUMPRODUCT((MOVIMIENTOS!$A$5:$A$400=DATE(2026,7,14))*(MOVIMIENTOS!$B$5:$B$400="PROCESO")*(MOVIMIENTOS!$C$5:$C$400<>"Chancho")*MOVIMIENTOS!$I$5:$I$400) -> 3134 | F21: A=45j · P=11j · C=12j · M=121j | G21: =N(G20) -> 4883
A22: 46217 | B22: CHANCHO (proceso) | D22: =N(MOVIMIENTOS!$I34) -> 679 | E22: =N(MOVIMIENTOS!$I34) -> 679 | F22: =TRIM(IF(MOVIMIENTOS!$G34<>"",MOVIMIENTOS!$G34&" ","")&IF(N(MOVIMIENTOS!$E34)>0,MOVIMIENTOS!$E34&" "&MOVIMIENTOS!$D34&" ","")&IF(MOVIMIENTOS!$H34<>"",MOVIMIENTOS!$H34,"")) -> 7 sacos | G22: =N(G21)+N(C22)-N(E22) -> 4204
A23: 46217 | B23: ENVÍO A SUPESA | E23: =N(MOVIMIENTOS!$I35)+N(MOVIMIENTOS!$I36)+N(MOVIMIENTOS!$I37)+N(MOVIMIENTOS!$I38) -> 3379 | F23: Cal. A+C+M+P · 2984 | G23: =N(G22)+N(C23)-N(E23) -> 825
A24: 46218 | B24: 📅 RESUMEN DEL DÍA | C24: =SUMPRODUCT((MOVIMIENTOS!$A$5:$A$400=DATE(2026,7,15))*(MOVIMIENTOS!$B$5:$B$400="COMPRA")*MOVIMIENTOS!$I$5:$I$400) -> 3880 | D24: =SUMPRODUCT((MOVIMIENTOS!$A$5:$A$400=DATE(2026,7,15))*(MOVIMIENTOS!$B$5:$B$400="PROCESO")*MOVIMIENTOS!$I$5:$I$400) -> 3834 | E24: =SUMPRODUCT((MOVIMIENTOS!$A$5:$A$400=DATE(2026,7,15))*((MOVIMIENTOS!$B$5:$B$400="ENVÍO A SUPESA")+(MOVIMIENTOS!$B$5:$B$400="ENVÍO A TOTTUS")+(MOVIMIENTOS!$B$5:$B$400="ENVIO A TOTTUS"))*MOVIMIENTOS!$I$5:$I$400) -> 2971 | F24: ="Selección: "&TEXT(SUMPRODUCT((MOVIMIENTOS!$A$5:$A$400=DATE(2026,7,15))*(MOVIMIENTOS!$B$5:$B$400="PROCESO")*(MOVIMIENTOS!$C$5:$C$400<>"Chancho")*MOVIMIENTOS!$I$5:$I$400),"#,##0")&" kg · Chancho: "&TEXT(SUMPRODUCT((MOVIMIENTOS!$A$5:$A$400=DATE(2026,7,15))*(MOVIMIENTOS!$B$5:$B$400="PROCESO")*(MOVIMIENTOS!$C$5:$C$400="Chancho")*MOVIMIENTOS!$I$5:$I$400),"#,##0")&" kg"&IF(C24>0," · "&TEXT(D24/C24,"0%")&" del ingreso","") -> Selección: 3,349 kg · Chancho: 485 kg · 99% del ingreso | G24: =N(G29) -> 1249
A25: 46218 | B25: INGRESO (compra) | C25: =N(MOVIMIENTOS!$I39) -> 3880 | F25: =TRIM(IF(MOVIMIENTOS!$G39<>"",MOVIMIENTOS!$G39&" ","")&IF(N(MOVIMIENTOS!$E39)>0,MOVIMIENTOS!$E39&" "&MOVIMIENTOS!$D39&" ","")&IF(MOVIMIENTOS!$H39<>"",MOVIMIENTOS!$H39,"")) -> 40 sacos peso aprox 95 kg/saco | G25: =N(G23)+N(C25)-N(E25) -> 4705
A26: 46218 | B26: SELECCIÓN (proceso) | D26: =SUMPRODUCT((MOVIMIENTOS!$A$5:$A$400=DATE(2026,7,15))*(MOVIMIENTOS!$B$5:$B$400="PROCESO")*(MOVIMIENTOS!$C$5:$C$400<>"Chancho")*MOVIMIENTOS!$I$5:$I$400) -> 3349 | F26: A=79j · P=22j · C=21j · M=83j | G26: =N(G25) -> 4705
A27: 46218 | B27: CHANCHO (proceso) | D27: =N(MOVIMIENTOS!$I44) -> 485 | E27: =N(MOVIMIENTOS!$I44) -> 485 | F27: =TRIM(IF(MOVIMIENTOS!$G44<>"",MOVIMIENTOS!$G44&" ","")&IF(N(MOVIMIENTOS!$E44)>0,MOVIMIENTOS!$E44&" "&MOVIMIENTOS!$D44&" ","")&IF(MOVIMIENTOS!$H44<>"",MOVIMIENTOS!$H44,"")) -> 5 sacos | G27: =N(G26)+N(C27)-N(E27) -> 4220
A28: 46218 | B28: ENVÍO A SUPESA | E28: =N(MOVIMIENTOS!$I45)+N(MOVIMIENTOS!$I46)+N(MOVIMIENTOS!$I47)+N(MOVIMIENTOS!$I48) -> 2971 | F28: Cal. A+C+M+P · 2986 | G28: =N(G27)+N(C28)-N(E28) -> 1249
A29: 46218 | B29: VENTA CHANCHO | F29: =TRIM(IF(MOVIMIENTOS!$G49<>"",MOVIMIENTOS!$G49&" ","")&IF(N(MOVIMIENTOS!$E49)>0,MOVIMIENTOS!$E49&" "&MOVIMIENTOS!$D49&" ","")&IF(MOVIMIENTOS!$H49<>"",MOVIMIENTOS!$H49,"")) -> TCK002-724 35 sacos | G29: =N(G28)+N(C29)-N(E29) -> 1249
A30: 46219 | B30: 📅 RESUMEN DEL DÍA | C30: =SUMPRODUCT((MOVIMIENTOS!$A$5:$A$400=DATE(2026,7,16))*(MOVIMIENTOS!$B$5:$B$400="COMPRA")*MOVIMIENTOS!$I$5:$I$400) -> 3880 | D30: =SUMPRODUCT((MOVIMIENTOS!$A$5:$A$400=DATE(2026,7,16))*(MOVIMIENTOS!$B$5:$B$400="PROCESO")*MOVIMIENTOS!$I$5:$I$400) -> 3782 | E30: =SUMPRODUCT((MOVIMIENTOS!$A$5:$A$400=DATE(2026,7,16))*((MOVIMIENTOS!$B$5:$B$400="ENVÍO A SUPESA")+(MOVIMIENTOS!$B$5:$B$400="ENVÍO A TOTTUS")+(MOVIMIENTOS!$B$5:$B$400="ENVIO A TOTTUS"))*MOVIMIENTOS!$I$5:$I$400) -> 3302 | F30: ="Selección: "&TEXT(SUMPRODUCT((MOVIMIENTOS!$A$5:$A$400=DATE(2026,7,16))*(MOVIMIENTOS!$B$5:$B$400="PROCESO")*(MOVIMIENTOS!$C$5:$C$400<>"Chancho")*MOVIMIENTOS!$I$5:$I$400),"#,##0")&" kg · Chancho: "&TEXT(SUMPRODUCT((MOVIMIENTOS!$A$5:$A$400=DATE(2026,7,16))*(MOVIMIENTOS!$B$5:$B$400="PROCESO")*(MOVIMIENTOS!$C$5:$C$400="Chancho")*MOVIMIENTOS!$I$5:$I$400),"#,##0")&" kg"&IF(C30>0," · "&TEXT(D30/C30,"0%")&" del ingreso","") -> Selección: 3,394 kg · Chancho: 388 kg · 97% del ingreso | G30: =N(G34) -> 1439
A31: 46219 | B31: INGRESO (compra) | C31: =N(MOVIMIENTOS!$I50) -> 3880 | F31: =TRIM(IF(MOVIMIENTOS!$G50<>"",MOVIMIENTOS!$G50&" ","")&IF(N(MOVIMIENTOS!$E50)>0,MOVIMIENTOS!$E50&" "&MOVIMIENTOS!$D50&" ","")&IF(MOVIMIENTOS!$H50<>"",MOVIMIENTOS!$H50,"")) -> 40 sacos peso aprox 95 kg/saco | G31: =N(G29)+N(C31)-N(E31) -> 5129
A32: 46219 | B32: SELECCIÓN (proceso) | D32: =SUMPRODUCT((MOVIMIENTOS!$A$5:$A$400=DATE(2026,7,16))*(MOVIMIENTOS!$B$5:$B$400="PROCESO")*(MOVIMIENTOS!$C$5:$C$400<>"Chancho")*MOVIMIENTOS!$I$5:$I$400) -> 3394 | F32: A=68j · P=11j · C=12j · M=116j | G32: =N(G31) -> 5129
A33: 46219 | B33: CHANCHO (proceso) | D33: =N(MOVIMIENTOS!$I55) -> 388 | E33: =N(MOVIMIENTOS!$I55) -> 388 | F33: =TRIM(IF(MOVIMIENTOS!$G55<>"",MOVIMIENTOS!$G55&" ","")&IF(N(MOVIMIENTOS!$E55)>0,MOVIMIENTOS!$E55&" "&MOVIMIENTOS!$D55&" ","")&IF(MOVIMIENTOS!$H55<>"",MOVIMIENTOS!$H55,"")) -> 4 sacos | G33: =N(G32)+N(C33)-N(E33) -> 4741
A34: 46219 | B34: ENVÍO A SUPESA | E34: =N(MOVIMIENTOS!$I56)+N(MOVIMIENTOS!$I57)+N(MOVIMIENTOS!$I58)+N(MOVIMIENTOS!$I59) -> 3302 | F34: Cal. A+C+M+P · 2992 | G34: =N(G33)+N(C34)-N(E34) -> 1439
A35: 46220 | B35: 📅 RESUMEN DEL DÍA | C35: =SUMPRODUCT((MOVIMIENTOS!$A$5:$A$400=DATE(2026,7,17))*(MOVIMIENTOS!$B$5:$B$400="COMPRA")*MOVIMIENTOS!$I$5:$I$400) -> 6305 | D35: =SUMPRODUCT((MOVIMIENTOS!$A$5:$A$400=DATE(2026,7,17))*(MOVIMIENTOS!$B$5:$B$400="PROCESO")*MOVIMIENTOS!$I$5:$I$400) -> 6169 | E35: =SUMPRODUCT((MOVIMIENTOS!$A$5:$A$400=DATE(2026,7,17))*((MOVIMIENTOS!$B$5:$B$400="ENVÍO A SUPESA")+(MOVIMIENTOS!$B$5:$B$400="ENVÍO A TOTTUS")+(MOVIMIENTOS!$B$5:$B$400="ENVIO A TOTTUS"))*MOVIMIENTOS!$I$5:$I$400) -> 3413 | F35: ="Selección: "&TEXT(SUMPRODUCT((MOVIMIENTOS!$A$5:$A$400=DATE(2026,7,17))*(MOVIMIENTOS!$B$5:$B$400="PROCESO")*(MOVIMIENTOS!$C$5:$C$400<>"Chancho")*MOVIMIENTOS!$I$5:$I$400),"#,##0")&" kg · Chancho: "&TEXT(SUMPRODUCT((MOVIMIENTOS!$A$5:$A$400=DATE(2026,7,17))*(MOVIMIENTOS!$B$5:$B$400="PROCESO")*(MOVIMIENTOS!$C$5:$C$400="Chancho")*MOVIMIENTOS!$I$5:$I$400),"#,##0")&" kg"&IF(C35>0," · "&TEXT(D35/C35,"0%")&" del ingreso","") -> Selección: 5,102 kg · Chancho: 1,067 kg · 98% del ingreso | G35: =N(G42) -> 3264
A36: 46220 | B36: INGRESO (compra) | C36: =N(MOVIMIENTOS!$I60) -> 5820 | F36: =TRIM(IF(MOVIMIENTOS!$G60<>"",MOVIMIENTOS!$G60&" ","")&IF(N(MOVIMIENTOS!$E60)>0,MOVIMIENTOS!$E60&" "&MOVIMIENTOS!$D60&" ","")&IF(MOVIMIENTOS!$H60<>"",MOVIMIENTOS!$H60,"")) -> 60 sacos peso aprox 95 kg/saco | G36: =N(G34)+N(C36)-N(E36) -> 7259
A37: 46220 | B37: SELECCIÓN (proceso) | D37: =SUMPRODUCT((MOVIMIENTOS!$A$5:$A$400=DATE(2026,7,17))*(MOVIMIENTOS!$B$5:$B$400="PROCESO")*(MOVIMIENTOS!$C$5:$C$400<>"Chancho")*MOVIMIENTOS!$I$5:$I$400) -> 5102 | F37: A=103j · P=4j · C=9j · M=196j | G37: =N(G36) -> 7259
A38: 46220 | B38: CHANCHO (proceso) | D38: =N(MOVIMIENTOS!$I65) -> 970 | E38: =N(MOVIMIENTOS!$I65) -> 970 | F38: =TRIM(IF(MOVIMIENTOS!$G65<>"",MOVIMIENTOS!$G65&" ","")&IF(N(MOVIMIENTOS!$E65)>0,MOVIMIENTOS!$E65&" "&MOVIMIENTOS!$D65&" ","")&IF(MOVIMIENTOS!$H65<>"",MOVIMIENTOS!$H65,"")) -> 10 sacos | G38: =N(G37)+N(C38)-N(E38) -> 6289
A39: 46220 | B39: ENVÍO A SUPESA | E39: =N(MOVIMIENTOS!$I66)+N(MOVIMIENTOS!$I67)+N(MOVIMIENTOS!$I68)+N(MOVIMIENTOS!$I69) -> 3413 | F39: Cal. A+C+M+P · 2994 | G39: =N(G38)+N(C39)-N(E39) -> 2876
A40: 46220 | B40: VENTA CHANCHO | F40: =TRIM(IF(MOVIMIENTOS!$G70<>"",MOVIMIENTOS!$G70&" ","")&IF(N(MOVIMIENTOS!$E70)>0,MOVIMIENTOS!$E70&" "&MOVIMIENTOS!$D70&" ","")&IF(MOVIMIENTOS!$H70<>"",MOVIMIENTOS!$H70,"")) -> TCK002-725 15 sacos | G40: =N(G39)+N(C40)-N(E40) -> 2876
A41: 46220 | B41: INGRESO (compra) | C41: =N(MOVIMIENTOS!$I71) -> 485 | F41: =TRIM(IF(MOVIMIENTOS!$G71<>"",MOVIMIENTOS!$G71&" ","")&IF(N(MOVIMIENTOS!$E71)>0,MOVIMIENTOS!$E71&" "&MOVIMIENTOS!$D71&" ","")&IF(MOVIMIENTOS!$H71<>"",MOVIMIENTOS!$H71,"")) -> 5 sacos peso aprox 95 kg/saco | G41: =N(G40)+N(C41)-N(E41) -> 3361
A42: 46220 | B42: CHANCHO (proceso) | D42: =N(MOVIMIENTOS!$I74) -> 97 | E42: =N(MOVIMIENTOS!$I74) -> 97 | F42: =TRIM(IF(MOVIMIENTOS!$G74<>"",MOVIMIENTOS!$G74&" ","")&IF(N(MOVIMIENTOS!$E74)>0,MOVIMIENTOS!$E74&" "&MOVIMIENTOS!$D74&" ","")&IF(MOVIMIENTOS!$H74<>"",MOVIMIENTOS!$H74,"")) -> 1 sacos | G42: =N(G41)+N(C42)-N(E42) -> 3264
A43: 46221 | B43: 📅 RESUMEN DEL DÍA | C43: =SUMPRODUCT((MOVIMIENTOS!$A$5:$A$400=DATE(2026,7,18))*(MOVIMIENTOS!$B$5:$B$400="COMPRA")*MOVIMIENTOS!$I$5:$I$400) -> 3201 | D43: =SUMPRODUCT((MOVIMIENTOS!$A$5:$A$400=DATE(2026,7,18))*(MOVIMIENTOS!$B$5:$B$400="PROCESO")*MOVIMIENTOS!$I$5:$I$400) -> 3295 | E43: =SUMPRODUCT((MOVIMIENTOS!$A$5:$A$400=DATE(2026,7,18))*((MOVIMIENTOS!$B$5:$B$400="ENVÍO A SUPESA")+(MOVIMIENTOS!$B$5:$B$400="ENVÍO A TOTTUS")+(MOVIMIENTOS!$B$5:$B$400="ENVIO A TOTTUS"))*MOVIMIENTOS!$I$5:$I$400) -> 3168 | F43: ="Selección: "&TEXT(SUMPRODUCT((MOVIMIENTOS!$A$5:$A$400=DATE(2026,7,18))*(MOVIMIENTOS!$B$5:$B$400="PROCESO")*(MOVIMIENTOS!$C$5:$C$400<>"Chancho")*MOVIMIENTOS!$I$5:$I$400),"#,##0")&" kg · Chancho: "&TEXT(SUMPRODUCT((MOVIMIENTOS!$A$5:$A$400=DATE(2026,7,18))*(MOVIMIENTOS!$B$5:$B$400="PROCESO")*(MOVIMIENTOS!$C$5:$C$400="Chancho")*MOVIMIENTOS!$I$5:$I$400),"#,##0")&" kg"&IF(C43>0," · "&TEXT(D43/C43,"0%")&" del ingreso","") -> Selección: 2,325 kg · Chancho: 970 kg · 103% del ingreso | G43: =N(G48) -> 2327
A44: 46221 | B44: ENVÍO A SUPESA | E44: =N(MOVIMIENTOS!$I75)+N(MOVIMIENTOS!$I76)+N(MOVIMIENTOS!$I77)+N(MOVIMIENTOS!$I78) -> 3168 | F44: Cal. A+C+M+P · 2996 | G44: =N(G42)+N(C44)-N(E44) -> 96
A45: 46221 | B45: SELECCIÓN (proceso) | D45: =SUMPRODUCT((MOVIMIENTOS!$A$5:$A$400=DATE(2026,7,18))*(MOVIMIENTOS!$B$5:$B$400="PROCESO")*(MOVIMIENTOS!$C$5:$C$400<>"Chancho")*MOVIMIENTOS!$I$5:$I$400) -> 2325 | F45: A=67j · P=11j · C=12j · M=54j | G45: =N(G44) -> 96
A46: 46221 | B46: CHANCHO (proceso) | D46: =N(MOVIMIENTOS!$I83) -> 970 | E46: =N(MOVIMIENTOS!$I83) -> 970 | F46: =TRIM(IF(MOVIMIENTOS!$G83<>"",MOVIMIENTOS!$G83&" ","")&IF(N(MOVIMIENTOS!$E83)>0,MOVIMIENTOS!$E83&" "&MOVIMIENTOS!$D83&" ","")&IF(MOVIMIENTOS!$H83<>"",MOVIMIENTOS!$H83,"")) -> 10 sacos | G46: =N(G45)+N(C46)-N(E46) -> -874
A47: 46221 | B47: TRASIEGO cal. A | F47: =MOVIMIENTOS!$E84&" jaba(s) movida(s) para completar otras · no resta del Stock Kg" -> 1 jaba(s) movida(s) para completar otras · no resta del Stock Kg | G47: =N(G46)+N(C47)-N(E47) -> -874
A48: 46221 | B48: INGRESO (compra) | C48: =N(MOVIMIENTOS!$I85) -> 3201 | F48: =TRIM(IF(MOVIMIENTOS!$G85<>"",MOVIMIENTOS!$G85&" ","")&IF(N(MOVIMIENTOS!$E85)>0,MOVIMIENTOS!$E85&" "&MOVIMIENTOS!$D85&" ","")&IF(MOVIMIENTOS!$H85<>"",MOVIMIENTOS!$H85,"")) -> 33 sacos Compra del sabado 18/07 (33 sacos) | G48: =N(G47)+N(C48)-N(E48) -> 2327
A49: 46222 | B49: 📅 RESUMEN DEL DÍA | C49: =SUMPRODUCT((MOVIMIENTOS!$A$5:$A$400=DATE(2026,7,19))*(MOVIMIENTOS!$B$5:$B$400="COMPRA")*MOVIMIENTOS!$I$5:$I$400) -> 1649 | D49: =SUMPRODUCT((MOVIMIENTOS!$A$5:$A$400=DATE(2026,7,19))*(MOVIMIENTOS!$B$5:$B$400="PROCESO")*MOVIMIENTOS!$I$5:$I$400) -> 1469 | E49: =SUMPRODUCT((MOVIMIENTOS!$A$5:$A$400=DATE(2026,7,19))*((MOVIMIENTOS!$B$5:$B$400="ENVÍO A SUPESA")+(MOVIMIENTOS!$B$5:$B$400="ENVÍO A TOTTUS")+(MOVIMIENTOS!$B$5:$B$400="ENVIO A TOTTUS"))*MOVIMIENTOS!$I$5:$I$400) -> 1883 | F49: ="Selección: "&TEXT(SUMPRODUCT((MOVIMIENTOS!$A$5:$A$400=DATE(2026,7,19))*(MOVIMIENTOS!$B$5:$B$400="PROCESO")*(MOVIMIENTOS!$C$5:$C$400<>"Chancho")*MOVIMIENTOS!$I$5:$I$400),"#,##0")&" kg · Chancho: "&TEXT(SUMPRODUCT((MOVIMIENTOS!$A$5:$A$400=DATE(2026,7,19))*(MOVIMIENTOS!$B$5:$B$400="PROCESO")*(MOVIMIENTOS!$C$5:$C$400="Chancho")*MOVIMIENTOS!$I$5:$I$400),"#,##0")&" kg"&IF(C49>0," · "&TEXT(D49/C49,"0%")&" del ingreso","") -> Selección: 1,178 kg · Chancho: 291 kg · 89% del ingreso | G49: =N(G53) -> 1802
A50: 46222 | B50: SELECCIÓN (proceso) | D50: =SUMPRODUCT((MOVIMIENTOS!$A$5:$A$400=DATE(2026,7,19))*(MOVIMIENTOS!$B$5:$B$400="PROCESO")*(MOVIMIENTOS!$C$5:$C$400<>"Chancho")*MOVIMIENTOS!$I$5:$I$400) -> 1178 | F50: A=40j · P=0j · C=0j · M=34j | G50: =N(G48) -> 2327
A51: 46222 | B51: CHANCHO (proceso) | D51: =N(MOVIMIENTOS!$I90) -> 291 | E51: =N(MOVIMIENTOS!$I90) -> 291 | F51: =TRIM(IF(MOVIMIENTOS!$G90<>"",MOVIMIENTOS!$G90&" ","")&IF(N(MOVIMIENTOS!$E90)>0,MOVIMIENTOS!$E90&" "&MOVIMIENTOS!$D90&" ","")&IF(MOVIMIENTOS!$H90<>"",MOVIMIENTOS!$H90,"")) -> 3 sacos | G51: =N(G50)+N(C51)-N(E51) -> 2036
A52: 46222 | B52: ENVÍO A SUPESA | E52: =N(MOVIMIENTOS!$I91)+N(MOVIMIENTOS!$I92)+N(MOVIMIENTOS!$I93)+N(MOVIMIENTOS!$I94) -> 1883 | F52: Cal. A+C+M+P · 2998 | G52: =N(G51)+N(C52)-N(E52) -> 153
A53: 46222 | B53: INGRESO (compra) | C53: =N(MOVIMIENTOS!$I95) -> 1649 | F53: =TRIM(IF(MOVIMIENTOS!$G95<>"",MOVIMIENTOS!$G95&" ","")&IF(N(MOVIMIENTOS!$E95)>0,MOVIMIENTOS!$E95&" "&MOVIMIENTOS!$D95&" ","")&IF(MOVIMIENTOS!$H95<>"",MOVIMIENTOS!$H95,"")) -> 17 sacos Compra del domingo 19/07 (17 sacos) | G53: =N(G52)+N(C53)-N(E53) -> 1802
A54: 46223 | B54: 📅 RESUMEN DEL DÍA | C54: =SUMPRODUCT((MOVIMIENTOS!$A$5:$A$400=DATE(2026,7,20))*(MOVIMIENTOS!$B$5:$B$400="COMPRA")*MOVIMIENTOS!$I$5:$I$400) -> 6790 | D54: =SUMPRODUCT((MOVIMIENTOS!$A$5:$A$400=DATE(2026,7,20))*(MOVIMIENTOS!$B$5:$B$400="PROCESO")*MOVIMIENTOS!$I$5:$I$400) -> 4648.5 | E54: =SUMPRODUCT((MOVIMIENTOS!$A$5:$A$400=DATE(2026,7,20))*((MOVIMIENTOS!$B$5:$B$400="ENVÍO A SUPESA")+(MOVIMIENTOS!$B$5:$B$400="ENVÍO A TOTTUS")+(MOVIMIENTOS!$B$5:$B$400="ENVIO A TOTTUS"))*MOVIMIENTOS!$I$5:$I$400) -> 3294 | F54: ="Selección: "&TEXT(SUMPRODUCT((MOVIMIENTOS!$A$5:$A$400=DATE(2026,7,20))*(MOVIMIENTOS!$B$5:$B$400="PROCESO")*(MOVIMIENTOS!$C$5:$C$400<>"Chancho")*MOVIMIENTOS!$I$5:$I$400),"#,##0")&" kg · Chancho: "&TEXT(SUMPRODUCT((MOVIMIENTOS!$A$5:$A$400=DATE(2026,7,20))*(MOVIMIENTOS!$B$5:$B$400="PROCESO")*(MOVIMIENTOS!$C$5:$C$400="Chancho")*MOVIMIENTOS!$I$5:$I$400),"#,##0")&" kg"&IF(C54>0," · "&TEXT(D54/C54,"0%")&" del ingreso","") -> Selección: 4,018 kg · Chancho: 631 kg · 68% del ingreso | G54: =N(G62) -> 4667.5
A55: 46223 | B55: INGRESO (compra) | C55: =N(MOVIMIENTOS!$I96) -> 4656 | F55: =TRIM(IF(MOVIMIENTOS!$G96<>"",MOVIMIENTOS!$G96&" ","")&IF(N(MOVIMIENTOS!$E96)>0,MOVIMIENTOS!$E96&" "&MOVIMIENTOS!$D96&" ","")&IF(MOVIMIENTOS!$H96<>"",MOVIMIENTOS!$H96,"")) -> 48 sacos TOTAL 70 SACOS, LUNES PROCESO 48 | G55: =N(G53)+N(C55)-N(E55) -> 6458
A56: 46223 | B56: SELECCIÓN (proceso) | D56: =SUMPRODUCT((MOVIMIENTOS!$A$5:$A$400=DATE(2026,7,20))*(MOVIMIENTOS!$B$5:$B$400="PROCESO")*(MOVIMIENTOS!$C$5:$C$400<>"Chancho")*MOVIMIENTOS!$I$5:$I$400) -> 4018 | F56: A=68j · P=23j · C=23j · M=129j | G56: =N(G55) -> 6458
A57: 46223 | B57: CHANCHO (proceso) | D57: =N(MOVIMIENTOS!$I101) -> 630.5 | E57: =N(MOVIMIENTOS!$I101) -> 630.5 | F57: =TRIM(IF(MOVIMIENTOS!$G101<>"",MOVIMIENTOS!$G101&" ","")&IF(N(MOVIMIENTOS!$E101)>0,MOVIMIENTOS!$E101&" "&MOVIMIENTOS!$D101&" ","")&IF(MOVIMIENTOS!$H101<>"",MOVIMIENTOS!$H101,"")) -> 6.5 sacos | G57: =N(G56)+N(C57)-N(E57) -> 5827.5
A58: 46223 | B58: ENVÍO A SUPESA | E58: =N(MOVIMIENTOS!$I102)+N(MOVIMIENTOS!$I103)+N(MOVIMIENTOS!$I104)+N(MOVIMIENTOS!$I105) -> 3294 | F58: Cal. A+C+M+P · 3001 | G58: =N(G57)+N(C58)-N(E58) -> 2533.5
A59: 46223 | B59: VENTA CHANCHO | F59: =TRIM(IF(MOVIMIENTOS!$G106<>"",MOVIMIENTOS!$G106&" ","")&IF(N(MOVIMIENTOS!$E106)>0,MOVIMIENTOS!$E106&" "&MOVIMIENTOS!$D106&" ","")&IF(MOVIMIENTOS!$H106<>"",MOVIMIENTOS!$H106,"")) -> TCK002-726 18 sacos | G59: =N(G58)+N(C59)-N(E59) -> 2533.5
A60: 46223 | B60: INGRESO (compra) | C60: =N(MOVIMIENTOS!$I107) -> 2134 | F60: =TRIM(IF(MOVIMIENTOS!$G107<>"",MOVIMIENTOS!$G107&" ","")&IF(N(MOVIMIENTOS!$E107)>0,MOVIMIENTOS!$E107&" "&MOVIMIENTOS!$D107&" ","")&IF(MOVIMIENTOS!$H107<>"",MOVIMIENTOS!$H107,"")) -> 22 sacos peso aprox 95 kg/saco | G60: =N(G59)+N(C60)-N(E60) -> 4667.5
A61: 46223 | B61: TRASIEGO cal. P | F61: =MOVIMIENTOS!$E108&" jaba(s) movida(s) para completar otras · no resta del Stock Kg" -> 1 jaba(s) movida(s) para completar otras · no resta del Stock Kg | G61: =N(G60)+N(C61)-N(E61) -> 4667.5
A62: 46223 | B62: TRASIEGO cal. C | F62: =MOVIMIENTOS!$E109&" jaba(s) movida(s) para completar otras · no resta del Stock Kg" -> 1 jaba(s) movida(s) para completar otras · no resta del Stock Kg | G62: =N(G61)+N(C62)-N(E62) -> 4667.5
A63: 46224 | B63: 📅 RESUMEN DEL DÍA | C63: =SUMPRODUCT((MOVIMIENTOS!$A$5:$A$400=DATE(2026,7,21))*(MOVIMIENTOS!$B$5:$B$400="COMPRA")*MOVIMIENTOS!$I$5:$I$400) -> 6790 | D63: =SUMPRODUCT((MOVIMIENTOS!$A$5:$A$400=DATE(2026,7,21))*(MOVIMIENTOS!$B$5:$B$400="PROCESO")*MOVIMIENTOS!$I$5:$I$400) -> 4879 | E63: =SUMPRODUCT((MOVIMIENTOS!$A$5:$A$400=DATE(2026,7,21))*((MOVIMIENTOS!$B$5:$B$400="ENVÍO A SUPESA")+(MOVIMIENTOS!$B$5:$B$400="ENVÍO A TOTTUS")+(MOVIMIENTOS!$B$5:$B$400="ENVIO A TOTTUS"))*MOVIMIENTOS!$I$5:$I$400) -> 3260 | F63: ="Selección: "&TEXT(SUMPRODUCT((MOVIMIENTOS!$A$5:$A$400=DATE(2026,7,21))*(MOVIMIENTOS!$B$5:$B$400="PROCESO")*(MOVIMIENTOS!$C$5:$C$400<>"Chancho")*MOVIMIENTOS!$I$5:$I$400),"#,##0")&" kg · Chancho: "&TEXT(SUMPRODUCT((MOVIMIENTOS!$A$5:$A$400=DATE(2026,7,21))*(MOVIMIENTOS!$B$5:$B$400="PROCESO")*(MOVIMIENTOS!$C$5:$C$400="Chancho")*MOVIMIENTOS!$I$5:$I$400),"#,##0")&" kg"&IF(C63>0," · "&TEXT(D63/C63,"0%")&" del ingreso","") -> Selección: 4,200 kg · Chancho: 679 kg · 72% del ingreso | G63: =N(G73) -> 7535.5
A64: 46224 | B64: SELECCIÓN (proceso) | D64: =SUMPRODUCT((MOVIMIENTOS!$A$5:$A$400=DATE(2026,7,21))*(MOVIMIENTOS!$B$5:$B$400="PROCESO")*(MOVIMIENTOS!$C$5:$C$400<>"Chancho")*MOVIMIENTOS!$I$5:$I$400) -> 4200 | F64: A=90j · P=11j · C=12j · M=144j | G64: =N(G62) -> 4667.5
A65: 46224 | B65: CHANCHO (proceso) | D65: =N(MOVIMIENTOS!$I112) -> 291 | E65: =N(MOVIMIENTOS!$I112) -> 291 | F65: =TRIM(IF(MOVIMIENTOS!$G112<>"",MOVIMIENTOS!$G112&" ","")&IF(N(MOVIMIENTOS!$E112)>0,MOVIMIENTOS!$E112&" "&MOVIMIENTOS!$D112&" ","")&IF(MOVIMIENTOS!$H112<>"",MOVIMIENTOS!$H112,"")) -> 3 sacos | G65: =N(G64)+N(C65)-N(E65) -> 4376.5
A66: 46224 | B66: INGRESO (compra) | C66: =N(MOVIMIENTOS!$I113) -> 6790 | F66: =TRIM(IF(MOVIMIENTOS!$G113<>"",MOVIMIENTOS!$G113&" ","")&IF(N(MOVIMIENTOS!$E113)>0,MOVIMIENTOS!$E113&" "&MOVIMIENTOS!$D113&" ","")&IF(MOVIMIENTOS!$H113<>"",MOVIMIENTOS!$H113,"")) -> 70 sacos peso aprox 95 kg/saco | G66: =N(G65)+N(C66)-N(E66) -> 11166.5
A67: 46224 | B67: CHANCHO (proceso) | D67: =N(MOVIMIENTOS!$I118) -> 388 | E67: =N(MOVIMIENTOS!$I118) -> 388 | F67: =TRIM(IF(MOVIMIENTOS!$G118<>"",MOVIMIENTOS!$G118&" ","")&IF(N(MOVIMIENTOS!$E118)>0,MOVIMIENTOS!$E118&" "&MOVIMIENTOS!$D118&" ","")&IF(MOVIMIENTOS!$H118<>"",MOVIMIENTOS!$H118,"")) -> 4 sacos | G67: =N(G66)+N(C67)-N(E67) -> 10778.5
A68: 46224 | B68: ENVÍO A SUPESA | E68: =N(MOVIMIENTOS!$I119)+N(MOVIMIENTOS!$I120)+N(MOVIMIENTOS!$I121)+N(MOVIMIENTOS!$I122) -> 3260 | F68: Cal. A+C+M+P · 3004 | G68: =N(G67)+N(C68)-N(E68) -> 7518.5
A69: 46224 | B69: RECHAZO cal. A (va a reproceso) | F69: =MOVIMIENTOS!$E123&" jabas rechazadas · van a reproceso (merma del día: "&TEXT(SUMPRODUCT((MOVIMIENTOS!$A$5:$A$400=MOVIMIENTOS!$A123)*(MOVIMIENTOS!$B$5:$B$400="RECHAZO")*(MOVIMIENTOS!$D$5:$D$400="jabas")*MOVIMIENTOS!$E$5:$E$400*IFERROR(_xlfn.SWITCH(MOVIMIENTOS!$C$5:$C$400,"A",15,"P",18,"C",17,"M",17,0),0))-SUMPRODUCT((MOVIMIENTOS!$A$5:$A$400=MOVIMIENTOS!$A123)*(MOVIMIENTOS!$B$5:$B$400="REPROCESO")*MOVIMIENTOS!$I$5:$I$400),"+#,##0;-#,##0;0")&" kg)" -> 1 jabas rechazadas · van a reproceso (merma del día: +15 kg) | G69: =N(G68)+N(C69)-N(E69) -> 7518.5
A70: 46224 | B70: RECHAZO cal. M (va a reproceso) | F70: =MOVIMIENTOS!$E124&" jabas rechazadas · van a reproceso (merma del día: "&TEXT(SUMPRODUCT((MOVIMIENTOS!$A$5:$A$400=MOVIMIENTOS!$A124)*(MOVIMIENTOS!$B$5:$B$400="RECHAZO")*(MOVIMIENTOS!$D$5:$D$400="jabas")*MOVIMIENTOS!$E$5:$E$400*IFERROR(_xlfn.SWITCH(MOVIMIENTOS!$C$5:$C$400,"A",15,"P",18,"C",17,"M",17,0),0))-SUMPRODUCT((MOVIMIENTOS!$A$5:$A$400=MOVIMIENTOS!$A124)*(MOVIMIENTOS!$B$5:$B$400="REPROCESO")*MOVIMIENTOS!$I$5:$I$400),"+#,##0;-#,##0;0")&" kg)" -> 1 jabas rechazadas · van a reproceso (merma del día: +15 kg) | G70: =N(G69)+N(C70)-N(E70) -> 7518.5
A71: 46224 | B71: TRASIEGO cal. A | F71: =MOVIMIENTOS!$E125&" jaba(s) movida(s) para completar otras · no resta del Stock Kg" -> 1 jaba(s) movida(s) para completar otras · no resta del Stock Kg | G71: =N(G70)+N(C71)-N(E71) -> 7518.5
A72: 46224 | B72: TRASIEGO cal. M | F72: =MOVIMIENTOS!$E126&" jaba(s) movida(s) para completar otras · no resta del Stock Kg" -> 1 jaba(s) movida(s) para completar otras · no resta del Stock Kg | G72: =N(G71)+N(C72)-N(E72) -> 7518.5
A73: 46224 | B73: REPROCESO | C73: =N(MOVIMIENTOS!$I127) -> 17 | F73: =MOVIMIENTOS!$E127&" kg recuperados (merma del día: "&TEXT(SUMPRODUCT((MOVIMIENTOS!$A$5:$A$400=MOVIMIENTOS!$A127)*(MOVIMIENTOS!$B$5:$B$400="RECHAZO")*(MOVIMIENTOS!$D$5:$D$400="jabas")*MOVIMIENTOS!$E$5:$E$400*IFERROR(_xlfn.SWITCH(MOVIMIENTOS!$C$5:$C$400,"A",15,"P",18,"C",17,"M",17,0),0))-SUMPRODUCT((MOVIMIENTOS!$A$5:$A$400=MOVIMIENTOS!$A127)*(MOVIMIENTOS!$B$5:$B$400="REPROCESO")*MOVIMIENTOS!$I$5:$I$400),"+#,##0;-#,##0;0")&" kg)" -> 17 kg recuperados (merma del día: +15 kg) | G73: =N(G72)+N(C73)-N(E73) -> 7535.5
A74: 46225 | B74: 📅 RESUMEN DEL DÍA | C74: =SUMPRODUCT((MOVIMIENTOS!$A$5:$A$400=DATE(2026,7,22))*(MOVIMIENTOS!$B$5:$B$400="COMPRA")*MOVIMIENTOS!$I$5:$I$400) -> 3880 | D74: =SUMPRODUCT((MOVIMIENTOS!$A$5:$A$400=DATE(2026,7,22))*(MOVIMIENTOS!$B$5:$B$400="PROCESO")*MOVIMIENTOS!$I$5:$I$400) -> 4025 | E74: =SUMPRODUCT((MOVIMIENTOS!$A$5:$A$400=DATE(2026,7,22))*((MOVIMIENTOS!$B$5:$B$400="ENVÍO A SUPESA")+(MOVIMIENTOS!$B$5:$B$400="ENVÍO A TOTTUS")+(MOVIMIENTOS!$B$5:$B$400="ENVIO A TOTTUS"))*MOVIMIENTOS!$I$5:$I$400) -> 3294 | F74: ="Selección: "&TEXT(SUMPRODUCT((MOVIMIENTOS!$A$5:$A$400=DATE(2026,7,22))*(MOVIMIENTOS!$B$5:$B$400="PROCESO")*(MOVIMIENTOS!$C$5:$C$400<>"Chancho")*MOVIMIENTOS!$I$5:$I$400),"#,##0")&" kg · Chancho: "&TEXT(SUMPRODUCT((MOVIMIENTOS!$A$5:$A$400=DATE(2026,7,22))*(MOVIMIENTOS!$B$5:$B$400="PROCESO")*(MOVIMIENTOS!$C$5:$C$400="Chancho")*MOVIMIENTOS!$I$5:$I$400),"#,##0")&" kg"&IF(C74>0," · "&TEXT(D74/C74,"0%")&" del ingreso","") -> Selección: 3,249 kg · Chancho: 776 kg · 104% del ingreso | G74: =N(G84) -> 7457.5
A75: 46225 | B75: SELECCIÓN (proceso) | D75: =SUMPRODUCT((MOVIMIENTOS!$A$5:$A$400=DATE(2026,7,22))*(MOVIMIENTOS!$B$5:$B$400="PROCESO")*(MOVIMIENTOS!$C$5:$C$400<>"Chancho")*MOVIMIENTOS!$I$5:$I$400) -> 3249 | F75: A=64j · P=11j · C=12j · M=111j | G75: =N(G73) -> 7535.5
A76: 46225 | B76: CHANCHO (proceso) | D76: =N(MOVIMIENTOS!$I132) -> 776 | E76: =N(MOVIMIENTOS!$I132) -> 776 | F76: =TRIM(IF(MOVIMIENTOS!$G132<>"",MOVIMIENTOS!$G132&" ","")&IF(N(MOVIMIENTOS!$E132)>0,MOVIMIENTOS!$E132&" "&MOVIMIENTOS!$D132&" ","")&IF(MOVIMIENTOS!$H132<>"",MOVIMIENTOS!$H132,"")) -> 8 sacos | G76: =N(G75)+N(C76)-N(E76) -> 6759.5
A77: 46225 | B77: MALOGRADO | E77: =N(MOVIMIENTOS!$I133) -> 50 | F77: =TRIM(IF(MOVIMIENTOS!$G133<>"",MOVIMIENTOS!$G133&" ","")&IF(N(MOVIMIENTOS!$E133)>0,MOVIMIENTOS!$E133&" "&MOVIMIENTOS!$D133&" ","")&IF(MOVIMIENTOS!$H133<>"",MOVIMIENTOS!$H133,"")) -> 50 kg | G77: =N(G76)+N(C77)-N(E77) -> 6709.5
A78: 46225 | B78: ENVÍO A SUPESA | E78: =N(MOVIMIENTOS!$I134)+N(MOVIMIENTOS!$I135)+N(MOVIMIENTOS!$I136)+N(MOVIMIENTOS!$I137) -> 3294 | F78: Cal. A+C+M+P · 3006 | G78: =N(G77)+N(C78)-N(E78) -> 3415.5
A79: 46225 | B79: VENTA CHANCHO | F79: =TRIM(IF(MOVIMIENTOS!$G138<>"",MOVIMIENTOS!$G138&" ","")&IF(N(MOVIMIENTOS!$E138)>0,MOVIMIENTOS!$E138&" "&MOVIMIENTOS!$D138&" ","")&IF(MOVIMIENTOS!$H138<>"",MOVIMIENTOS!$H138,"")) -> S/T 10 sacos | G79: =N(G78)+N(C79)-N(E79) -> 3415.5
A80: 46225 | B80: RECHAZO cal. A (va a reproceso) | F80: =MOVIMIENTOS!$E139&" jabas rechazadas · van a reproceso (merma del día: "&TEXT(SUMPRODUCT((MOVIMIENTOS!$A$5:$A$400=MOVIMIENTOS!$A139)*(MOVIMIENTOS!$B$5:$B$400="RECHAZO")*(MOVIMIENTOS!$D$5:$D$400="jabas")*MOVIMIENTOS!$E$5:$E$400*IFERROR(_xlfn.SWITCH(MOVIMIENTOS!$C$5:$C$400,"A",15,"P",18,"C",17,"M",17,0),0))-SUMPRODUCT((MOVIMIENTOS!$A$5:$A$400=MOVIMIENTOS!$A139)*(MOVIMIENTOS!$B$5:$B$400="REPROCESO")*MOVIMIENTOS!$I$5:$I$400),"+#,##0;-#,##0;0")&" kg)" -> 1 jabas rechazadas · van a reproceso (merma del día: +6 kg) | G80: =N(G79)+N(C80)-N(E80) -> 3415.5
A81: 46225 | B81: DEVOLUCIÓN (regresa intacta) | C81: =N(MOVIMIENTOS!$I140) -> 153 | G81: =N(G80)+N(C81)-N(E81) -> 3568.5
A82: 46225 | B82: TRASIEGO cal. A | F82: =MOVIMIENTOS!$E141&" jaba(s) movida(s) para completar otras · no resta del Stock Kg" -> 1 jaba(s) movida(s) para completar otras · no resta del Stock Kg | G82: =N(G81)+N(C82)-N(E82) -> 3568.5
A83: 46225 | B83: REPROCESO | C83: =N(MOVIMIENTOS!$I142) -> 9 | F83: =MOVIMIENTOS!$E142&" kg recuperados (merma del día: "&TEXT(SUMPRODUCT((MOVIMIENTOS!$A$5:$A$400=MOVIMIENTOS!$A142)*(MOVIMIENTOS!$B$5:$B$400="RECHAZO")*(MOVIMIENTOS!$D$5:$D$400="jabas")*MOVIMIENTOS!$E$5:$E$400*IFERROR(_xlfn.SWITCH(MOVIMIENTOS!$C$5:$C$400,"A",15,"P",18,"C",17,"M",17,0),0))-SUMPRODUCT((MOVIMIENTOS!$A$5:$A$400=MOVIMIENTOS!$A142)*(MOVIMIENTOS!$B$5:$B$400="REPROCESO")*MOVIMIENTOS!$I$5:$I$400),"+#,##0;-#,##0;0")&" kg)" -> 9 kg recuperados (merma del día: +6 kg) | G83: =N(G82)+N(C83)-N(E83) -> 3577.5
A84: 46225 | B84: INGRESO (compra) | C84: =N(MOVIMIENTOS!$I143) -> 3880 | F84: =TRIM(IF(MOVIMIENTOS!$G143<>"",MOVIMIENTOS!$G143&" ","")&IF(N(MOVIMIENTOS!$E143)>0,MOVIMIENTOS!$E143&" "&MOVIMIENTOS!$D143&" ","")&IF(MOVIMIENTOS!$H143<>"",MOVIMIENTOS!$H143,"")) -> 40 sacos peso aprox 95 kg/saco | G84: =N(G83)+N(C84)-N(E84) -> 7457.5
A85: 46226 | B85: 📅 RESUMEN DEL DÍA | C85: =SUMPRODUCT((MOVIMIENTOS!$A$5:$A$400=DATE(2026,7,23))*(MOVIMIENTOS!$B$5:$B$400="COMPRA")*MOVIMIENTOS!$I$5:$I$400) -> 7760 | D85: =SUMPRODUCT((MOVIMIENTOS!$A$5:$A$400=DATE(2026,7,23))*(MOVIMIENTOS!$B$5:$B$400="PROCESO")*MOVIMIENTOS!$I$5:$I$400) -> 3800.5 | E85: =SUMPRODUCT((MOVIMIENTOS!$A$5:$A$400=DATE(2026,7,23))*((MOVIMIENTOS!$B$5:$B$400="ENVÍO A SUPESA")+(MOVIMIENTOS!$B$5:$B$400="ENVÍO A TOTTUS")+(MOVIMIENTOS!$B$5:$B$400="ENVIO A TOTTUS"))*MOVIMIENTOS!$I$5:$I$400) -> 3413 | F85: ="Selección: "&TEXT(SUMPRODUCT((MOVIMIENTOS!$A$5:$A$400=DATE(2026,7,23))*(MOVIMIENTOS!$B$5:$B$400="PROCESO")*(MOVIMIENTOS!$C$5:$C$400<>"Chancho")*MOVIMIENTOS!$I$5:$I$400),"#,##0")&" kg · Chancho: "&TEXT(SUMPRODUCT((MOVIMIENTOS!$A$5:$A$400=DATE(2026,7,23))*(MOVIMIENTOS!$B$5:$B$400="PROCESO")*(MOVIMIENTOS!$C$5:$C$400="Chancho")*MOVIMIENTOS!$I$5:$I$400),"#,##0")&" kg"&IF(C85>0," · "&TEXT(D85/C85,"0%")&" del ingreso","") -> Selección: 3,170 kg · Chancho: 631 kg · 49% del ingreso | G85: =N(G90) -> 11174
A86: 46226 | B86: SELECCIÓN (proceso) | D86: =SUMPRODUCT((MOVIMIENTOS!$A$5:$A$400=DATE(2026,7,23))*(MOVIMIENTOS!$B$5:$B$400="PROCESO")*(MOVIMIENTOS!$C$5:$C$400<>"Chancho")*MOVIMIENTOS!$I$5:$I$400) -> 3170 | F86: A=78j · P=11j · C=12j · M=94j | G86: =N(G84) -> 7457.5
A87: 46226 | B87: CHANCHO (proceso) | D87: =N(MOVIMIENTOS!$I148) -> 630.5 | E87: =N(MOVIMIENTOS!$I148) -> 630.5 | F87: =TRIM(IF(MOVIMIENTOS!$G148<>"",MOVIMIENTOS!$G148&" ","")&IF(N(MOVIMIENTOS!$E148)>0,MOVIMIENTOS!$E148&" "&MOVIMIENTOS!$D148&" ","")&IF(MOVIMIENTOS!$H148<>"",MOVIMIENTOS!$H148,"")) -> 6.5 sacos | G87: =N(G86)+N(C87)-N(E87) -> 6827
A88: 46226 | B88: ENVÍO A SUPESA | E88: =N(MOVIMIENTOS!$I149)+N(MOVIMIENTOS!$I150)+N(MOVIMIENTOS!$I151)+N(MOVIMIENTOS!$I152) -> 3413 | F88: Cal. A+C+M+P · 3008 | G88: =N(G87)+N(C88)-N(E88) -> 3414
A89: 46226 | B89: INGRESO (compra) | C89: =N(MOVIMIENTOS!$I153) -> 4171 | F89: =TRIM(IF(MOVIMIENTOS!$G153<>"",MOVIMIENTOS!$G153&" ","")&IF(N(MOVIMIENTOS!$E153)>0,MOVIMIENTOS!$E153&" "&MOVIMIENTOS!$D153&" ","")&IF(MOVIMIENTOS!$H153<>"",MOVIMIENTOS!$H153,"")) -> 43 sacos EN TOTAL SE COMPRARON 80 SACOS, 43 PROCESARON 24-07 Y 37 PROCESARAN SABADO 25 | G89: =N(G88)+N(C89)-N(E89) -> 7585
A90: 46226 | B90: INGRESO (compra) | C90: =N(MOVIMIENTOS!$I154) -> 3589 | F90: =TRIM(IF(MOVIMIENTOS!$G154<>"",MOVIMIENTOS!$G154&" ","")&IF(N(MOVIMIENTOS!$E154)>0,MOVIMIENTOS!$E154&" "&MOVIMIENTOS!$D154&" ","")&IF(MOVIMIENTOS!$H154<>"",MOVIMIENTOS!$H154,"")) -> 37 sacos peso aprox 95 kg/saco | G90: =N(G89)+N(C90)-N(E90) -> 11174
A91: 46227 | B91: 📅 RESUMEN DEL DÍA | C91: =SUMPRODUCT((MOVIMIENTOS!$A$5:$A$400=DATE(2026,7,24))*(MOVIMIENTOS!$B$5:$B$400="COMPRA")*MOVIMIENTOS!$I$5:$I$400) -> 0 | D91: =SUMPRODUCT((MOVIMIENTOS!$A$5:$A$400=DATE(2026,7,24))*(MOVIMIENTOS!$B$5:$B$400="PROCESO")*MOVIMIENTOS!$I$5:$I$400) -> 3056 | E91: =SUMPRODUCT((MOVIMIENTOS!$A$5:$A$400=DATE(2026,7,24))*((MOVIMIENTOS!$B$5:$B$400="ENVÍO A SUPESA")+(MOVIMIENTOS!$B$5:$B$400="ENVÍO A TOTTUS")+(MOVIMIENTOS!$B$5:$B$400="ENVIO A TOTTUS"))*MOVIMIENTOS!$I$5:$I$400) -> 3461 | F91: ="Selección: "&TEXT(SUMPRODUCT((MOVIMIENTOS!$A$5:$A$400=DATE(2026,7,24))*(MOVIMIENTOS!$B$5:$B$400="PROCESO")*(MOVIMIENTOS!$C$5:$C$400<>"Chancho")*MOVIMIENTOS!$I$5:$I$400),"#,##0")&" kg · Chancho: "&TEXT(SUMPRODUCT((MOVIMIENTOS!$A$5:$A$400=DATE(2026,7,24))*(MOVIMIENTOS!$B$5:$B$400="PROCESO")*(MOVIMIENTOS!$C$5:$C$400="Chancho")*MOVIMIENTOS!$I$5:$I$400),"#,##0")&" kg"&IF(C91>0," · "&TEXT(D91/C91,"0%")&" del ingreso","") -> Selección: 2,474 kg · Chancho: 582 kg | G91: =N(G101) -> 7152
A92: 46227 | B92: SELECCIÓN (proceso) | D92: =SUMPRODUCT((MOVIMIENTOS!$A$5:$A$400=DATE(2026,7,24))*(MOVIMIENTOS!$B$5:$B$400="PROCESO")*(MOVIMIENTOS!$C$5:$C$400<>"Chancho")*MOVIMIENTOS!$I$5:$I$400) -> 2474 | F92: A=48j · P=3j · C=5j · M=95j | G92: =N(G90) -> 11174
A93: 46227 | B93: CHANCHO (proceso) | D93: =N(MOVIMIENTOS!$I159) -> 582 | E93: =N(MOVIMIENTOS!$I159) -> 582 | F93: =TRIM(IF(MOVIMIENTOS!$G159<>"",MOVIMIENTOS!$G159&" ","")&IF(N(MOVIMIENTOS!$E159)>0,MOVIMIENTOS!$E159&" "&MOVIMIENTOS!$D159&" ","")&IF(MOVIMIENTOS!$H159<>"",MOVIMIENTOS!$H159,"")) -> 6 sacos | G93: =N(G92)+N(C93)-N(E93) -> 10592
A94: 46227 | B94: ENVÍO A SUPESA | E94: =N(MOVIMIENTOS!$I160)+N(MOVIMIENTOS!$I161)+N(MOVIMIENTOS!$I162)+N(MOVIMIENTOS!$I163) -> 3413 | F94: Cal. A+C+M+P · 3011 | G94: =N(G93)+N(C94)-N(E94) -> 7179
A95: 46227 | B95: RECHAZO cal. A (va a reproceso) | F95: =MOVIMIENTOS!$E164&" jabas rechazadas · van a reproceso (merma del día: "&TEXT(SUMPRODUCT((MOVIMIENTOS!$A$5:$A$400=MOVIMIENTOS!$A164)*(MOVIMIENTOS!$B$5:$B$400="RECHAZO")*(MOVIMIENTOS!$D$5:$D$400="jabas")*MOVIMIENTOS!$E$5:$E$400*IFERROR(_xlfn.SWITCH(MOVIMIENTOS!$C$5:$C$400,"A",15,"P",18,"C",17,"M",17,0),0))-SUMPRODUCT((MOVIMIENTOS!$A$5:$A$400=MOVIMIENTOS!$A164)*(MOVIMIENTOS!$B$5:$B$400="REPROCESO")*MOVIMIENTOS!$I$5:$I$400),"+#,##0;-#,##0;0")&" kg)" -> 1 jabas rechazadas · van a reproceso (merma del día: +11 kg) | G95: =N(G94)+N(C95)-N(E95) -> 7179
A96: 46227 | B96: REPROCESO | C96: =N(MOVIMIENTOS!$I165) -> 11 | F96: =MOVIMIENTOS!$E165&" kg recuperados (merma del día: "&TEXT(SUMPRODUCT((MOVIMIENTOS!$A$5:$A$400=MOVIMIENTOS!$A165)*(MOVIMIENTOS!$B$5:$B$400="RECHAZO")*(MOVIMIENTOS!$D$5:$D$400="jabas")*MOVIMIENTOS!$E$5:$E$400*IFERROR(_xlfn.SWITCH(MOVIMIENTOS!$C$5:$C$400,"A",15,"P",18,"C",17,"M",17,0),0))-SUMPRODUCT((MOVIMIENTOS!$A$5:$A$400=MOVIMIENTOS!$A165)*(MOVIMIENTOS!$B$5:$B$400="REPROCESO")*MOVIMIENTOS!$I$5:$I$400),"+#,##0;-#,##0;0")&" kg)" -> 11 kg recuperados (merma del día: +11 kg) | G96: =N(G95)+N(C96)-N(E96) -> 7190
A97: 46227 | B97: RECHAZO cal. M (va a reproceso) | F97: =MOVIMIENTOS!$E166&" jabas rechazadas · van a reproceso (merma del día: "&TEXT(SUMPRODUCT((MOVIMIENTOS!$A$5:$A$400=MOVIMIENTOS!$A166)*(MOVIMIENTOS!$B$5:$B$400="RECHAZO")*(MOVIMIENTOS!$D$5:$D$400="jabas")*MOVIMIENTOS!$E$5:$E$400*IFERROR(_xlfn.SWITCH(MOVIMIENTOS!$C$5:$C$400,"A",15,"P",18,"C",17,"M",17,0),0))-SUMPRODUCT((MOVIMIENTOS!$A$5:$A$400=MOVIMIENTOS!$A166)*(MOVIMIENTOS!$B$5:$B$400="REPROCESO")*MOVIMIENTOS!$I$5:$I$400),"+#,##0;-#,##0;0")&" kg)" -> 1 jabas rechazadas · van a reproceso (merma del día: +11 kg) | G97: =N(G96)+N(C97)-N(E97) -> 7190
A98: 46227 | B98: REPROCESO | C98: =N(MOVIMIENTOS!$I167) -> 10 | F98: =MOVIMIENTOS!$E167&" kg recuperados (merma del día: "&TEXT(SUMPRODUCT((MOVIMIENTOS!$A$5:$A$400=MOVIMIENTOS!$A167)*(MOVIMIENTOS!$B$5:$B$400="RECHAZO")*(MOVIMIENTOS!$D$5:$D$400="jabas")*MOVIMIENTOS!$E$5:$E$400*IFERROR(_xlfn.SWITCH(MOVIMIENTOS!$C$5:$C$400,"A",15,"P",18,"C",17,"M",17,0),0))-SUMPRODUCT((MOVIMIENTOS!$A$5:$A$400=MOVIMIENTOS!$A167)*(MOVIMIENTOS!$B$5:$B$400="REPROCESO")*MOVIMIENTOS!$I$5:$I$400),"+#,##0;-#,##0;0")&" kg)" -> 10 kg recuperados (merma del día: +11 kg) | G98: =N(G97)+N(C98)-N(E98) -> 7200
A99: 46227 | B99: VENTA CHANCHO | F99: =TRIM(IF(MOVIMIENTOS!$G168<>"",MOVIMIENTOS!$G168&" ","")&IF(N(MOVIMIENTOS!$E168)>0,MOVIMIENTOS!$E168&" "&MOVIMIENTOS!$D168&" ","")&IF(MOVIMIENTOS!$H168<>"",MOVIMIENTOS!$H168,"")) -> TCK002-729 9 sacos | G99: =N(G98)+N(C99)-N(E99) -> 7200
A100: 46227 | B100: VENTA CHANCHO | F100: =TRIM(IF(MOVIMIENTOS!$G169<>"",MOVIMIENTOS!$G169&" ","")&IF(N(MOVIMIENTOS!$E169)>0,MOVIMIENTOS!$E169&" "&MOVIMIENTOS!$D169&" ","")&IF(MOVIMIENTOS!$H169<>"",MOVIMIENTOS!$H169,"")) -> 1 sacos No hicieron ticket | G100: =N(G99)+N(C100)-N(E100) -> 7200
A101: 46227 | B101: ENVÍO A TOTTUS | E101: =N(MOVIMIENTOS!$I170) -> 48 | G101: =N(G100)+N(C101)-N(E101) -> 7152
...

Sheet LISTAS
A1: Calidad | B1: Kg | D1: Tipos | F1: Calidades | H1: Unidades
A2: A | B2: 15 | D2: COMPRA | F2: A | H2: jabas
A3: P | B3: 18 | D3: PROCESO | F3: P | H3: sacos
A4: C | B4: 17 | D4: ENVÍO A SUPESA | F4: C | H4: kg
A5: M | B5: 17 | D5: ENVÍO A TOTTUS | F5: M
A6: Chancho | B6: 95 | D6: VENTA | F6: Chancho
D7: VENTA CHANCHO | F7: —
D8: REGALO | F8: Primera
A9: (Agrega aquí nuevas calidades con su factor kg por jaba para que los Kg salgan solos) | D9: RECHAZO | F9: Segunda
D10: REPROCESO
D11: DEVOLUCIÓN
D12: MALOGRADO
D13: OTRA SALIDA
D14: TRASIEGO
D15: AJUSTE
D16: SALDO INICIAL
